Workbook

Sheet Overview
A1: GLOBAL VTS | INVENTORY v0.3
A3: Version 0.3 | 29 September 2026 | Supersedes both v0.1 workbooks. Research counts, not a verified worldwide census.
A6: TSS SOURCE ENTRIES | E6: VTS SERVICE RECORDS | I6: REPORTING SCHEME RECORDS
A7: =COUNTA('TSS Candidates'!A7:A176) | E7: =COUNTA('VTS Services'!A7:A63) | I7: =COUNTA('Reporting Schemes'!A7:A33)
A11: DO NOT USE 170 AS THE WORLDWIDE TSS OR VTS TOTAL. The official baseline and later amendments remain unreconciled. Component, area and publication counts are still undetermined.
A15: RESEARCH PROGRESS | I15: COUNTING CHECKS
A16: Identification screening started | G16: =COUNTA('TSS Candidates'!A7:A176)-COUNTIF('TSS Candidates'!R7:R176,"Candidate recorded") | I16: Mandatory schemes | L16: =COUNTIF('Reporting Schemes'!D7:D33,"Mandatory for applicable vessels")
A17: Initial named associations evidenced | G17: =COUNTIF('TSS Candidates'!R7:R176,"Initial association evidenced") | I17: Voluntary schemes | L17: =COUNTIF('Reporting Schemes'!D7:D33,"Voluntary")
A18: Source records not yet screened | G18: =COUNTIF('TSS Candidates'!R7:R176,"Candidate recorded") | I18: Non-additive TSS children | L18: =COUNTA('TSS Components'!A7:A107)
A19: Fully audited operational records | G19: =COUNTIF('TSS Candidates'!R7:R176,"Fully audited")
A20: Five-record research batches | G20: =COUNTA('Batches'!A7:A40) | I20: NOT YET DETERMINED Worldwide TSS total Distinct VTS areas Guide entries and pages
A21: Open research issues | G21: =COUNTIF('Issues'!E7:E34,"Open")
A22: Sources and source leads | G22: =COUNTA('Sources'!A7:A142)
A25: AUDIT OUTCOME AND LIMITS
A27: v0.3 adds first-pass Stage 4 research for B10 to B34 (125 source rows): TSS identity, VTS and mandatory reporting findings, with primary sources.
A29: Merge audit downgraded one VTS finding and three 'Confirmed absent' findings, and reclassified VTS and port reporting duties under their services. See Stage 4 Findings and research/stage4/merge_log.md.
A31: Services and schemes marked Lead only are research leads and are excluded from counted totals. Unresolved never means absent.
A33: B01 to B09 remain at v0.2 screening level. The official baseline (Ships' Routeing 2025, UKHO Notice 17) is still unreconciled.
A35: Use Audit Findings for corrections, ID Crosswalk for old identifiers, and Legacy Links for the earlier relationship assertions.
A37: RESEARCH ONLY. No operational channels, reporting lines, coordinates or passage instructions are authorised by this workbook.
A40: STAGE 4 FIRST PASS: B10 TO B34
A41: Records researched | G41: =COUNTA('Stage 4 Findings'!A7:A131)
A42: TSS identity confirmed | G42: =COUNTIF('Stage 4 Findings'!G7:G131,"Confirmed")
A43: VTS: confirmed present | G43: =COUNTIF('Stage 4 Findings'!K7:K131,"Confirmed present")
A44: VTS: unresolved | G44: =COUNTIF('Stage 4 Findings'!K7:K131,"Unresolved")
A45: VTS: confirmed absent | G45: =COUNTIF('Stage 4 Findings'!K7:K131,"Confirmed absent")
A46: Mandatory reporting: confirmed present | G46: =COUNTIF('Stage 4 Findings'!N7:N131,"Confirmed present")
A47: Mandatory reporting: unresolved | G47: =COUNTIF('Stage 4 Findings'!N7:N131,"Unresolved")
A48: Mandatory reporting: confirmed absent | G48: =COUNTIF('Stage 4 Findings'!N7:N131,"Confirmed absent")
A49: Withdrawn or superseded | G49: =COUNTIF('Stage 4 Findings'!I7:I131,"Withdrawn/superseded")
A50: Counted VTS services in register (excludes leads) | G50: =COUNTA('VTS Services'!A7:A63)-COUNTIF('VTS Services'!F7:F63,"Stage 4 research lead (not counted)")

Sheet TSS Candidates
A1: TSS CANDIDATE INVENTORY
A3: Version 0.3 | 29 September 2026 | TSS Candidates. Reconciled register; see Audit Findings and Overview for limits.
A6: Record ID | B6: Region | C6: Candidate source label | D6: Record type | E6: Baseline status | F6: VTS screening | G6: Reporting screening | H6: Related service IDs | I6: Related reporting IDs | J6: Grouping / reconciliation note | K6: Source ID | L6: Source URL | M6: Source locator | N6: Source limitation | O6: Additional evidence IDs | P6: Additional evidence URLs | Q6: Batch | R6: Review stage | S6: Last record check
A7: TSS-0001 | B7: British Isles and southern North Sea | C7: In the approaches to the River Humber | D7: Source entry; component check pending | E7: Provisional: official baseline reconciliation pending | F7: Not researched | G7: Not researched | K7: SRC-001 | L7: https://www.scribd.com/document/1014775753/1-1-IMO-Adopted-Traffic-Separation-Schemes-on-the-ADMIRALTY-Chart-Series | M7: Notice 17; scheme label: In the approaches to the River Humber | N7: UKHO-labelled document on third-party host; edition and currency unverified. | Q7: B01 | R7: Candidate recorded | S7: Not established
A8: TSS-0002 | B8: British Isles and southern North Sea | C8: In the Sunk area and northern Approaches to the Thames Estuary | D8: Source entry; component check pending | E8: Provisional: official baseline reconciliation pending | F8: Not researched | G8: Not researched | K8: SRC-001 | L8: https://www.scribd.com/document/1014775753/1-1-IMO-Adopted-Traffic-Separation-Schemes-on-the-ADMIRALTY-Chart-Series | M8: Notice 17; scheme label: In the Sunk area and northern Approaches to the Thames Estuary | N8: UKHO-labelled document on third-party host; edition and currency unverified. | Q8: B01 | R8: Candidate recorded | S8: Not established
A9: TSS-0003 | B9: British Isles and southern North Sea | C9: In the Approaches to Hook of Holland and at North Hinder | D9: Source entry; component check pending | E9: Provisional: official baseline reconciliation pending | F9: Not researched | G9: Not researched | J9: Combined label. Check whether separate scheme records are required. | K9: SRC-001 | L9: https://www.scribd.com/document/1014775753/1-1-IMO-Adopted-Traffic-Separation-Schemes-on-the-ADMIRALTY-Chart-Series | M9: Notice 17; scheme label: In the Approaches to Hook of Holland and at North Hinder | N9: UKHO-labelled document on third-party host; edition and currency unverified. | Q9: B01 | R9: Candidate recorded | S9: Not established
A10: TSS-0004 | B10: British Isles and southern North Sea | C10: At West Hinder | D10: Source entry; component check pending | E10: Provisional: official baseline reconciliation pending | F10: Not researched | G10: Not researched | K10: SRC-001 | L10: https://www.scribd.com/document/1014775753/1-1-IMO-Adopted-Traffic-Separation-Schemes-on-the-ADMIRALTY-Chart-Series | M10: Notice 17; scheme label: At West Hinder | N10: UKHO-labelled document on third-party host; edition and currency unverified. | Q10: B01 | R10: Candidate recorded | S10: Not established
A11: TSS-0005 | B11: British Isles and southern North Sea | C11: In the Strait of Dover and adjacent waters | D11: Source entry; component check pending | E11: Provisional: official baseline reconciliation pending | F11: Authority evidence found | G11: Authority evidence found | H11: VTS-001 | I11: SRS-001 | K11: SRC-001 | L11: https://www.scribd.com/document/1014775753/1-1-IMO-Adopted-Traffic-Separation-Schemes-on-the-ADMIRALTY-Chart-Series | M11: Notice 17; scheme label: In the Strait of Dover and adjacent waters | N11: UKHO-labelled document on third-party host; edition and currency unverified. | O11: SRC-004; SRC-005 | P11: https://www.gov.uk/government/publications/dover-strait-crossings-channel-navigation-information-service/dover-strait-crossings-channel-navigation-information-service-cnis https://www.gov.uk/government/publications/mgn-364-mf-amendment-2-navigation-safety-traffic-separation-schemes-application-of-rule-10-and-navigation-in-the-dover-strait/mgn-364-mf-amendment-2-navigation-safety-traffic-separation-schemes-application-of-rule-10-and-navigation-in-the-dover-strait | Q11: B01 | R11: Initial association evidenced | S11: Identification screening only
A12: TSS-0006 | B12: British Isles and southern North Sea | C12: Off Casquets | D12: Source entry; component check pending | E12: Provisional: official baseline reconciliation pending | F12: Not researched | G12: Not researched | K12: SRC-001 | L12: https://www.scribd.com/document/1014775753/1-1-IMO-Adopted-Traffic-Separation-Schemes-on-the-ADMIRALTY-Chart-Series | M12: Notice 17; scheme label: Off Casquets | N12: UKHO-labelled document on third-party host; edition and currency unverified. | Q12: B02 | R12: Candidate recorded | S12: Not established
A13: TSS-0007 | B13: British Isles and southern North Sea | C13: Off Land's End, between Seven Stones and Longships | D13: Source entry; component check pending | E13: Provisional: official baseline reconciliation pending | F13: Not researched | G13: Not researched | K13: SRC-001 | L13: https://www.scribd.com/document/1014775753/1-1-IMO-Adopted-Traffic-Separation-Schemes-on-the-ADMIRALTY-Chart-Series | M13: Notice 17; scheme label: Off Land's End, between Seven Stones and Longships | N13: UKHO-labelled document on third-party host; edition and currency unverified. | Q13: B02 | R13: Candidate recorded | S13: Not established
A14: TSS-0008 | B14: British Isles and southern North Sea | C14: South of the Isles of Scilly | D14: Source entry; component check pending | E14: Provisional: official baseline reconciliation pending | F14: Not researched | G14: Not researched | K14: SRC-001 | L14: https://www.scribd.com/document/1014775753/1-1-IMO-Adopted-Traffic-Separation-Schemes-on-the-ADMIRALTY-Chart-Series | M14: Notice 17; scheme label: South of the Isles of Scilly | N14: UKHO-labelled document on third-party host; edition and currency unverified. | Q14: B02 | R14: Candidate recorded | S14: Not established
A15: TSS-0009 | B15: British Isles and southern North Sea | C15: West of the Isles of Scilly | D15: Source entry; component check pending | E15: Provisional: official baseline reconciliation pending | F15: Not researched | G15: Not researched | K15: SRC-001 | L15: https://www.scribd.com/document/1014775753/1-1-IMO-Adopted-Traffic-Separation-Schemes-on-the-ADMIRALTY-Chart-Series | M15: Notice 17; scheme label: West of the Isles of Scilly | N15: UKHO-labelled document on third-party host; edition and currency unverified. | Q15: B02 | R15: Candidate recorded | S15: Not established
A16: TSS-0010 | B16: British Isles and southern North Sea | C16: Off Fastnet Rock | D16: Source entry; component check pending | E16: Provisional: official baseline reconciliation pending | F16: Not researched | G16: Not researched | K16: SRC-001 | L16: https://www.scribd.com/document/1014775753/1-1-IMO-Adopted-Traffic-Separation-Schemes-on-the-ADMIRALTY-Chart-Series | M16: Notice 17; scheme label: Off Fastnet Rock | N16: UKHO-labelled document on third-party host; edition and currency unverified. | Q16: B02 | R16: Candidate recorded | S16: Not established
A17: TSS-0011 | B17: British Isles and southern North Sea | C17: Off Smalls | D17: Source entry; component check pending | E17: Provisional: official baseline reconciliation pending | F17: Not researched | G17: Not researched | K17: SRC-001 | L17: https://www.scribd.com/document/1014775753/1-1-IMO-Adopted-Traffic-Separation-Schemes-on-the-ADMIRALTY-Chart-Series | M17: Notice 17; scheme label: Off Smalls | N17: UKHO-labelled document on third-party host; edition and currency unverified. | Q17: B03 | R17: Candidate recorded | S17: Not established
A18: TSS-0012 | B18: British Isles and southern North Sea | C18: Off Tuskar Rock | D18: Source entry; component check pending | E18: Provisional: official baseline reconciliation pending | F18: Not researched | G18: Not researched | K18: SRC-001 | L18: https://www.scribd.com/document/1014775753/1-1-IMO-Adopted-Traffic-Separation-Schemes-on-the-ADMIRALTY-Chart-Series | M18: Notice 17; scheme label: Off Tuskar Rock | N18: UKHO-labelled document on third-party host; edition and currency unverified. | Q18: B03 | R18: Candidate recorded | S18: Not established
A19: TSS-0013 | B19: British Isles and southern North Sea | C19: Off Skerries | D19: Source entry; component check pending | E19: Provisional: official baseline reconciliation pending | F19: Not researched | G19: Not researched | K19: SRC-001 | L19: https://www.scribd.com/document/1014775753/1-1-IMO-Adopted-Traffic-Separation-Schemes-on-the-ADMIRALTY-Chart-Series | M19: Notice 17; scheme label: Off Skerries | N19: UKHO-labelled document on third-party host; edition and currency unverified. | Q19: B03 | R19: Candidate recorded | S19: Not established
A20: TSS-0014 | B20: British Isles and southern North Sea | C20: In Liverpool Bay | D20: Source entry; component check pending | E20: Provisional: official baseline reconciliation pending | F20: Not researched | G20: Not researched | K20: SRC-001 | L20: https://www.scribd.com/document/1014775753/1-1-IMO-Adopted-Traffic-Separation-Schemes-on-the-ADMIRALTY-Chart-Series | M20: Notice 17; scheme label: In Liverpool Bay | N20: UKHO-labelled document on third-party host; edition and currency unverified. | Q20: B03 | R20: Candidate recorded | S20: Not established
A21: TSS-0015 | B21: British Isles and southern North Sea | C21: In the North Channel | D21: Source entry; component check pending | E21: Provisional: official baseline reconciliation pending | F21: Not researched | G21: Not researched | K21: SRC-001 | L21: https://www.scribd.com/document/1014775753/1-1-IMO-Adopted-Traffic-Separation-Schemes-on-the-ADMIRALTY-Chart-Series | M21: Notice 17; scheme label: In the North Channel | N21: UKHO-labelled document on third-party host; edition and currency unverified. | Q21: B03 | R21: Candidate recorded | S21: Not established
A22: TSS-0016 | B22: British Isles and southern North Sea | C22: Off Neist Point | D22: Source entry; component check pending | E22: Provisional: official baseline reconciliation pending | F22: Not researched | G22: Not researched | K22: SRC-001 | L22: https://www.scribd.com/document/1014775753/1-1-IMO-Adopted-Traffic-Separation-Schemes-on-the-ADMIRALTY-Chart-Series | M22: Notice 17; scheme label: Off Neist Point | N22: UKHO-labelled document on third-party host; edition and currency unverified. | Q22: B04 | R22: Candidate recorded | S22: Not established
A23: TSS-0017 | B23: Norway and Iceland | C23: Off the coast of Norway | D23: Source entry; component check pending | E23: Provisional: official baseline reconciliation pending | F23: Not researched | G23: Not researched | J23: Grouped coastline label. Expand into named component schemes before counting. | K23: SRC-001 | L23: https://www.scribd.com/document/1014775753/1-1-IMO-Adopted-Traffic-Separation-Schemes-on-the-ADMIRALTY-Chart-Series | M23: Notice 17; scheme label: Off the coast of Norway | N23: UKHO-labelled document on third-party host; edition and currency unverified. | Q23: B04 | R23: Candidate recorded | S23: Not established
A24: TSS-0018 | B24: Norway and Iceland | C24: Off the south-west coast of Iceland: North-west of Garoskagi Point | D24: Source entry; component check pending | E24: Provisional: official baseline reconciliation pending | F24: Not researched | G24: Not researched | J24: Check official Icelandic spelling against the primary publication. | K24: SRC-001 | L24: https://www.scribd.com/document/1014775753/1-1-IMO-Adopted-Traffic-Separation-Schemes-on-the-ADMIRALTY-Chart-Series | M24: Notice 17; scheme label: Off the south-west coast of Iceland: North-west of Garoskagi Point | N24: UKHO-labelled document on third-party host; edition and currency unverified. | Q24: B04 | R24: Candidate recorded | S24: Not established
A25: TSS-0019 | B25: Norway and Iceland | C25: Off the south-west coast of Iceland: South-west of the Reykjanes Peninsula | D25: Source entry; component check pending | E25: Provisional: official baseline reconciliation pending | F25: Not researched | G25: Not researched | K25: SRC-001 | L25: https://www.scribd.com/document/1014775753/1-1-IMO-Adopted-Traffic-Separation-Schemes-on-the-ADMIRALTY-Chart-Series | M25: Notice 17; scheme label: Off the south-west coast of Iceland: South-west of the Reykjanes Peninsula | N25: UKHO-labelled document on third-party host; edition and currency unverified. | Q25: B04 | R25: Candidate recorded | S25: Not established
A26: TSS-0020 | B26: Baltic Sea and approaches | C26: The Åland Sea: North Åland Sea, South Åland Sea | D26: Source entry; component check pending | E26: Provisional: official baseline reconciliation pending | F26: Not researched | G26: Not researched | J26: Two named components appear within one source entry. Retain parent; reconcile component IDs. | K26: SRC-001 | L26: https://www.scribd.com/document/1014775753/1-1-IMO-Adopted-Traffic-Separation-Schemes-on-the-ADMIRALTY-Chart-Series | M26: Notice 17; scheme label: The Åland Sea: North Åland Sea, South Åland Sea | N26: UKHO-labelled document on third-party host; edition and currency unverified. | Q26: B04 | R26: Candidate recorded | S26: Not established
A27: TSS-0021 | B27: Baltic Sea and approaches | C27: Off Sommers Island (Ostrov Sommers) | D27: Source entry; component check pending | E27: Provisional: official baseline reconciliation pending | F27: Not researched | G27: Legacy GOFREP lead; direct association unverified | I27: SRS-006 | J27: Restored from the earlier v0.1 research leads. The checked Fintraffic pages do not identify this TSS by name. Direct authority/boundary verification is still required. | K27: SRC-001 | L27: https://www.scribd.com/document/1014775753/1-1-IMO-Adopted-Traffic-Separation-Schemes-on-the-ADMIRALTY-Chart-Series | M27: Notice 17; scheme label: Off Sommers Island (Ostrov Sommers) | N27: UKHO-labelled document on third-party host; edition and currency unverified. | O27: SRC-011; SRC-012 | P27: https://mastersguide.fintraffic.fi/en/gofrep-area https://www.fintraffic.fi/sv/node/254 | Q27: B05 | R27: Association proposed | S27: 2026-09-29
A28: TSS-0022 | B28: Baltic Sea and approaches | C28: Off Hogland (Gogland) Island (Ostrov Gogland) | D28: Source entry; component check pending | E28: Provisional: official baseline reconciliation pending | F28: Not researched | G28: Legacy GOFREP lead; direct association unverified | I28: SRS-006 | J28: Restored from the earlier v0.1 research leads. The checked Fintraffic pages do not identify this TSS by name. Direct authority/boundary verification is still required. | K28: SRC-001 | L28: https://www.scribd.com/document/1014775753/1-1-IMO-Adopted-Traffic-Separation-Schemes-on-the-ADMIRALTY-Chart-Series | M28: Notice 17; scheme label: Off Hogland (Gogland) Island (Ostrov Gogland) | N28: UKHO-labelled document on third-party host; edition and currency unverified. | O28: SRC-011; SRC-012 | P28: https://mastersguide.fintraffic.fi/en/gofrep-area https://www.fintraffic.fi/sv/node/254 | Q28: B05 | R28: Association proposed | S28: 2026-09-29
A29: TSS-0023 | B29: Baltic Sea and approaches | C29: Off Rodsher Island (Ostrov Rodsher) | D29: Source entry; component check pending | E29: Provisional: official baseline reconciliation pending | F29: Not researched | G29: Legacy GOFREP lead; direct association unverified | I29: SRS-006 | J29: Restored from the earlier v0.1 research leads. The checked Fintraffic pages do not identify this TSS by name. Direct authority/boundary verification is still required. | K29: SRC-001 | L29: https://www.scribd.com/document/1014775753/1-1-IMO-Adopted-Traffic-Separation-Schemes-on-the-ADMIRALTY-Chart-Series | M29: Notice 17; scheme label: Off Rodsher Island (Ostrov Rodsher) | N29: UKHO-labelled document on third-party host; edition and currency unverified. | O29: SRC-011; SRC-012 | P29: https://mastersguide.fintraffic.fi/en/gofrep-area https://www.fintraffic.fi/sv/node/254 | Q29: B05 | R29: Association proposed | S29: 2026-09-29
A30: TSS-0024 | B30: Baltic Sea and approaches | C30: Off Kalbådagrund Lighthouse | D30: Source entry; component check pending | E30: Provisional: official baseline reconciliation pending | F30: Not established by reporting source | G30: Authority evidence found | I30: SRS-006 | K30: SRC-001 | L30: https://www.scribd.com/document/1014775753/1-1-IMO-Adopted-Traffic-Separation-Schemes-on-the-ADMIRALTY-Chart-Series | M30: Notice 17; scheme label: Off Kalbådagrund Lighthouse | N30: UKHO-labelled document on third-party host; edition and currency unverified. | O30: SRC-011; SRC-012 | P30: https://mastersguide.fintraffic.fi/en/gofrep-area https://www.fintraffic.fi/sv/node/254 | Q30: B05 | R30: Initial association evidenced | S30: Identification screening only
A31: TSS-0025 | B31: Baltic Sea and approaches | C31: Off Porkkala Lighthouse | D31: Source entry; component check pending | E31: Provisional: official baseline reconciliation pending | F31: Not established by reporting source | G31: Authority evidence found | I31: SRS-006 | K31: SRC-001 | L31: https://www.scribd.com/document/1014775753/1-1-IMO-Adopted-Traffic-Separation-Schemes-on-the-ADMIRALTY-Chart-Series | M31: Notice 17; scheme label: Off Porkkala Lighthouse | N31: UKHO-labelled document on third-party host; edition and currency unverified. | O31: SRC-011; SRC-012 | P31: https://mastersguide.fintraffic.fi/en/gofrep-area https://www.fintraffic.fi/sv/node/254 | Q31: B05 | R31: Initial association evidenced | S31: Identification screening only
A32: TSS-0026 | B32: Baltic Sea and approaches | C32: Off Hankoniemi Peninsula (Hanko) | D32: Source entry; component check pending | E32: Provisional: official baseline reconciliation pending | F32: Not established by reporting source | G32: Authority evidence found | I32: SRS-006 | K32: SRC-001 | L32: https://www.scribd.com/document/1014775753/1-1-IMO-Adopted-Traffic-Separation-Schemes-on-the-ADMIRALTY-Chart-Series | M32: Notice 17; scheme label: Off Hankoniemi Peninsula (Hanko) | N32: UKHO-labelled document on third-party host; edition and currency unverified. | O32: SRC-011; SRC-012 | P32: https://mastersguide.fintraffic.fi/en/gofrep-area https://www.fintraffic.fi/sv/node/254 | Q32: B06 | R32: Initial association evidenced | S32: Identification screening only
A33: TSS-0027 | B33: Baltic Sea and approaches | C33: Off Köpu Peninsula (Hiiumaa Island) | D33: Source entry; component check pending | E33: Provisional: official baseline reconciliation pending | F33: Not established by reporting source | G33: Authority evidence found | I33: SRS-006 | K33: SRC-001 | L33: https://www.scribd.com/document/1014775753/1-1-IMO-Adopted-Traffic-Separation-Schemes-on-the-ADMIRALTY-Chart-Series | M33: Notice 17; scheme label: Off Köpu Peninsula (Hiiumaa Island) | N33: UKHO-labelled document on third-party host; edition and currency unverified. | O33: SRC-011; SRC-012 | P33: https://mastersguide.fintraffic.fi/en/gofrep-area https://www.fintraffic.fi/sv/node/254 | Q33: B06 | R33: Initial association evidenced | S33: Identification screening only
A34: TSS-0028 | B34: Baltic Sea and approaches | C34: North Hoburgs Bank | D34: Source entry; component check pending | E34: Provisional: official baseline reconciliation pending | F34: Not researched | G34: Not researched | K34: SRC-001 | L34: https://www.scribd.com/document/1014775753/1-1-IMO-Adopted-Traffic-Separation-Schemes-on-the-ADMIRALTY-Chart-Series | M34: Notice 17; scheme label: North Hoburgs Bank | N34: UKHO-labelled document on third-party host; edition and currency unverified. | Q34: B06 | R34: Candidate recorded | S34: Not established
A35: TSS-0029 | B35: Baltic Sea and approaches | C35: South Hoburgs Bank | D35: Source entry; component check pending | E35: Provisional: official baseline reconciliation pending | F35: Not researched | G35: Not researched | K35: SRC-001 | L35: https://www.scribd.com/document/1014775753/1-1-IMO-Adopted-Traffic-Separation-Schemes-on-the-ADMIRALTY-Chart-Series | M35: Notice 17; scheme label: South Hoburgs Bank | N35: UKHO-labelled document on third-party host; edition and currency unverified. | Q35: B06 | R35: Candidate recorded | S35: Not established
A36: TSS-0030 | B36: Baltic Sea and approaches | C36: West Klintehamn | D36: Source entry; component check pending | E36: Provisional: official baseline reconciliation pending | F36: Not researched | G36: Not researched | K36: SRC-001 | L36: https://www.scribd.com/document/1014775753/1-1-IMO-Adopted-Traffic-Separation-Schemes-on-the-ADMIRALTY-Chart-Series | M36: Notice 17; scheme label: West Klintehamn | N36: UKHO-labelled document on third-party host; edition and currency unverified. | Q36: B06 | R36: Candidate recorded | S36: Not established
A37: TSS-0031 | B37: Baltic Sea and approaches | C37: Midsjöbankarna | D37: Source entry; component check pending | E37: Provisional: official baseline reconciliation pending | F37: Not researched | G37: Not researched | K37: SRC-001 | L37: https://www.scribd.com/document/1014775753/1-1-IMO-Adopted-Traffic-Separation-Schemes-on-the-ADMIRALTY-Chart-Series | M37: Notice 17; scheme label: Midsjöbankarna | N37: UKHO-labelled document on third-party host; edition and currency unverified. | Q37: B07 | R37: Candidate recorded | S37: Not established
A38: TSS-0032 | B38: Baltic Sea and approaches | C38: Adlergrund | D38: Source entry; component check pending | E38: Provisional: official baseline reconciliation pending | F38: Not researched | G38: Not researched | K38: SRC-001 | L38: https://www.scribd.com/document/1014775753/1-1-IMO-Adopted-Traffic-Separation-Schemes-on-the-ADMIRALTY-Chart-Series | M38: Notice 17; scheme label: Adlergrund | N38: UKHO-labelled document on third-party host; edition and currency unverified. | Q38: B07 | R38: Candidate recorded | S38: Not established
A39: TSS-0033 | B39: Baltic Sea and approaches | C39: Slupska Bank | D39: Source entry; component check pending | E39: Provisional: official baseline reconciliation pending | F39: Not researched | G39: Not researched | J39: Check component names and amendments; do not assume this label represents one current scheme. | K39: SRC-001 | L39: https://www.scribd.com/document/1014775753/1-1-IMO-Adopted-Traffic-Separation-Schemes-on-the-ADMIRALTY-Chart-Series | M39: Notice 17; scheme label: Slupska Bank | N39: UKHO-labelled document on third-party host; edition and currency unverified. | Q39: B07 | R39: Candidate recorded | S39: Not established
A40: TSS-0034 | B40: Baltic Sea and approaches | C40: Off Öland Island | D40: Source entry; component check pending | E40: Provisional: official baseline reconciliation pending | F40: Not researched | G40: Not researched | K40: SRC-001 | L40: https://www.scribd.com/document/1014775753/1-1-IMO-Adopted-Traffic-Separation-Schemes-on-the-ADMIRALTY-Chart-Series | M40: Notice 17; scheme label: Off Öland Island | N40: UKHO-labelled document on third-party host; edition and currency unverified. | Q40: B07 | R40: Candidate recorded | S40: Not established
A41: TSS-0035 | B41: Baltic Sea and approaches | C41: In Bornholmsgat | D41: Source entry; component check pending | E41: Provisional: official baseline reconciliation pending | F41: Not researched | G41: Not researched | K41: SRC-001 | L41: https://www.scribd.com/document/1014775753/1-1-IMO-Adopted-Traffic-Separation-Schemes-on-the-ADMIRALTY-Chart-Series | M41: Notice 17; scheme label: In Bornholmsgat | N41: UKHO-labelled document on third-party host; edition and currency unverified. | Q41: B07 | R41: Candidate recorded | S41: Not established
A42: TSS-0036 | B42: Baltic Sea and approaches | C42: North of Rügen | D42: Source entry; component check pending | E42: Provisional: official baseline reconciliation pending | F42: Not researched | G42: Not researched | K42: SRC-001 | L42: https://www.scribd.com/document/1014775753/1-1-IMO-Adopted-Traffic-Separation-Schemes-on-the-ADMIRALTY-Chart-Series | M42: Notice 17; scheme label: North of Rügen | N42: UKHO-labelled document on third-party host; edition and currency unverified. | Q42: B08 | R42: Candidate recorded | S42: Not established
A43: TSS-0037 | B43: Baltic Sea and approaches | C43: South of Gedser | D43: Source entry; component check pending | E43: Provisional: official baseline reconciliation pending | F43: Not researched | G43: Not researched | K43: SRC-001 | L43: https://www.scribd.com/document/1014775753/1-1-IMO-Adopted-Traffic-Separation-Schemes-on-the-ADMIRALTY-Chart-Series | M43: Notice 17; scheme label: South of Gedser | N43: UKHO-labelled document on third-party host; edition and currency unverified. | Q43: B08 | R43: Candidate recorded | S43: Not established
A44: TSS-0038 | B44: Baltic Sea and approaches | C44: Between Korsoer and Sprogoe (Korsør and Sprogø) | D44: Source entry; component check pending | E44: Provisional: official baseline reconciliation pending | F44: Service association evidenced; boundary audit pending | G44: Mandatory scheme association evidenced; applicability audit pending | H44: VTS-002 | I44: SRS-002 | J44: MSC.332(90), annex 2.1–2.2 and 6.2–6.4, explicitly names the relevant TSS. Detailed chart and current rule reconciliation remain pending. | K44: SRC-001 | L44: https://www.scribd.com/document/1014775753/1-1-IMO-Adopted-Traffic-Separation-Schemes-on-the-ADMIRALTY-Chart-Series | M44: Notice 17; scheme label: Between Korsoer and Sprogoe (Korsør and Sprogø) | N44: UKHO-labelled document on third-party host; edition and currency unverified. | O44: SRC-008; SRC-015; SRC-020 | P44: https://www.forsvaret.dk/da/organisation/soevaernet/civile-opgaver/beltrep/ https://www.forsvaret.dk/da/organisation/soevaernet/nationalt-maritimt-operationscenter/vts/ https://wwwcdn.imo.org/localresources/en/KnowledgeCentre/IndexofIMOResolutions/MSCResolutions/MSC.332(90).pdf | Q44: B08 | R44: Initial association evidenced | S44: 2026-09-29
A45: TSS-0039 | B45: Baltic Sea and approaches | C45: At Hatter Barn | D45: Source entry; component check pending | E45: Provisional: official baseline reconciliation pending | F45: Service association evidenced; boundary audit pending | G45: Mandatory scheme association evidenced; applicability audit pending | H45: VTS-002 | I45: SRS-002 | J45: MSC.332(90), annex 2.1–2.2 and 6.2–6.4, explicitly names the relevant TSS. Detailed chart and current rule reconciliation remain pending. | K45: SRC-001 | L45: https://www.scribd.com/document/1014775753/1-1-IMO-Adopted-Traffic-Separation-Schemes-on-the-ADMIRALTY-Chart-Series | M45: Notice 17; scheme label: At Hatter Barn | N45: UKHO-labelled document on third-party host; edition and currency unverified. | O45: SRC-008; SRC-015; SRC-020 | P45: https://www.forsvaret.dk/da/organisation/soevaernet/civile-opgaver/beltrep/ https://www.forsvaret.dk/da/organisation/soevaernet/nationalt-maritimt-operationscenter/vts/ https://wwwcdn.imo.org/localresources/en/KnowledgeCentre/IndexofIMOResolutions/MSCResolutions/MSC.332(90).pdf | Q45: B08 | R45: Initial association evidenced | S45: 2026-09-29
A46: TSS-0040 | B46: Baltic Sea and approaches | C46: In The Sound | D46: Source entry; component check pending | E46: Provisional: official baseline reconciliation pending | F46: Service association evidenced; boundary audit pending | G46: Mandatory scheme association evidenced; applicability audit pending | H46: VTS-003 | I46: SRS-003 | J46: MSC.314(88), annex 6.2–6.3, names 'In the Sound' and 'Off Falsterbo'. Preserve the candidate label; formal alias reconciliation remains pending. | K46: SRC-001 | L46: https://www.scribd.com/document/1014775753/1-1-IMO-Adopted-Traffic-Separation-Schemes-on-the-ADMIRALTY-Chart-Series | M46: Notice 17; scheme label: In The Sound | N46: UKHO-labelled document on third-party host; edition and currency unverified. | O46: SRC-009; SRC-015; SRC-021 | P46: https://www.sjofartsverket.se/en/services/maritime-traffic-information/soundrep/soundrep-information/about-soundrep/ https://www.forsvaret.dk/da/organisation/soevaernet/nationalt-maritimt-operationscenter/vts/ https://www.sjofartsverket.se/globalassets/tjanster/sjotrafiktjanster/msc.31488.pdf | Q46: B08 | R46: Initial association evidenced | S46: 2026-09-29
A47: TSS-0041 | B47: Baltic Sea and approaches | C47: Off Falsterborev | D47: Source entry; component check pending | E47: Provisional: official baseline reconciliation pending | F47: Service association evidenced; boundary audit pending | G47: Mandatory scheme association evidenced; applicability audit pending | H47: VTS-003 | I47: SRS-003 | J47: MSC.314(88), annex 6.2–6.3, names 'In the Sound' and 'Off Falsterbo'. Preserve the candidate label; formal alias reconciliation remains pending. | K47: SRC-001 | L47: https://www.scribd.com/document/1014775753/1-1-IMO-Adopted-Traffic-Separation-Schemes-on-the-ADMIRALTY-Chart-Series | M47: Notice 17; scheme label: Off Falsterborev | N47: UKHO-labelled document on third-party host; edition and currency unverified. | O47: SRC-009; SRC-015; SRC-021 | P47: https://www.sjofartsverket.se/en/services/maritime-traffic-information/soundrep/soundrep-information/about-soundrep/ https://www.forsvaret.dk/da/organisation/soevaernet/nationalt-maritimt-operationscenter/vts/ https://www.sjofartsverket.se/globalassets/tjanster/sjotrafiktjanster/msc.31488.pdf | Q47: B09 | R47: Initial association evidenced | S47: 2026-09-29
A48: TSS-0042 | B48: Baltic Sea and approaches | C48: Off Kiel Lighthouse | D48: Source entry; component check pending | E48: Provisional: official baseline reconciliation pending | F48: Not researched | G48: Not researched | K48: SRC-001 | L48: https://www.scribd.com/document/1014775753/1-1-IMO-Adopted-Traffic-Separation-Schemes-on-the-ADMIRALTY-Chart-Series | M48: Notice 17; scheme label: Off Kiel Lighthouse | N48: UKHO-labelled document on third-party host; edition and currency unverified. | Q48: B09 | R48: Candidate recorded | S48: Not established
A49: TSS-0043 | B49: Baltic Sea and approaches | C49: Gulf of Gdansk | D49: Grouped source entry; two components identified | E49: Provisional: official baseline reconciliation pending | F49: Service association evidenced; boundary audit pending | G49: Mandatory scheme association evidenced; applicability audit pending | H49: VTS-015 | I49: SRS-007 | J49: Authority explicitly identifies TSS East and TSS West within VTS Zatoka Gdańska. Children retained in TSS Components, without changing the parent-row count. | K49: SRC-001 | L49: https://www.scribd.com/document/1014775753/1-1-IMO-Adopted-Traffic-Separation-Schemes-on-the-ADMIRALTY-Chart-Series | M49: Notice 17; scheme label: Gulf of Gdansk | N49: UKHO-labelled document on third-party host; edition and currency unverified. | O49: SRC-019; SRC-010 | P49: https://www.umgdy.gov.pl/en/marine-safety/vts-zatoka-gdanska-en/ https://www.transportstyrelsen.se/sv/sjofart/sjotrafik-och-hamnar/sjotrafikrapporteringssystem-srs/ | Q49: B09 | R49: Initial association evidenced | S49: 2026-09-29
A50: TSS-0044 | B50: Baltic Sea and approaches | C50: In Norra Kvarken | D50: Source entry; component check pending | E50: Provisional: official baseline reconciliation pending | F50: Not researched | G50: Not researched | K50: SRC-001 | L50: https://www.scribd.com/document/1014775753/1-1-IMO-Adopted-Traffic-Separation-Schemes-on-the-ADMIRALTY-Chart-Series | M50: Notice 17; scheme label: In Norra Kvarken | N50: UKHO-labelled document on third-party host; edition and currency unverified. | Q50: B09 | R50: Candidate recorded | S50: Not established
A51: TSS-0045 | B51: Baltic Sea and approaches | C51: In the vicinity of the Kattegat | D51: Source entry; component check pending | E51: Provisional: official baseline reconciliation pending | F51: Not researched | G51: Not researched | J51: Area-level label. Reconcile component schemes and 2020 routeing changes. | K51: SRC-001 | L51: https://www.scribd.com/document/1014775753/1-1-IMO-Adopted-Traffic-Separation-Schemes-on-the-ADMIRALTY-Chart-Series | M51: Notice 17; scheme label: In the vicinity of the Kattegat | N51: UKHO-labelled document on third-party host; edition and currency unverified. | Q51: B09 | R51: Candidate recorded | S51: Not established
A52: TSS-0046 | B52: North Sea continental coast | C52: German Bight Western Approach | D52: Source entry; single scheme on first-pass evidence | E52: TSS identity confirmed (first pass); operational status: In force. Official baseline reconciliation pending. | F52: Confirmed present: VTS-016 | G52: Unresolved | H52: VTS-016 | J52: Official name found: German Bight western approach. Named in IMO COLREG.2/Circ.59 (MSC 83, 2007) as amended scheme with special provisions for the North Hinder to German Bight tanker route, implemented 1 May 2008 (S1); listed in IMO Ships' Routeing 2008 (S27) and Transportstyrelsen 2017 list (S4). German statute designates it a deep-water route (Tiefwasserweg) mandatory for large tankers (S6 Nr. 6). MSC 109 adopted a revised containership recommendation covering it from 1 July 2025 (lead S5). No evidence of renaming or restructuring by recent IMO amendments was found. | K52: SRC-001 | L52: https://www.scribd.com/document/1014775753/1-1-IMO-Adopted-Traffic-Separation-Schemes-on-the-ADMIRALTY-Chart-Series | M52: Notice 17; scheme label: German Bight Western Approach | N52: UKHO-labelled document on third-party host; edition and currency unverified. | O52: SRC-024; SRC-027; SRC-028; SRC-029; SRC-031; SRC-033; SRC-034; SRC-050 | P52: https://cimrc.shmtu.edu.cn/_upload/article/files/63/dc/35c66be74d12873254dc88a2ef00/465d5392-0ba5-4f33-8e61-a48e3499b1b3.pdf https://transportstyrelsen.se/globalassets/global/sjofart/dokument/sjotrafik_dok/ruttsystem.pdf https://www.isesassociation.com/wp-content/uploads/2024/12/MSC_109_Summary_Report.pdf https://www.gesetze-im-internet.de/anlbv_2004/anlage.html https://www.wsa-weser-jade-nordsee.wsv.de/Webs/WSA/Weser-Jade-Nordsee/DE/Schifffahrt/Verkehrszentralen/verkehrsundrevierzentralen_node.html https://www.elwis.de/DE/Seeschifffahrt/Verkehrs-und-Sicherheitsmanagement/Verkehrszentralen/Verkehrskanaele.pdf?__blob=publicationFile https://epflicht.ulb.uni-bonn.de/download/pdf/564811 https://www.fpp.uni-lj.si/mma_bin.php?id=2011032217361737 | Q52: B10 | R52: Initial association evidenced | S52: 2026-09-29
A53: TSS-0047 | B53: North Sea continental coast | C53: Elbe Approach | D53: Source entry; single scheme on first-pass evidence | E53: TSS identity confirmed (first pass); operational status: In force. Official baseline reconciliation pending. | F53: Confirmed present: VTS-018, VTS-016 | G53: Unresolved | H53: VTS-018; VTS-016 | J53: Official name found: Elbe approach. Listed as 'Elbe approach' in IMO Ships' Routeing 2008 (S27) and the Transportstyrelsen 2017 list of IMO schemes (S4). Adopting and latest amending circular not retrieved. | K53: SRC-001 | L53: https://www.scribd.com/document/1014775753/1-1-IMO-Adopted-Traffic-Separation-Schemes-on-the-ADMIRALTY-Chart-Series | M53: Notice 17; scheme label: Elbe Approach | N53: UKHO-labelled document on third-party host; edition and currency unverified. | O53: SRC-027; SRC-029; SRC-030; SRC-032; SRC-033; SRC-050 | P53: https://transportstyrelsen.se/globalassets/global/sjofart/dokument/sjotrafik_dok/ruttsystem.pdf https://www.gesetze-im-internet.de/anlbv_2004/anlage.html https://www.elwis.de/DE/Schifffahrtsrecht/Seeschifffahrtsrecht/SeeSchStrO/Achter-Abschnitt/58/58-node.html https://www.wsa-elbe-nordsee.wsv.de/Webs/WSA/Elbe-Nordsee/DE/2_Schifffahrt/4_Verkehrszentralen/2_Cuxhaven/Cuxhaven_node.html https://www.elwis.de/DE/Seeschifffahrt/Verkehrs-und-Sicherheitsmanagement/Verkehrszentralen/Verkehrskanaele.pdf?__blob=publicationFile https://www.fpp.uni-lj.si/mma_bin.php?id=2011032217361737 | Q53: B10 | R53: Initial association evidenced | S53: 2026-09-29
A54: TSS-0048 | B54: North Sea continental coast | C54: Jade Approach | D54: Source entry; single scheme on first-pass evidence | E54: TSS identity confirmed (first pass); operational status: In force. Official baseline reconciliation pending. | F54: Confirmed present: VTS-016 | G54: Unresolved | H54: VTS-016 | J54: Official name found: Jade approach. Listed as 'Jade approach' in IMO Ships' Routeing 2008 (S27) and Transportstyrelsen 2017 list (S4). WSV describes it as the link between Terschelling-German Bight and the Western Approach giving access to Weser and Jade from the north (S11). German statute places a pilot transfer position 'im Verkehrstrennungsgebiet Jade Approach' within the Inner German Bight (S6 Nr. 8). | K54: SRC-001 | L54: https://www.scribd.com/document/1014775753/1-1-IMO-Adopted-Traffic-Separation-Schemes-on-the-ADMIRALTY-Chart-Series | M54: Notice 17; scheme label: Jade Approach | N54: UKHO-labelled document on third-party host; edition and currency unverified. | O54: SRC-027; SRC-029; SRC-030; SRC-031; SRC-034; SRC-050 | P54: https://transportstyrelsen.se/globalassets/global/sjofart/dokument/sjotrafik_dok/ruttsystem.pdf https://www.gesetze-im-internet.de/anlbv_2004/anlage.html https://www.elwis.de/DE/Schifffahrtsrecht/Seeschifffahrtsrecht/SeeSchStrO/Achter-Abschnitt/58/58-node.html https://www.wsa-weser-jade-nordsee.wsv.de/Webs/WSA/Weser-Jade-Nordsee/DE/Schifffahrt/Verkehrszentralen/verkehrsundrevierzentralen_node.html https://epflicht.ulb.uni-bonn.de/download/pdf/564811 https://www.fpp.uni-lj.si/mma_bin.php?id=2011032217361737 | Q54: B10 | R54: Initial association evidenced | S54: 2026-09-29
A55: TSS-0049 | B55: North Sea continental coast | C55: Terschelling - German Bight | D55: Source entry; single scheme on first-pass evidence | E55: TSS identity confirmed (first pass); operational status: In force. Official baseline reconciliation pending. | F55: Confirmed present: VTS-016 | G55: Unresolved | H55: VTS-016 | J55: Official name found: Terschelling-German Bight. Amended by COLREG.2/Circ.59 (MSC 83, implemented 1 May 2008) (S1); listed in Ships' Routeing 2008 (S27) and Transportstyrelsen 2017 list (S4). MSC 109 containership recommendation from 1 July 2025 (lead S5). | K55: SRC-001 | L55: https://www.scribd.com/document/1014775753/1-1-IMO-Adopted-Traffic-Separation-Schemes-on-the-ADMIRALTY-Chart-Series | M55: Notice 17; scheme label: Terschelling - German Bight | N55: UKHO-labelled document on third-party host; edition and currency unverified. | O55: SRC-024; SRC-027; SRC-028; SRC-029; SRC-030; SRC-031; SRC-034; SRC-036; SRC-037; SRC-038; SRC-050 | P55: https://cimrc.shmtu.edu.cn/_upload/article/files/63/dc/35c66be74d12873254dc88a2ef00/465d5392-0ba5-4f33-8e61-a48e3499b1b3.pdf https://transportstyrelsen.se/globalassets/global/sjofart/dokument/sjotrafik_dok/ruttsystem.pdf https://www.isesassociation.com/wp-content/uploads/2024/12/MSC_109_Summary_Report.pdf https://www.gesetze-im-internet.de/anlbv_2004/anlage.html https://www.elwis.de/DE/Schifffahrtsrecht/Seeschifffahrtsrecht/SeeSchStrO/Achter-Abschnitt/58/58-node.html https://www.wsa-weser-jade-nordsee.wsv.de/Webs/WSA/Weser-Jade-Nordsee/DE/Schifffahrt/Verkehrszentralen/verkehrsundrevierzentralen_node.html https://epflicht.ulb.uni-bonn.de/download/pdf/564811 https://kustwacht.nl/en/merchant-shipping/advice-for-container-ships-near-west-frisian-islands/ https://kustwacht.nl/hulpverlening/vtm/ https://kustwacht.nl/maritieme-organisaties/verkeerscentrales/ https://www.fpp.uni-lj.si/mma_bin.php?id=2011032217361737 | Q55: B10 | R55: Initial association evidenced | S55: 2026-09-29
A56: TSS-0050 | B56: North Sea continental coast | C56: Vlieland North | D56: Source entry; 3 parts recorded (structure only, not a scheme count) | E56: TSS identity confirmed (first pass); operational status: In force. Official baseline reconciliation pending. | F56: Unresolved | G56: Unresolved | J56: Official name found: Vlieland North (part of 'Off Vlieland, Vlieland North and Vlieland Junction'). COLREG.2/Circ.59 (MSC 83, implemented 1 May 2008) amended the special provisions of 'Off Vlieland, Vlieland North and Vlieland Junction' (S1). IMO Ships' Routeing 2008 treats these as one routeing system entry (S27). Component of the same system as TSS-0051. | K56: SRC-001 | L56: https://www.scribd.com/document/1014775753/1-1-IMO-Adopted-Traffic-Separation-Schemes-on-the-ADMIRALTY-Chart-Series | M56: Notice 17; scheme label: Vlieland North | N56: UKHO-labelled document on third-party host; edition and currency unverified. | O56: SRC-024; SRC-027; SRC-036; SRC-037; SRC-038; SRC-050 | P56: https://cimrc.shmtu.edu.cn/_upload/article/files/63/dc/35c66be74d12873254dc88a2ef00/465d5392-0ba5-4f33-8e61-a48e3499b1b3.pdf https://transportstyrelsen.se/globalassets/global/sjofart/dokument/sjotrafik_dok/ruttsystem.pdf https://kustwacht.nl/en/merchant-shipping/advice-for-container-ships-near-west-frisian-islands/ https://kustwacht.nl/hulpverlening/vtm/ https://kustwacht.nl/maritieme-organisaties/verkeerscentrales/ https://www.fpp.uni-lj.si/mma_bin.php?id=2011032217361737 | Q56: B10 | R56: Researched; unresolved | S56: 2026-09-29
A57: TSS-0051 | B57: North Sea continental coast | C57: Off Vlieland | D57: Source entry; 3 parts recorded (structure only, not a scheme count) | E57: TSS identity confirmed (first pass); operational status: In force. Official baseline reconciliation pending. | F57: Unresolved | G57: Unresolved | J57: Official name found: Off Vlieland (part of 'Off Vlieland, Vlieland North and Vlieland Junction'). As TSS-0050: amended by COLREG.2/Circ.59, implemented 1 May 2008 (S1); single entry in Ships' Routeing 2008 (S27). MSC 109 containership recommendation covers 'Off Vlieland' from 1 July 2025 (lead S5). | K57: SRC-001 | L57: https://www.scribd.com/document/1014775753/1-1-IMO-Adopted-Traffic-Separation-Schemes-on-the-ADMIRALTY-Chart-Series | M57: Notice 17; scheme label: Off Vlieland | N57: UKHO-labelled document on third-party host; edition and currency unverified. | O57: SRC-024; SRC-027; SRC-028; SRC-036; SRC-037; SRC-038; SRC-050 | P57: https://cimrc.shmtu.edu.cn/_upload/article/files/63/dc/35c66be74d12873254dc88a2ef00/465d5392-0ba5-4f33-8e61-a48e3499b1b3.pdf https://transportstyrelsen.se/globalassets/global/sjofart/dokument/sjotrafik_dok/ruttsystem.pdf https://www.isesassociation.com/wp-content/uploads/2024/12/MSC_109_Summary_Report.pdf https://kustwacht.nl/en/merchant-shipping/advice-for-container-ships-near-west-frisian-islands/ https://kustwacht.nl/hulpverlening/vtm/ https://kustwacht.nl/maritieme-organisaties/verkeerscentrales/ https://www.fpp.uni-lj.si/mma_bin.php?id=2011032217361737 | Q57: B11 | R57: Researched; unresolved | S57: 2026-09-29
A58: TSS-0052 | B58: North Sea continental coast | C58: Off Texel | D58: Source entry; single scheme on first-pass evidence | E58: TSS identity confirmed (first pass); operational status: In force. Official baseline reconciliation pending. | F58: Unresolved | G58: Unresolved | J58: Amended by COLREG.2/Circ.59 (implemented 1 May 2008) (S1); further amended by COLREG.2/Circ.64 (MSC 91, 2012), implemented 1 August 2013, per the Transportstyrelsen list (S4); Circ.64 text itself not retrieved. | K58: SRC-001 | L58: https://www.scribd.com/document/1014775753/1-1-IMO-Adopted-Traffic-Separation-Schemes-on-the-ADMIRALTY-Chart-Series | M58: Notice 17; scheme label: Off Texel | N58: UKHO-labelled document on third-party host; edition and currency unverified. | O58: SRC-024; SRC-027; SRC-037; SRC-038 | P58: https://cimrc.shmtu.edu.cn/_upload/article/files/63/dc/35c66be74d12873254dc88a2ef00/465d5392-0ba5-4f33-8e61-a48e3499b1b3.pdf https://transportstyrelsen.se/globalassets/global/sjofart/dokument/sjotrafik_dok/ruttsystem.pdf https://kustwacht.nl/hulpverlening/vtm/ https://kustwacht.nl/maritieme-organisaties/verkeerscentrales/ | Q58: B11 | R58: Researched; unresolved | S58: 2026-09-29
A59: TSS-0053 | B59: North Sea continental coast | C59: In the Approaches to IJmuiden | D59: Source entry; single scheme on first-pass evidence | E59: TSS identity confirmed (first pass); operational status: In force. Official baseline reconciliation pending. | F59: Unresolved (lead: VTS-019) | G59: Unresolved | J59: Official name found: In the approaches to IJmuiden. New scheme adopted by MSC 91 and circulated as COLREG.2/Circ.64 (2012), implemented 1 August 2013, per Transportstyrelsen list (S4); associated precautionary areas in SN.1/Circ.317 (S4). Separate IMO deep-water route leading to IJmuiden listed in Ships' Routeing 2008 (S27). Circ.64 text not retrieved. | K59: SRC-001 | L59: https://www.scribd.com/document/1014775753/1-1-IMO-Adopted-Traffic-Separation-Schemes-on-the-ADMIRALTY-Chart-Series | M59: Notice 17; scheme label: In the Approaches to IJmuiden | N59: UKHO-labelled document on third-party host; edition and currency unverified. | O59: SRC-027; SRC-035; SRC-050 | P59: https://transportstyrelsen.se/globalassets/global/sjofart/dokument/sjotrafik_dok/ruttsystem.pdf https://www.portofamsterdam.com/sites/default/files/2025-09/2025-479_VTS%20communicatieregeling%202.0%20def_NLEN_rev.pdf https://www.fpp.uni-lj.si/mma_bin.php?id=2011032217361737 | Q59: B11 | R59: Association proposed | S59: 2026-09-29
A60: TSS-0054 | B60: North Sea continental coast | C60: Off Brown Ridge | D60: Source entry; single scheme on first-pass evidence | E60: TSS identity provisional (first pass); operational status: Not established. Official baseline reconciliation pending. | F60: Unresolved | G60: Unresolved | J60: Existence of a TSS 'Off Brown Ridge' is indicated only by leads: Wikipedia list 'Brown Ridge' (S30) and search snippets describing a deep-water route linking TSS Off Brown Ridge to TSS West Friesland and the 1 August 2013 Dutch re-routeing. Not found in Ships' Routeing 2008 contents (S27) or Transportstyrelsen 2017 list (S4) as a separate entry; may be a component of 'Off Friesland' or of the 2013 Dutch routeing package. Adopting instrument not retrieved. | K60: SRC-001 | L60: https://www.scribd.com/document/1014775753/1-1-IMO-Adopted-Traffic-Separation-Schemes-on-the-ADMIRALTY-Chart-Series | M60: Notice 17; scheme label: Off Brown Ridge | N60: UKHO-labelled document on third-party host; edition and currency unverified. | O60: SRC-027; SRC-050; SRC-053 | P60: https://transportstyrelsen.se/globalassets/global/sjofart/dokument/sjotrafik_dok/ruttsystem.pdf https://www.fpp.uni-lj.si/mma_bin.php?id=2011032217361737 https://en.wikipedia.org/wiki/List_of_traffic_separation_schemes | Q60: B11 | R60: Researched; unresolved | S60: 2026-09-29
A61: TSS-0055 | B61: North Sea continental coast | C61: West Friesland | D61: Source entry; 5 parts recorded (structure only, not a scheme count) | E61: TSS identity confirmed (first pass); operational status: In force. Official baseline reconciliation pending. | F61: Unresolved | G61: Unresolved | J61: Official name found: West Friesland scheme (part of routeing system 'Off Friesland'). Component of the 'Off Friesland' routeing system; amended by COLREG.2/Circ.66 (MSC 94, 21 November 2014), implemented 1 June 2015 (S2), corrected by COLREG.2/Circ.66/Corr.1 (MSC 96, 2016, immediate effect) (S3). MSC 109 containership recommendation covers 'Off Friesland' from 1 July 2025 (lead S5). | K61: SRC-001 | L61: https://www.scribd.com/document/1014775753/1-1-IMO-Adopted-Traffic-Separation-Schemes-on-the-ADMIRALTY-Chart-Series | M61: Notice 17; scheme label: West Friesland | N61: UKHO-labelled document on third-party host; edition and currency unverified. | O61: SRC-024; SRC-025; SRC-026; SRC-028; SRC-037; SRC-038 | P61: https://cimrc.shmtu.edu.cn/_upload/article/files/63/dc/35c66be74d12873254dc88a2ef00/465d5392-0ba5-4f33-8e61-a48e3499b1b3.pdf https://www.vimawa.gov.vn/f/Circ%2066.pdf https://mindev.gov.ua/storage/app/sites/1/uploaded-files/colreg2-circ66-corr1-corrigendum-secretariat.pdf https://www.isesassociation.com/wp-content/uploads/2024/12/MSC_109_Summary_Report.pdf https://kustwacht.nl/hulpverlening/vtm/ https://kustwacht.nl/maritieme-organisaties/verkeerscentrales/ | Q61: B11 | R61: Researched; unresolved | S61: 2026-09-29
A62: TSS-0056 | B62: North Sea continental coast | C62: North Friesland | D62: Source entry; 3 parts recorded (structure only, not a scheme count) | E62: TSS identity confirmed (first pass); operational status: In force. Official baseline reconciliation pending. | F62: Unresolved | G62: Unresolved | J62: Official name found: North Friesland scheme (part of routeing system 'Off Friesland'). Established within 'Off Friesland' by COLREG.2/Circ.66 (implemented 1 June 2015), with separation zones around 54° 00' to 54° 05' N, 004° 40' to 005° 06' E (S2, S3). Dutch offshore scheme, not the German North Frisian coast. Lead (search summary) says it replaced the Friesland Junction precautionary area; not verified in retrieved text. | K62: SRC-001 | L62: https://www.scribd.com/document/1014775753/1-1-IMO-Adopted-Traffic-Separation-Schemes-on-the-ADMIRALTY-Chart-Series | M62: Notice 17; scheme label: North Friesland | N62: UKHO-labelled document on third-party host; edition and currency unverified. | O62: SRC-025; SRC-026; SRC-037; SRC-038 | P62: https://www.vimawa.gov.vn/f/Circ%2066.pdf https://mindev.gov.ua/storage/app/sites/1/uploaded-files/colreg2-circ66-corr1-corrigendum-secretariat.pdf https://kustwacht.nl/hulpverlening/vtm/ https://kustwacht.nl/maritieme-organisaties/verkeerscentrales/ | Q62: B12 | R62: Researched; unresolved | S62: 2026-09-29
A63: TSS-0057 | B63: North Sea continental coast | C63: East Friesland | D63: Source entry; 3 parts recorded (structure only, not a scheme count) | E63: TSS identity confirmed (first pass); operational status: In force. Official baseline reconciliation pending. | F63: Unresolved | G63: Unresolved | J63: Official name found: East Friesland scheme (part of routeing system 'Off Friesland'). Amended within 'Off Friesland' by COLREG.2/Circ.66 (implemented 1 June 2015) and Corr.1 (2016) (S2, S3). Dutch offshore scheme around 54° 02' to 54° 06' N, 005° 08' to 005° 10' E at its western boundary; not the German East Frisian coast. | K63: SRC-001 | L63: https://www.scribd.com/document/1014775753/1-1-IMO-Adopted-Traffic-Separation-Schemes-on-the-ADMIRALTY-Chart-Series | M63: Notice 17; scheme label: East Friesland | N63: UKHO-labelled document on third-party host; edition and currency unverified. | O63: SRC-025; SRC-026; SRC-037; SRC-038 | P63: https://www.vimawa.gov.vn/f/Circ%2066.pdf https://mindev.gov.ua/storage/app/sites/1/uploaded-files/colreg2-circ66-corr1-corrigendum-secretariat.pdf https://kustwacht.nl/hulpverlening/vtm/ https://kustwacht.nl/maritieme-organisaties/verkeerscentrales/ | Q63: B12 | R63: Researched; unresolved | S63: 2026-09-29
A64: TSS-0058 | B64: North Sea continental coast | C64: Off Botney Ground | D64: Source entry; single scheme on first-pass evidence | E64: TSS identity confirmed (first pass); operational status: In force. Official baseline reconciliation pending. | F64: Unresolved | G64: Unresolved | J64: Official name found: Off Botney Ground (part of western route of routeing system 'Off Friesland'). COLREG.2/Circ.59 names 'TSS Off Botney Ground' as part of the alternative western route of the routeing system 'Off Friesland' for deep-draught tankers (S1). Not a separate entry in Ships' Routeing 2008 contents (S27). Currency after 2015 not separately verified. | K64: SRC-001 | L64: https://www.scribd.com/document/1014775753/1-1-IMO-Adopted-Traffic-Separation-Schemes-on-the-ADMIRALTY-Chart-Series | M64: Notice 17; scheme label: Off Botney Ground | N64: UKHO-labelled document on third-party host; edition and currency unverified. | O64: SRC-024; SRC-050; SRC-053 | P64: https://cimrc.shmtu.edu.cn/_upload/article/files/63/dc/35c66be74d12873254dc88a2ef00/465d5392-0ba5-4f33-8e61-a48e3499b1b3.pdf https://www.fpp.uni-lj.si/mma_bin.php?id=2011032217361737 https://en.wikipedia.org/wiki/List_of_traffic_separation_schemes | Q64: B12 | R64: Researched; unresolved | S64: 2026-09-29
A65: TSS-0059 | B65: France, Iberia and Canary Islands | C65: Off Ushant (Île d'Ouessant) | D65: Source entry; single scheme on first-pass evidence | E65: TSS identity confirmed (first pass); operational status: In force. Official baseline reconciliation pending. | F65: Confirmed present: VTS-021 | G65: Confirmed present: SRS-009 | H65: VTS-021 | I65: SRS-009 | J65: Official name found: Off Ushant. Amended by COLREG.2/Circ.51 (MSC 75), implemented 1 May 2003 (S18); further amended by COLREG.2/Circ.64 (MSC 91), implemented 1 June 2013 per search result (Circ.64 text not retrieved). French ministry 2024 confirms DST Ouessant under CROSS Corsen (S19). | K65: SRC-001 | L65: https://www.scribd.com/document/1014775753/1-1-IMO-Adopted-Traffic-Separation-Schemes-on-the-ADMIRALTY-Chart-Series | M65: Notice 17; scheme label: Off Ushant (Île d'Ouessant) | N65: UKHO-labelled document on third-party host; edition and currency unverified. | O65: SRC-039; SRC-040; SRC-041; SRC-042 | P65: https://wwwcdn.imo.org/localresources/en/KnowledgeCentre/IndexofIMOResolutions/MSCResolutions/MSC.52(66).pdf https://wwwcdn.imo.org/localresources/en/KnowledgeCentre/IndexofIMOResolutions/MSCResolutions/MSC.251(83).pdf https://cimrc.shmtu.edu.cn/_upload/article/files/63/dc/35c66be74d12873254dc88a2ef00/a4f3f58b-c400-41cb-858b-89dccee63151.pdf https://www.statistiques.developpement-durable.gouv.fr/edition-numerique/chiffres-cles-mer-littoral/18-surveillance-de-la-navigation-maritime | Q65: B12 | R65: Initial association evidenced | S65: 2026-09-29
A66: TSS-0060 | B66: France, Iberia and Canary Islands | C66: Off Finisterre | D66: Source entry; single scheme on first-pass evidence | E66: TSS identity confirmed (first pass); operational status: In force. Official baseline reconciliation pending. | F66: Confirmed present: VTS-022 | G66: Confirmed present: SRS-010 | H66: VTS-022 | I66: SRS-010 | J66: Originally adopted by A.767(18) (cited in S20); amended by A.957(23), implemented 1 June 2004, adding lanes for ships carrying dangerous or pollutant cargoes in bulk (S21). Listed in Ships' Routeing 2008 (S27). | K66: SRC-001 | L66: https://www.scribd.com/document/1014775753/1-1-IMO-Adopted-Traffic-Separation-Schemes-on-the-ADMIRALTY-Chart-Series | M66: Notice 17; scheme label: Off Finisterre | N66: UKHO-labelled document on third-party host; edition and currency unverified. | O66: SRC-043; SRC-044; SRC-045; SRC-050 | P66: https://wwwcdn.imo.org/localresources/en/KnowledgeCentre/IndexofIMOResolutions/MSCResolutions/MSC.63(67).pdf https://wwwcdn.imo.org/localresources/en/KnowledgeCentre/IndexofIMOResolutions/AssemblyDocuments/A.957(23).pdf https://metropolitano.gal/extra/el-centro-de-coordinacion-de-salvamento-maritimo-de-vigo-rescato-a-316-personas-en-el-2024 https://www.fpp.uni-lj.si/mma_bin.php?id=2011032217361737 | Q66: B12 | R66: Initial association evidenced | S66: 2026-09-29
A67: TSS-0061 | B67: France, Iberia and Canary Islands | C67: Off Cape Roca (Cabo da Roca) | D67: Source entry; single scheme on first-pass evidence | E67: TSS identity confirmed (first pass); operational status: In force. Official baseline reconciliation pending. | F67: Confirmed present: VTS-023 | G67: Confirmed present: SRS-011 | H67: VTS-023 | I67: SRS-011 | J67: Official name found: Off Cape Roca. Amended by MSC 79 (December 2004) with entry into force 1 July 2005 (S23 preamble) and again by COLREG.2/Circ.61 (MSC 87), implemented 1 December 2010 (S26). Established in Portuguese law as 'EST do cabo da Roca' (S23 art. 4). | K67: SRC-001 | L67: https://www.scribd.com/document/1014775753/1-1-IMO-Adopted-Traffic-Separation-Schemes-on-the-ADMIRALTY-Chart-Series | M67: Notice 17; scheme label: Off Cape Roca (Cabo da Roca) | N67: UKHO-labelled document on third-party host; edition and currency unverified. | O67: SRC-046; SRC-047; SRC-048; SRC-049 | P67: https://www.marinha.pt/Conteudos_Externos/LexMar2/PGPAT%20100/PGPAT%201000%20-%20Cap%C3%ADtulos/Capitulo%20K%20EST/Decreto-Lei%20198-2006%20(19OUT2006).pdf https://www.marinha.pt/Conteudos_Externos/LexMar2/PGPAT%20100/PGPAT%201000%20-%20Cap%C3%ADtulos/Capitulo%20K%20EST/Dec.%20Lei%20263_2009,%20de%2028Set.pdf https://wwwcdn.imo.org/localresources/en/KnowledgeCentre/IndexofIMOResolutions/MSCResolutions/MSC.278(85).pdf https://cimrc.shmtu.edu.cn/_upload/article/files/63/dc/35c66be74d12873254dc88a2ef00/25e2ceb4-d2d9-4cf2-b55b-cdb3d56001b5.pdf | Q67: B13 | R67: Initial association evidenced | S67: 2026-09-29
A68: TSS-0062 | B68: France, Iberia and Canary Islands | C68: Off Cape St. Vicente (Cabo de São Vicente) | D68: Source entry; single scheme on first-pass evidence | E68: TSS identity confirmed (first pass); operational status: In force. Official baseline reconciliation pending. | F68: Confirmed present: VTS-023 | G68: Confirmed present: SRS-011 | H68: VTS-023 | I68: SRS-011 | J68: Official name found: Off Cape S. Vicente. Amended by MSC 79 (in force 1 July 2005) (S23 preamble) and COLREG.2/Circ.61, implemented 1 December 2010 (S26). 'EST do cabo de São Vicente' in Portuguese law (S23 art. 4). | K68: SRC-001 | L68: https://www.scribd.com/document/1014775753/1-1-IMO-Adopted-Traffic-Separation-Schemes-on-the-ADMIRALTY-Chart-Series | M68: Notice 17; scheme label: Off Cape St. Vicente (Cabo de São Vicente) | N68: UKHO-labelled document on third-party host; edition and currency unverified. | O68: SRC-046; SRC-047; SRC-048; SRC-049 | P68: https://www.marinha.pt/Conteudos_Externos/LexMar2/PGPAT%20100/PGPAT%201000%20-%20Cap%C3%ADtulos/Capitulo%20K%20EST/Decreto-Lei%20198-2006%20(19OUT2006).pdf https://www.marinha.pt/Conteudos_Externos/LexMar2/PGPAT%20100/PGPAT%201000%20-%20Cap%C3%ADtulos/Capitulo%20K%20EST/Dec.%20Lei%20263_2009,%20de%2028Set.pdf https://wwwcdn.imo.org/localresources/en/KnowledgeCentre/IndexofIMOResolutions/MSCResolutions/MSC.278(85).pdf https://cimrc.shmtu.edu.cn/_upload/article/files/63/dc/35c66be74d12873254dc88a2ef00/25e2ceb4-d2d9-4cf2-b55b-cdb3d56001b5.pdf | Q68: B13 | R68: Initial association evidenced | S68: 2026-09-29
A69: TSS-0063 | B69: France, Iberia and Canary Islands | C69: At Banco del Hoyo | D69: Source entry; single scheme on first-pass evidence | E69: TSS identity provisional (first pass); operational status: In force. Official baseline reconciliation pending. | F69: Unresolved | G69: Unresolved | J69: Listed in IMO Ships' Routeing 2008 contents, Section II Western European waters, page II/32, after Off Cape S. Vicente (S27), and in Transportstyrelsen 2017 list as adopted by A.284(VIII) 1973 with no later amendment (S4). Location, coordinates and responsible State not retrieved. | K69: SRC-001 | L69: https://www.scribd.com/document/1014775753/1-1-IMO-Adopted-Traffic-Separation-Schemes-on-the-ADMIRALTY-Chart-Series | M69: Notice 17; scheme label: At Banco del Hoyo | N69: UKHO-labelled document on third-party host; edition and currency unverified. | O69: SRC-027; SRC-043; SRC-050; SRC-053 | P69: https://transportstyrelsen.se/globalassets/global/sjofart/dokument/sjotrafik_dok/ruttsystem.pdf https://wwwcdn.imo.org/localresources/en/KnowledgeCentre/IndexofIMOResolutions/MSCResolutions/MSC.63(67).pdf https://www.fpp.uni-lj.si/mma_bin.php?id=2011032217361737 https://en.wikipedia.org/wiki/List_of_traffic_separation_schemes | Q69: B13 | R69: Researched; unresolved | S69: 2026-09-29
A70: TSS-0064 | B70: France, Iberia and Canary Islands | C70: Between Grand Canary and Tenerife | D70: Source entry; single scheme on first-pass evidence | E70: TSS identity confirmed (first pass); operational status: In force. Official baseline reconciliation pending. | F70: Unresolved | G70: Confirmed present: SRS-012 | I70: SRS-012 | J70: Official name found: Western Traffic Separation Scheme (between Grand Canary and Tenerife), part of the Canary Islands schemes. New scheme adopted by MSC 81 in COLREG.2/Circ.57 (26 May 2006), implemented 1 December 2006 (S28). Listed as 'Between Grand Canary and Tenerife' in Ships' Routeing 2008 (S27). | K70: SRC-001 | L70: https://www.scribd.com/document/1014775753/1-1-IMO-Adopted-Traffic-Separation-Schemes-on-the-ADMIRALTY-Chart-Series | M70: Notice 17; scheme label: Between Grand Canary and Tenerife | N70: UKHO-labelled document on third-party host; edition and currency unverified. | O70: SRC-050; SRC-051; SRC-052 | P70: https://www.fpp.uni-lj.si/mma_bin.php?id=2011032217361737 https://cimrc.shmtu.edu.cn/_upload/article/files/63/dc/35c66be74d12873254dc88a2ef00/8c6a3c5f-5a85-4450-980a-5534de9fcd0a.pdf https://wwwcdn.imo.org/localresources/en/KnowledgeCentre/IndexofIMOResolutions/MSCResolutions/MSC.213(81).pdf | Q70: B13 | R70: Initial association evidenced | S70: 2026-09-29
A71: TSS-0065 | B71: France, Iberia and Canary Islands | C71: Between Grand Canary and Fuerteventura | D71: Source entry; single scheme on first-pass evidence | E71: TSS identity confirmed (first pass); operational status: In force. Official baseline reconciliation pending. | F71: Unresolved | G71: Confirmed present: SRS-012 | I71: SRS-012 | J71: Official name found: Eastern Traffic Separation Scheme (between Grand Canary and Fuerteventura), part of the Canary Islands schemes. New scheme in COLREG.2/Circ.57, implemented 1 December 2006 (S28); includes a precautionary area and inshore traffic zone. Listed in Ships' Routeing 2008 (S27). | K71: SRC-001 | L71: https://www.scribd.com/document/1014775753/1-1-IMO-Adopted-Traffic-Separation-Schemes-on-the-ADMIRALTY-Chart-Series | M71: Notice 17; scheme label: Between Grand Canary and Fuerteventura | N71: UKHO-labelled document on third-party host; edition and currency unverified. | O71: SRC-050; SRC-051; SRC-052 | P71: https://www.fpp.uni-lj.si/mma_bin.php?id=2011032217361737 https://cimrc.shmtu.edu.cn/_upload/article/files/63/dc/35c66be74d12873254dc88a2ef00/8c6a3c5f-5a85-4450-980a-5534de9fcd0a.pdf https://wwwcdn.imo.org/localresources/en/KnowledgeCentre/IndexofIMOResolutions/MSCResolutions/MSC.213(81).pdf | Q71: B13 | R71: Initial association evidenced | S71: 2026-09-29
A72: TSS-0066 | B72: Mediterranean and Black Seas | C72: In the Strait of Gibraltar | D72: Source entry; single scheme on first-pass evidence | E72: TSS identity confirmed (first pass); operational status: In force. Official baseline reconciliation pending. | F72: Confirmed present: VTS-025, VTS-026 | G72: Confirmed present: SRS-015 | H72: VTS-025; VTS-026 | I72: SRS-015 | J72: Listed as amended scheme in COLREG.2/Circ.40 (implemented 24 Nov 1994) and COLREG.2/Circ.58 (MSC 82, implemented 1 July 2007); MSC.300(87) (2010) refers to the amended TSS within the GIBREP area. Earlier original adoption not traced. | K72: SRC-001 | L72: https://www.scribd.com/document/1014775753/1-1-IMO-Adopted-Traffic-Separation-Schemes-on-the-ADMIRALTY-Chart-Series | M72: Notice 17; scheme label: In the Strait of Gibraltar | N72: UKHO-labelled document on third-party host; edition and currency unverified. | O72: SRC-054; SRC-055; SRC-056; SRC-059 | P72: https://www.transportstyrelsen.se/globalassets/global/sjofart/dokument/sjotrafik_dok/imo_colreg.2_cirkular.pdf?id=58526 https://wwwcdn.imo.org/localresources/en/KnowledgeCentre/IndexofIMOResolutions/MSCResolutions/MSC.300(87).pdf https://www.transportes.gob.es/recursos_mfom/comodin/recursos/06_los_dst_autopistas_del_mar.pdf https://transportstyrelsen.se/globalassets/global/sjofart/dokument/sjotrafik_dok/mandatory-and-recommended-srs.pdf | Q72: B14 | R72: Initial association evidenced | S72: 2026-09-29
A73: TSS-0067 | B73: Mediterranean and Black Seas | C73: Off Cabo de Gata | D73: Source entry; single scheme on first-pass evidence | E73: TSS identity confirmed (first pass); operational status: In force. Official baseline reconciliation pending. | F73: Confirmed present: VTS-027 | G73: Unresolved | H73: VTS-027 | J73: New scheme in COLREG.2/Circ.44 (MSC 69, implemented 1 Dec 1998); amended by COLREG.2/Circ.57 (MSC 81, implemented 1 Dec 2006). Amended scheme includes an inshore traffic zone. | K73: SRC-001 | L73: https://www.scribd.com/document/1014775753/1-1-IMO-Adopted-Traffic-Separation-Schemes-on-the-ADMIRALTY-Chart-Series | M73: Notice 17; scheme label: Off Cabo de Gata | N73: UKHO-labelled document on third-party host; edition and currency unverified. | O73: SRC-054; SRC-056; SRC-057 | P73: https://www.transportstyrelsen.se/globalassets/global/sjofart/dokument/sjotrafik_dok/imo_colreg.2_cirkular.pdf?id=58526 https://www.transportes.gob.es/recursos_mfom/comodin/recursos/06_los_dst_autopistas_del_mar.pdf https://www.lamoncloa.gob.es/serviciosdeprensa/notasprensa/mfom/Paginas/2015/140115-tarifa.aspx | Q73: B14 | R73: Initial association evidenced | S73: 2026-09-29
A74: TSS-0068 | B74: Mediterranean and Black Seas | C74: Off Cape Palos (Cabo de Palos) | D74: Source entry; single scheme on first-pass evidence | E74: TSS identity confirmed (first pass); operational status: In force. Official baseline reconciliation pending. | F74: Unresolved (lead: VTS-028) | G74: Unresolved | J74: Official name found: Off Cape Palos. New scheme in COLREG.2/Circ.52 (MSC 76, implemented 1 July 2003). S11 (2025) lists cabo de Palos among Spain's existing DSTs. | K74: SRC-001 | L74: https://www.scribd.com/document/1014775753/1-1-IMO-Adopted-Traffic-Separation-Schemes-on-the-ADMIRALTY-Chart-Series | M74: Notice 17; scheme label: Off Cape Palos (Cabo de Palos) | N74: UKHO-labelled document on third-party host; edition and currency unverified. | O74: SRC-054; SRC-056 | P74: https://www.transportstyrelsen.se/globalassets/global/sjofart/dokument/sjotrafik_dok/imo_colreg.2_cirkular.pdf?id=58526 https://www.transportes.gob.es/recursos_mfom/comodin/recursos/06_los_dst_autopistas_del_mar.pdf | Q74: B14 | R74: Association proposed | S74: 2026-09-29
A75: TSS-0069 | B75: Mediterranean and Black Seas | C75: Off Cape la Nao (Cabo de la Nao) | D75: Source entry; single scheme on first-pass evidence | E75: TSS identity confirmed (first pass); operational status: In force. Official baseline reconciliation pending. | F75: Unresolved (lead: VTS-029) | G75: Unresolved | J75: Official name found: Off Cape La Nao. New scheme in COLREG.2/Circ.52 (MSC 76, implemented 1 July 2003); reference chart Spanish IHM chart 47. S11 (2025) lists cabo de la Nao among Spain's DSTs. | K75: SRC-001 | L75: https://www.scribd.com/document/1014775753/1-1-IMO-Adopted-Traffic-Separation-Schemes-on-the-ADMIRALTY-Chart-Series | M75: Notice 17; scheme label: Off Cape la Nao (Cabo de la Nao) | N75: UKHO-labelled document on third-party host; edition and currency unverified. | O75: SRC-054; SRC-056 | P75: https://www.transportstyrelsen.se/globalassets/global/sjofart/dokument/sjotrafik_dok/imo_colreg.2_cirkular.pdf?id=58526 https://www.transportes.gob.es/recursos_mfom/comodin/recursos/06_los_dst_autopistas_del_mar.pdf | Q75: B14 | R75: Association proposed | S75: 2026-09-29
A76: TSS-0070 | B76: Mediterranean and Black Seas | C76: Off Cani Island (Îles Cani) | D76: Source entry; single scheme on first-pass evidence | E76: TSS identity confirmed (first pass); operational status: In force. Official baseline reconciliation pending. | F76: Unresolved | G76: Unresolved | J76: Official name found: North of Cani Island (Off Cani Island). Tunisian scheme (Îles Cani, off Bizerte coast), not the Bonifacio Strait. Amended by COLREG.2/Circ.58 (MSC 82, implemented 1 July 2007) together with Off Cape Bon; reference chart 150-DST of the Tunisian Hydrographic and Oceanographic Service. Original scheme reported operating since 1 Aug 1970 (search snippet from NOAA document, lead only). | K76: SRC-001 | L76: https://www.scribd.com/document/1014775753/1-1-IMO-Adopted-Traffic-Separation-Schemes-on-the-ADMIRALTY-Chart-Series | M76: Notice 17; scheme label: Off Cani Island (Îles Cani) | N76: UKHO-labelled document on third-party host; edition and currency unverified. | O76: SRC-054; SRC-059 | P76: https://www.transportstyrelsen.se/globalassets/global/sjofart/dokument/sjotrafik_dok/imo_colreg.2_cirkular.pdf?id=58526 https://transportstyrelsen.se/globalassets/global/sjofart/dokument/sjotrafik_dok/mandatory-and-recommended-srs.pdf | Q76: B14 | R76: Researched; unresolved | S76: 2026-09-29
A77: TSS-0071 | B77: Mediterranean and Black Seas | C77: Off Cape Bon (Cap Bon) | D77: Source entry; single scheme on first-pass evidence | E77: TSS identity confirmed (first pass); operational status: In force. Official baseline reconciliation pending. | F77: Unresolved | G77: Unresolved | J77: Official name found: North of Cape Bon (Off Cape Bon). Amended by COLREG.2/Circ.58 (MSC 82, implemented 1 July 2007) with Off Cani Island; reference chart 150-DST (Tunisia). Original scheme reported operating since 1 Aug 1970 (lead only). | K77: SRC-001 | L77: https://www.scribd.com/document/1014775753/1-1-IMO-Adopted-Traffic-Separation-Schemes-on-the-ADMIRALTY-Chart-Series | M77: Notice 17; scheme label: Off Cape Bon (Cap Bon) | N77: UKHO-labelled document on third-party host; edition and currency unverified. | O77: SRC-054; SRC-059 | P77: https://www.transportstyrelsen.se/globalassets/global/sjofart/dokument/sjotrafik_dok/imo_colreg.2_cirkular.pdf?id=58526 https://transportstyrelsen.se/globalassets/global/sjofart/dokument/sjotrafik_dok/mandatory-and-recommended-srs.pdf | Q77: B15 | R77: Researched; unresolved | S77: 2026-09-29
A78: TSS-0072 | B78: Mediterranean and Black Seas | C78: In the Corsica Channel | D78: Source entry; single scheme on first-pass evidence | E78: TSS identity confirmed (first pass); operational status: In force. Official baseline reconciliation pending. | F78: Unresolved | G78: Unresolved | J78: New scheme in COLREG.2/Circ.67 (MSC 96, implemented 1 Dec 2016), between Cap Corse and Isola Capraia, with ITZ along the Corsican coast; reference charts SHOM 7013 and IIM 40. | K78: SRC-001 | L78: https://www.scribd.com/document/1014775753/1-1-IMO-Adopted-Traffic-Separation-Schemes-on-the-ADMIRALTY-Chart-Series | M78: Notice 17; scheme label: In the Corsica Channel | N78: UKHO-labelled document on third-party host; edition and currency unverified. | O78: SRC-054; SRC-063; SRC-064; SRC-059 | P78: https://www.transportstyrelsen.se/globalassets/global/sjofart/dokument/sjotrafik_dok/imo_colreg.2_cirkular.pdf?id=58526 https://www.guardiacostiera.gov.it/portale/vessel-traffic-service https://documenti.camera.it/leg19/documentiAcquisiti/COM08/Audizioni/leg19.com08.Audizioni.Memoria.PUBBLICO.ideGes.7923.15-06-2023-16-25-26.360.pdf https://transportstyrelsen.se/globalassets/global/sjofart/dokument/sjotrafik_dok/mandatory-and-recommended-srs.pdf | Q78: B15 | R78: Researched; unresolved | S78: 2026-09-29
A79: TSS-0073 | B79: Mediterranean and Black Seas | C79: In the Adriatic Sea: In the North Adriatic Sea | D79: Source entry; 3 parts recorded (structure only, not a scheme count) | E79: TSS identity confirmed (first pass); operational status: In force. Official baseline reconciliation pending. | F79: Unresolved (lead: VTS-033) | G79: Confirmed present: SRS-016 | I79: SRS-016 | J79: Official name found: In the North Adriatic Sea (eastern part and western part), part of 'In the Adriatic Sea'. Adopted in COLREG.2/Circ.54 annex 3 (MSC 78, implemented 1 Dec 2004); western part amended by COLREG.2/Circ.58 (implemented 1 July 2007). Includes precautionary area at southern limits. | K79: SRC-001 | L79: https://www.scribd.com/document/1014775753/1-1-IMO-Adopted-Traffic-Separation-Schemes-on-the-ADMIRALTY-Chart-Series | M79: Notice 17; scheme label: In the Adriatic Sea: In the North Adriatic Sea | N79: UKHO-labelled document on third-party host; edition and currency unverified. | O79: SRC-054; SRC-058; SRC-065 | P79: https://www.transportstyrelsen.se/globalassets/global/sjofart/dokument/sjotrafik_dok/imo_colreg.2_cirkular.pdf?id=58526 https://wwwcdn.imo.org/localresources/en/KnowledgeCentre/IndexofIMOResolutions/MSCResolutions/MSC.598(111).pdf https://www.hhi.hr/Portals/0/adam/HHI/a14_Qn4yJECeVbpwF_KLag/CouponFiles/VTS_RS_2015.pdf | Q79: B15 | R79: Initial association evidenced | S79: 2026-09-29
A80: TSS-0074 | B80: Mediterranean and Black Seas | C80: In the Adriatic Sea: Approaches to the Gulf of Trieste | D80: Source entry; single scheme on first-pass evidence | E80: TSS identity confirmed (first pass); operational status: In force. Official baseline reconciliation pending. | F80: Unresolved (lead: VTS-033) | G80: Confirmed present: SRS-016 | I80: SRS-016 | J80: Official name found: Approaches to Gulf of Trieste. Component of 'In the Adriatic Sea', COLREG.2/Circ.54 annex 3 (implemented 1 Dec 2004); separation line 45°07'.50N 013°00'.37E to 45°19'.00N 012°56'.87E. | K80: SRC-001 | L80: https://www.scribd.com/document/1014775753/1-1-IMO-Adopted-Traffic-Separation-Schemes-on-the-ADMIRALTY-Chart-Series | M80: Notice 17; scheme label: In the Adriatic Sea: Approaches to the Gulf of Trieste | N80: UKHO-labelled document on third-party host; edition and currency unverified. | O80: SRC-054; SRC-058; SRC-065 | P80: https://www.transportstyrelsen.se/globalassets/global/sjofart/dokument/sjotrafik_dok/imo_colreg.2_cirkular.pdf?id=58526 https://wwwcdn.imo.org/localresources/en/KnowledgeCentre/IndexofIMOResolutions/MSCResolutions/MSC.598(111).pdf https://www.hhi.hr/Portals/0/adam/HHI/a14_Qn4yJECeVbpwF_KLag/CouponFiles/VTS_RS_2015.pdf | Q80: B15 | R80: Initial association evidenced | S80: 2026-09-29
A81: TSS-0075 | B81: Mediterranean and Black Seas | C81: In the Adriatic Sea: Approaches to the Gulf of Venice | D81: Source entry; single scheme on first-pass evidence | E81: TSS identity confirmed (first pass); operational status: In force. Official baseline reconciliation pending. | F81: Confirmed present: VTS-032 | G81: Confirmed present: SRS-016 | H81: VTS-032 | I81: SRS-016 | J81: Official name found: Approaches to Gulf of Venice. Component of 'In the Adriatic Sea', COLREG.2/Circ.54 annex 3 (implemented 1 Dec 2004); separation zone amended by COLREG.2/Circ.58 (implemented 1 July 2007). | K81: SRC-001 | L81: https://www.scribd.com/document/1014775753/1-1-IMO-Adopted-Traffic-Separation-Schemes-on-the-ADMIRALTY-Chart-Series | M81: Notice 17; scheme label: In the Adriatic Sea: Approaches to the Gulf of Venice | N81: UKHO-labelled document on third-party host; edition and currency unverified. | O81: SRC-054; SRC-058; SRC-062; SRC-063 | P81: https://www.transportstyrelsen.se/globalassets/global/sjofart/dokument/sjotrafik_dok/imo_colreg.2_cirkular.pdf?id=58526 https://wwwcdn.imo.org/localresources/en/KnowledgeCentre/IndexofIMOResolutions/MSCResolutions/MSC.598(111).pdf https://www.guardiacostiera.gov.it/portale/documents/d/guest/en_venezia_manuale_utentevts https://www.guardiacostiera.gov.it/portale/vessel-traffic-service | Q81: B15 | R81: Initial association evidenced | S81: 2026-09-29
A82: TSS-0076 | B82: Mediterranean and Black Seas | C82: In the Adriatic Sea: In the Gulf of Trieste and approaches to/from Koper | D82: Source entry; 3 parts recorded (structure only, not a scheme count) | E82: TSS identity confirmed (first pass); operational status: In force. Official baseline reconciliation pending. | F82: Confirmed present: VTS-030, VTS-031 | G82: Confirmed present: SRS-016 | H82: VTS-030; VTS-031 | I82: SRS-016 | J82: Official name found: In the Gulf of Trieste; Approaches to/from Koper (with precautionary area in the Gulf of Trieste). Components of 'In the Adriatic Sea', COLREG.2/Circ.54 annex 3 (implemented 1 Dec 2004). Label groups two schemes plus a precautionary area. | K82: SRC-001 | L82: https://www.scribd.com/document/1014775753/1-1-IMO-Adopted-Traffic-Separation-Schemes-on-the-ADMIRALTY-Chart-Series | M82: Notice 17; scheme label: In the Adriatic Sea: In the Gulf of Trieste and approaches to/from Koper | N82: UKHO-labelled document on third-party host; edition and currency unverified. | O82: SRC-054; SRC-058; SRC-060; SRC-061 | P82: https://www.transportstyrelsen.se/globalassets/global/sjofart/dokument/sjotrafik_dok/imo_colreg.2_cirkular.pdf?id=58526 https://wwwcdn.imo.org/localresources/en/KnowledgeCentre/IndexofIMOResolutions/MSCResolutions/MSC.598(111).pdf https://www.gov.si/assets/organi-v-sestavi/URSP/Dokumenti/VTS/Koper-VTS-Users-Manual.pdf https://www.guardiacostiera.gov.it/portale/documents/d/guest/it_trieste_manuale_utentevts | Q82: B16 | R82: Initial association evidenced | S82: 2026-09-29
A83: TSS-0077 | B83: Mediterranean and Black Seas | C83: In the Adriatic Sea: Approaches to/from Monfalcone | D83: Source entry; single scheme on first-pass evidence | E83: TSS identity confirmed (first pass); operational status: In force. Official baseline reconciliation pending. | F83: Confirmed present: VTS-031 | G83: Confirmed present: SRS-016 | H83: VTS-031 | I83: SRS-016 | J83: Official name found: Approaches to/from Monfalcone. Component of 'In the Adriatic Sea', COLREG.2/Circ.54 annex 3 (implemented 1 Dec 2004); amended scheme per COLREG.2/Circ.58 referenced in VTS Trieste manual. | K83: SRC-001 | L83: https://www.scribd.com/document/1014775753/1-1-IMO-Adopted-Traffic-Separation-Schemes-on-the-ADMIRALTY-Chart-Series | M83: Notice 17; scheme label: In the Adriatic Sea: Approaches to/from Monfalcone | N83: UKHO-labelled document on third-party host; edition and currency unverified. | O83: SRC-054; SRC-058; SRC-061 | P83: https://www.transportstyrelsen.se/globalassets/global/sjofart/dokument/sjotrafik_dok/imo_colreg.2_cirkular.pdf?id=58526 https://wwwcdn.imo.org/localresources/en/KnowledgeCentre/IndexofIMOResolutions/MSCResolutions/MSC.598(111).pdf https://www.guardiacostiera.gov.it/portale/documents/d/guest/it_trieste_manuale_utentevts | Q83: B16 | R83: Initial association evidenced | S83: 2026-09-29
A84: TSS-0078 | B84: Mediterranean and Black Seas | C84: Saronicos Gulf (Saronikós Kólpos, in the Approaches to Piraiévs) | D84: Source entry; single scheme on first-pass evidence | E84: TSS identity provisional (first pass); operational status: In force. Official baseline reconciliation pending. | F84: Unresolved (lead: VTS-035) | G84: Unresolved | J84: Official name found: Saronicos Gulf. Existence as an IMO-adopted TSS evidenced by the 1991 COLREG.2 circular cancelling its inshore traffic zone (implemented 19 April 1991); original adoption instrument and current status not verified. | K84: SRC-001 | L84: https://www.scribd.com/document/1014775753/1-1-IMO-Adopted-Traffic-Separation-Schemes-on-the-ADMIRALTY-Chart-Series | M84: Notice 17; scheme label: Saronicos Gulf (Saronikós Kólpos, in the Approaches to Piraiévs) | N84: UKHO-labelled document on third-party host; edition and currency unverified. | O84: SRC-054; SRC-068; SRC-069 | P84: https://www.transportstyrelsen.se/globalassets/global/sjofart/dokument/sjotrafik_dok/imo_colreg.2_cirkular.pdf?id=58526 https://mitos.gov.gr/index.php/%CE%94%CE%94:%CE%A3%CF%84%CE%B5%CE%BB%CE%AD%CF%87%CF%89%CF%83%CE%B7_%CF%84%CF%89%CE%BD_%CE%9A%CE%AD%CE%BD%CF%84%CF%81%CF%89%CE%BD_%CE%A0%CE%B1%CF%81%CE%B1%CE%BA%CE%BF%CE%BB%CE%BF%CF%8D%CE%B8%CE%B7%CF%83%CE%B7%CF%82_%CE%B8%CE%B1%CE%BB%CE%AC%CF%83%CF%83%CE%B9%CE%B1%CF%82_%CE%9A%CF%85%CE%BA%CE%BB%CE%BF%CF%86%CE%BF%CF%81%CE%AF%CE%B1%CF%82_(VTS)_%CF%84%CE%B7%CF%82_%CE%A7%CF%8E%CF%81%CE%B1%CF%82 https://maredu.hcg.gr/modules/document/file.php/MAK264/%CE%9D%CE%B1%CF%85%CF%84%CE%B9%CE%BA%CE%AD%CF%82%20%CE%95%CF%80%CE%B9%CE%BA%CE%BF%CE%B9%CE%BD%CF%89%CE%BD%CE%AF%CE%B5%CF%82%20-%20%CE%9D%CE%97%CE%9F/%CE%A3%CF%85%CF%83%CF%84%CE%AE%CE%BC%CE%B1%CF%84%CE%B1%20%CF%80%CE%B1%CF%81%CE%B1%CE%BA%CE%BF%CE%BB%CE%BF%CF%8D%CE%B8%CE%B7%CF%83%CE%B7%CF%82%20%CF%80%CE%BB%CE%BF%CE%AF%CF%89%CE%BD%20%CE%B1%CE%BD%CE%AC%20%CF%84%CE%B7%CE%BD%20%CF%85%CF%86%CE%AE%CE%BB%CE%B9%CE%BF%20%CE%BA%CE%B1%CE%B9%20%CE%B5%CE%BE%CE%BF%CF%80%CE%BB%CE%B9%CF%83%CE%BC%CF%8C%CF%82%20%CE%B5%CF%80%CE%AF%20%CF%84%CE%BF%CF%85%20%CF%80%CE%BB%CE%BF%CE%AF%CE%BF%CF%85.pdf | Q84: B16 | R84: Association proposed | S84: 2026-09-29
A85: TSS-0079 | B85: Mediterranean and Black Seas | C85: In the approaches to the port of Thessaloníki | D85: Source entry; single scheme on first-pass evidence | E85: TSS identity confirmed (first pass); operational status: In force. Official baseline reconciliation pending. | F85: Unresolved | G85: Unresolved | J85: Official name found: In the approaches to the Port of Thessaloniki. New scheme in COLREG.2/Circ.60 (MSC 85, implemented 1 June 2009). | K85: SRC-001 | L85: https://www.scribd.com/document/1014775753/1-1-IMO-Adopted-Traffic-Separation-Schemes-on-the-ADMIRALTY-Chart-Series | M85: Notice 17; scheme label: In the approaches to the port of Thessaloníki | N85: UKHO-labelled document on third-party host; edition and currency unverified. | O85: SRC-054; SRC-068; SRC-069 | P85: https://www.transportstyrelsen.se/globalassets/global/sjofart/dokument/sjotrafik_dok/imo_colreg.2_cirkular.pdf?id=58526 https://mitos.gov.gr/index.php/%CE%94%CE%94:%CE%A3%CF%84%CE%B5%CE%BB%CE%AD%CF%87%CF%89%CF%83%CE%B7_%CF%84%CF%89%CE%BD_%CE%9A%CE%AD%CE%BD%CF%84%CF%81%CF%89%CE%BD_%CE%A0%CE%B1%CF%81%CE%B1%CE%BA%CE%BF%CE%BB%CE%BF%CF%8D%CE%B8%CE%B7%CF%83%CE%B7%CF%82_%CE%B8%CE%B1%CE%BB%CE%AC%CF%83%CF%83%CE%B9%CE%B1%CF%82_%CE%9A%CF%85%CE%BA%CE%BB%CE%BF%CF%86%CE%BF%CF%81%CE%AF%CE%B1%CF%82_(VTS)_%CF%84%CE%B7%CF%82_%CE%A7%CF%8E%CF%81%CE%B1%CF%82 https://maredu.hcg.gr/modules/document/file.php/MAK264/%CE%9D%CE%B1%CF%85%CF%84%CE%B9%CE%BA%CE%AD%CF%82%20%CE%95%CF%80%CE%B9%CE%BA%CE%BF%CE%B9%CE%BD%CF%89%CE%BD%CE%AF%CE%B5%CF%82%20-%20%CE%9D%CE%97%CE%9F/%CE%A3%CF%85%CF%83%CF%84%CE%AE%CE%BC%CE%B1%CF%84%CE%B1%20%CF%80%CE%B1%CF%81%CE%B1%CE%BA%CE%BF%CE%BB%CE%BF%CF%8D%CE%B8%CE%B7%CF%83%CE%B7%CF%82%20%CF%80%CE%BB%CE%BF%CE%AF%CF%89%CE%BD%20%CE%B1%CE%BD%CE%AC%20%CF%84%CE%B7%CE%BD%20%CF%85%CF%86%CE%AE%CE%BB%CE%B9%CE%BF%20%CE%BA%CE%B1%CE%B9%20%CE%B5%CE%BE%CE%BF%CF%80%CE%BB%CE%B9%CF%83%CE%BC%CF%8C%CF%82%20%CE%B5%CF%80%CE%AF%20%CF%84%CE%BF%CF%85%20%CF%80%CE%BB%CE%BF%CE%AF%CE%BF%CF%85.pdf | Q85: B16 | R85: Researched; unresolved | S85: 2026-09-29
A86: TSS-0080 | B86: Mediterranean and Black Seas | C86: Strait of Istanbul - North Approach | D86: Source entry; single scheme on first-pass evidence | E86: TSS identity confirmed (first pass); operational status: In force. Official baseline reconciliation pending. | F86: Confirmed present: VTS-034 | G86: Confirmed present: SRS-017 | H86: VTS-034 | I86: SRS-017 | J86: Linked Turkish Straits source segments. Resolve component schemes and VTS areas separately. Adopted by MSC 63, COLREG.2/Circ.40 (implemented 24 Nov 1994), together with 'Strait of Istanbul', 'Strait of Istanbul - South Approach and Sea of Marmara', 'Strait of Canakkale' and its South-West Approach. National regulation (2019) Art. 4 sets the TSS limits in the north at 41°20'.944 N. This record covers the North Approach only; linked components to be resolved in their own records. | K86: SRC-001 | L86: https://www.scribd.com/document/1014775753/1-1-IMO-Adopted-Traffic-Separation-Schemes-on-the-ADMIRALTY-Chart-Series | M86: Notice 17; scheme label: Strait of Istanbul - North Approach | N86: UKHO-labelled document on third-party host; edition and currency unverified. | O86: SRC-054; SRC-066; SRC-067; SRC-059 | P86: https://www.transportstyrelsen.se/globalassets/global/sjofart/dokument/sjotrafik_dok/imo_colreg.2_cirkular.pdf?id=58526 https://kiyiemniyeti.gov.tr/vessel_traffic_and_pilotage_services https://www.resmigazete.gov.tr/eskiler/2019/08/20190815-18.pdf https://transportstyrelsen.se/globalassets/global/sjofart/dokument/sjotrafik_dok/mandatory-and-recommended-srs.pdf | Q86: B16 | R86: Initial association evidenced | S86: 2026-09-29
A87: TSS-0081 | B87: Mediterranean and Black Seas | C87: Strait of Istanbul | D87: Source entry; 2 parts recorded (structure only, not a scheme count) | E87: TSS identity confirmed (first pass); operational status: In force. Official baseline reconciliation pending. | F87: Confirmed present: VTS-034 | G87: Confirmed present: SRS-017 | H87: VTS-034 | I87: SRS-017 | J87: Linked Turkish Straits source segments. Resolve component schemes and VTS areas separately. Adopted by MSC 63 (May 1994), COLREG.2/Circ.40 item .3, implemented 0000 UTC 24 November 1994; companion schemes 'Strait of Istanbul - North Approach' (item .2) and 'South Approach and Sea of Marmara' (item .4) are separate IMO entries. Associated Rules and Recommendations confirmed by A.827(19). Nationally reproduced in 2019 Turkish Straits Maritime Traffic Regulation Annex 1 (English text lead only). | K87: SRC-001 | L87: https://www.scribd.com/document/1014775753/1-1-IMO-Adopted-Traffic-Separation-Schemes-on-the-ADMIRALTY-Chart-Series | M87: Notice 17; scheme label: Strait of Istanbul | N87: UKHO-labelled document on third-party host; edition and currency unverified. | O87: SRC-066; SRC-070; SRC-071; SRC-072; SRC-073; SRC-054 | P87: https://kiyiemniyeti.gov.tr/vessel_traffic_and_pilotage_services https://www.kiyiemniyeti.gov.tr/gemi_trafik_ve_kilavuzluk_hizmeti https://denizcilik.uab.gov.tr/uploads/pages/yonerge-talimat/tbdtduy.pdf https://wwwcdn.imo.org/localresources/en/KnowledgeCentre/IndexofIMOResolutions/AssemblyDocuments/A.827(19).pdf https://media.ellinikahoaxes.gr/uploads/2021/03/TURK-BOGAZLARI-DENIZ-TRAFIK-DUZENI-YONETMELIGI-INGILIZCE-2019.pdf https://www.transportstyrelsen.se/globalassets/global/sjofart/dokument/sjotrafik_dok/imo_colreg.2_cirkular.pdf?id=58526 | Q87: B17 | R87: Initial association evidenced | S87: 2026-09-29
A88: TSS-0082 | B88: Mediterranean and Black Seas | C88: Strait of Istanbul - South Approach and Sea of Marmara | D88: Source entry; 2 parts recorded (structure only, not a scheme count) | E88: TSS identity confirmed (first pass); operational status: In force. Official baseline reconciliation pending. | F88: Confirmed present: VTS-034 | G88: Confirmed present: SRS-017 | H88: VTS-034 | I88: SRS-017 | J88: Linked Turkish Straits source segments. Resolve component schemes and VTS areas separately. COLREG.2/Circ.40 item .4, implemented 0000 UTC 24 November 1994. 2019 national regulation Annex 1.3 'Istanbul Strait Southern Approach and Marmara Sea' (English text lead only). | K88: SRC-001 | L88: https://www.scribd.com/document/1014775753/1-1-IMO-Adopted-Traffic-Separation-Schemes-on-the-ADMIRALTY-Chart-Series | M88: Notice 17; scheme label: Strait of Istanbul - South Approach and Sea of Marmara | N88: UKHO-labelled document on third-party host; edition and currency unverified. | O88: SRC-066; SRC-070; SRC-071; SRC-072; SRC-073; SRC-054 | P88: https://kiyiemniyeti.gov.tr/vessel_traffic_and_pilotage_services https://www.kiyiemniyeti.gov.tr/gemi_trafik_ve_kilavuzluk_hizmeti https://denizcilik.uab.gov.tr/uploads/pages/yonerge-talimat/tbdtduy.pdf https://wwwcdn.imo.org/localresources/en/KnowledgeCentre/IndexofIMOResolutions/AssemblyDocuments/A.827(19).pdf https://media.ellinikahoaxes.gr/uploads/2021/03/TURK-BOGAZLARI-DENIZ-TRAFIK-DUZENI-YONETMELIGI-INGILIZCE-2019.pdf https://www.transportstyrelsen.se/globalassets/global/sjofart/dokument/sjotrafik_dok/imo_colreg.2_cirkular.pdf?id=58526 | Q88: B17 | R88: Initial association evidenced | S88: 2026-09-29
A89: TSS-0083 | B89: Mediterranean and Black Seas | C89: Strait of Canakkale | D89: Source entry; single scheme on first-pass evidence | E89: TSS identity confirmed (first pass); operational status: In force. Official baseline reconciliation pending. | F89: Confirmed present: VTS-034 | G89: Confirmed present: SRS-017 | H89: VTS-034 | I89: SRS-017 | J89: Linked Turkish Straits source segments. Resolve component schemes and VTS areas separately. COLREG.2/Circ.40 item .5, implemented 0000 UTC 24 November 1994; national Annex 1.4 (English text lead only). | K89: SRC-001 | L89: https://www.scribd.com/document/1014775753/1-1-IMO-Adopted-Traffic-Separation-Schemes-on-the-ADMIRALTY-Chart-Series | M89: Notice 17; scheme label: Strait of Canakkale | N89: UKHO-labelled document on third-party host; edition and currency unverified. | O89: SRC-066; SRC-071; SRC-072; SRC-073; SRC-054 | P89: https://kiyiemniyeti.gov.tr/vessel_traffic_and_pilotage_services https://denizcilik.uab.gov.tr/uploads/pages/yonerge-talimat/tbdtduy.pdf https://wwwcdn.imo.org/localresources/en/KnowledgeCentre/IndexofIMOResolutions/AssemblyDocuments/A.827(19).pdf https://media.ellinikahoaxes.gr/uploads/2021/03/TURK-BOGAZLARI-DENIZ-TRAFIK-DUZENI-YONETMELIGI-INGILIZCE-2019.pdf https://www.transportstyrelsen.se/globalassets/global/sjofart/dokument/sjotrafik_dok/imo_colreg.2_cirkular.pdf?id=58526 | Q89: B17 | R89: Initial association evidenced | S89: 2026-09-29
A90: TSS-0084 | B90: Mediterranean and Black Seas | C90: Strait of Canakkale - South-west Approach | D90: Source entry; single scheme on first-pass evidence | E90: TSS identity confirmed (first pass); operational status: In force. Official baseline reconciliation pending. | F90: Unresolved (lead: VTS-034) | G90: Unresolved (lead: SRS-017) | J90: Linked Turkish Straits source segments. Resolve component schemes and VTS areas separately. Official name found: Strait of Canakkale - South-West Approach. COLREG.2/Circ.40 item .6, implemented 0000 UTC 24 November 1994; national Annex 1.5 'Canakkale Strait Southwestern Approaches' (English text lead only). | K90: SRC-001 | L90: https://www.scribd.com/document/1014775753/1-1-IMO-Adopted-Traffic-Separation-Schemes-on-the-ADMIRALTY-Chart-Series | M90: Notice 17; scheme label: Strait of Canakkale - South-west Approach | N90: UKHO-labelled document on third-party host; edition and currency unverified. | O90: SRC-066; SRC-071; SRC-073; SRC-054 | P90: https://kiyiemniyeti.gov.tr/vessel_traffic_and_pilotage_services https://denizcilik.uab.gov.tr/uploads/pages/yonerge-talimat/tbdtduy.pdf https://media.ellinikahoaxes.gr/uploads/2021/03/TURK-BOGAZLARI-DENIZ-TRAFIK-DUZENI-YONETMELIGI-INGILIZCE-2019.pdf https://www.transportstyrelsen.se/globalassets/global/sjofart/dokument/sjotrafik_dok/imo_colreg.2_cirkular.pdf?id=58526 | Q90: B17 | R90: Association proposed | S90: 2026-09-29
A91: TSS-0085 | B91: Mediterranean and Black Seas | C91: In the Approaches to the Ports of Odessa and Ilichevsk | D91: Source entry; single scheme on first-pass evidence | E91: TSS identity confirmed (first pass); operational status: Withdrawn/superseded. Official baseline reconciliation pending. | F91: Unresolved (lead: VTS-036) | G91: Unresolved | J91: Historical source label retained. Current naming, implementation and service status require authority confirmation. Official name found: In the approaches to the ports of Odessa and Ilichevsk (historical); now part of 'Approaches to the Chornomorsk, Odesa and Pivdennyi ports'. Adopted by IMCO/IMO, COLREG.2/Circ.14 of 22 April 1981 (Marad and scanned circular). Ilichevsk renamed Chornomorsk. Per secondary summary of COLREG.2/Circ.78 (MSC 106, issued 13 December 2022), replaced by the amended scheme 'Approaches to the Chornomorsk, Odesa and Pivdennyi ports', implemented 0000 UTC 1 June 2023. Marad primary confirms Ukraine's proposal to merge the two schemes; IMO circular text not itself retrieved. | K91: SRC-001 | L91: https://www.scribd.com/document/1014775753/1-1-IMO-Adopted-Traffic-Separation-Schemes-on-the-ADMIRALTY-Chart-Series | M91: Notice 17; scheme label: In the Approaches to the Ports of Odessa and Ilichevsk | N91: UKHO-labelled document on third-party host; edition and currency unverified. | O91: SRC-075; SRC-076; SRC-077; SRC-054 | P91: https://marad.gov.ua/storage/app/sites/1/international-activities/Propozicii_sistemi_rozpodilu_ryhu_en.pdf https://hksoa.org/member_circulars/colreg-2-circ-78-new-separation-schemes-and-associated-measures/ https://www.uspa.gov.ua/en/announcements-en/information-for-shipowners-agents-port-operators https://www.transportstyrelsen.se/globalassets/global/sjofart/dokument/sjotrafik_dok/imo_colreg.2_cirkular.pdf?id=58526 | Q91: B17 | R91: Association proposed | S91: 2026-09-29
A92: TSS-0086 | B92: Mediterranean and Black Seas | C92: Between the Ports of Odessa and Ilichevsk | D92: Source entry; single scheme on first-pass evidence | E92: TSS identity confirmed (first pass); operational status: Withdrawn/superseded. Official baseline reconciliation pending. | F92: Unresolved (lead: VTS-036) | G92: Unresolved | J92: Historical source label retained. Current naming, implementation and service status require authority confirmation. Official name found: Between the ports of Odessa and Ilichevsk (historical); now part of 'Approaches to the Chornomorsk, Odesa and Pivdennyi ports'. Adopted per COLREG.2/Circ.14 (22 April 1981). Replaced with effect from 1 June 2023 by the combined amended scheme under COLREG.2/Circ.78 (secondary summary; Marad primary confirms merger proposal). | K92: SRC-001 | L92: https://www.scribd.com/document/1014775753/1-1-IMO-Adopted-Traffic-Separation-Schemes-on-the-ADMIRALTY-Chart-Series | M92: Notice 17; scheme label: Between the Ports of Odessa and Ilichevsk | N92: UKHO-labelled document on third-party host; edition and currency unverified. | O92: SRC-075; SRC-076; SRC-077; SRC-054 | P92: https://marad.gov.ua/storage/app/sites/1/international-activities/Propozicii_sistemi_rozpodilu_ryhu_en.pdf https://hksoa.org/member_circulars/colreg-2-circ-78-new-separation-schemes-and-associated-measures/ https://www.uspa.gov.ua/en/announcements-en/information-for-shipowners-agents-port-operators https://www.transportstyrelsen.se/globalassets/global/sjofart/dokument/sjotrafik_dok/imo_colreg.2_cirkular.pdf?id=58526 | Q92: B18 | R92: Association proposed | S92: 2026-09-29
A93: TSS-0087 | B93: Mediterranean and Black Seas | C93: In the area Off the South-western Coast of the Crimea | D93: Source entry; 2 parts recorded (structure only, not a scheme count) | E93: TSS identity confirmed (first pass); operational status: Not established. Official baseline reconciliation pending. | F93: Unresolved | G93: Unresolved | J93: Historical source label retained. Current naming, implementation and service status require authority confirmation. Official name found: In the area off the south-western coast of the Crimea. New scheme adopted at MSC 87, COLREG.2/Circ.61 (1 June 2010), implemented 0000 UTC 1 December 2010. Two parts: Routeing System No.9 'Sevastopol Harbour Approach' and No.3 'From Cape Khersones to Cape Aitodor'. No IMO revocation found in retrieved sources. | K93: SRC-001 | L93: https://www.scribd.com/document/1014775753/1-1-IMO-Adopted-Traffic-Separation-Schemes-on-the-ADMIRALTY-Chart-Series | M93: Notice 17; scheme label: In the area Off the South-western Coast of the Crimea | N93: UKHO-labelled document on third-party host; edition and currency unverified. | O93: SRC-049; SRC-078; SRC-079 | P93: https://cimrc.shmtu.edu.cn/_upload/article/files/63/dc/35c66be74d12873254dc88a2ef00/25e2ceb4-d2d9-4cf2-b55b-cdb3d56001b5.pdf https://iho.int/uploads/user/Inter-Regional%20Coordination/RHC/MBSHC/BASWG/BASWG15/StatementOnMSI_Ukraine.pdf https://marina.gov.ph/wp-content/uploads/2022/03/Circular-Letter-No.4508-Communication-From-The-Government-Of-Ukraine-Secretariat1.pdf | Q93: B18 | R93: Researched; unresolved | S93: 2026-09-29
A94: TSS-0088 | B94: Mediterranean and Black Seas | C94: In the Southern Approaches to the Kerch Strait | D94: Source entry; single scheme on first-pass evidence | E94: TSS identity confirmed (first pass); operational status: Not established. Official baseline reconciliation pending. | F94: Unresolved | G94: Unresolved | J94: Historical source label retained. Current naming, implementation and service status require authority confirmation. Official name found: In the southern approaches to the Kerch Strait. New scheme adopted by resolution A.374(X), 14 November 1977 (reference chart USSR No.514). Implementation date 15 May 1978 is a search-snippet lead only. Ukraine's IMO Circular Letter 4508 calls it 'Approaches to the Kerch Strait from the South', approved by IMO. No revocation found. | K94: SRC-001 | L94: https://www.scribd.com/document/1014775753/1-1-IMO-Adopted-Traffic-Separation-Schemes-on-the-ADMIRALTY-Chart-Series | M94: Notice 17; scheme label: In the Southern Approaches to the Kerch Strait | N94: UKHO-labelled document on third-party host; edition and currency unverified. | O94: SRC-074; SRC-078; SRC-079 | P94: https://wwwcdn.imo.org/localresources/en/KnowledgeCentre/IndexofIMOResolutions/AssemblyDocuments/A.374(10).pdf https://iho.int/uploads/user/Inter-Regional%20Coordination/RHC/MBSHC/BASWG/BASWG15/StatementOnMSI_Ukraine.pdf https://marina.gov.ph/wp-content/uploads/2022/03/Circular-Letter-No.4508-Communication-From-The-Government-Of-Ukraine-Secretariat1.pdf | Q94: B18 | R94: Researched; unresolved | S94: 2026-09-29
A95: TSS-0089 | B95: Mediterranean and Black Seas | C95: Off the Mediterranean Coast of Egypt | D95: Source entry; 6 parts recorded (structure only, not a scheme count) | E95: TSS identity confirmed (first pass); operational status: In force. Official baseline reconciliation pending. | F95: Unresolved | G95: Unresolved | J95: Official name found: Off the Mediterranean coast of Egypt. New scheme adopted at MSC 75, COLREG.2/Circ.51 (31 May 2002), implemented 0000 UTC 1 December 2002. Comprises approach schemes to Damietta (Mina Dumyat) and Port Said (Bur Said) with two precautionary areas. | K95: SRC-001 | L95: https://www.scribd.com/document/1014775753/1-1-IMO-Adopted-Traffic-Separation-Schemes-on-the-ADMIRALTY-Chart-Series | M95: Notice 17; scheme label: Off the Mediterranean Coast of Egypt | N95: UKHO-labelled document on third-party host; edition and currency unverified. | O95: SRC-041 | P95: https://cimrc.shmtu.edu.cn/_upload/article/files/63/dc/35c66be74d12873254dc88a2ef00/a4f3f58b-c400-41cb-858b-89dccee63151.pdf | Q95: B18 | R95: Researched; unresolved | S95: 2026-09-29
A96: TSS-0090 | B96: Southern Africa | C96: Off Alphard Banks, 34 miles south of Cape Infanta | D96: Source entry; single scheme on first-pass evidence | E96: TSS identity confirmed (first pass); operational status: In force. Official baseline reconciliation pending. | F96: Unresolved | G96: Unresolved | J96: Official name found: Off Alphard Banks 34 miles south of Cape Infanta. New scheme adopted at MSC 69, COLREG.2/Circ.44 (May 1998) Annex 9 'Off the south coast of South Africa', implemented 0000 UTC 1 December 1998. Charts on Cape Datum. | K96: SRC-001 | L96: https://www.scribd.com/document/1014775753/1-1-IMO-Adopted-Traffic-Separation-Schemes-on-the-ADMIRALTY-Chart-Series | M96: Notice 17; scheme label: Off Alphard Banks, 34 miles south of Cape Infanta | N96: UKHO-labelled document on third-party host; edition and currency unverified. | O96: SRC-054; SRC-081; SRC-082 | P96: https://www.transportstyrelsen.se/globalassets/global/sjofart/dokument/sjotrafik_dok/imo_colreg.2_cirkular.pdf?id=58526 https://www.westpandi.com/globalassets/news/mn-13-of-2017.pdf https://source.acts.co.za/south-african-maritime-and%20aeronautical-search-and-rescue-act-2002/r604_30__ship_reporting_sy.php | Q96: B18 | R96: Researched; unresolved | S96: 2026-09-29
A97: TSS-0091 | B97: Southern Africa | C97: Off the FA Platform, 47 miles south of Mossel Bay | D97: Source entry; single scheme on first-pass evidence | E97: TSS identity confirmed (first pass); operational status: In force. Official baseline reconciliation pending. | F97: Unresolved | G97: Unresolved | J97: Official name found: Off the FA Platform 47 miles south of Mossel Bay. New scheme adopted at MSC 69, COLREG.2/Circ.44 Annex 9, implemented 0000 UTC 1 December 1998. | K97: SRC-001 | L97: https://www.scribd.com/document/1014775753/1-1-IMO-Adopted-Traffic-Separation-Schemes-on-the-ADMIRALTY-Chart-Series | M97: Notice 17; scheme label: Off the FA Platform, 47 miles south of Mossel Bay | N97: UKHO-labelled document on third-party host; edition and currency unverified. | O97: SRC-054; SRC-081; SRC-082 | P97: https://www.transportstyrelsen.se/globalassets/global/sjofart/dokument/sjotrafik_dok/imo_colreg.2_cirkular.pdf?id=58526 https://www.westpandi.com/globalassets/news/mn-13-of-2017.pdf https://source.acts.co.za/south-african-maritime-and%20aeronautical-search-and-rescue-act-2002/r604_30__ship_reporting_sy.php | Q97: B19 | R97: Researched; unresolved | S97: 2026-09-29
A98: TSS-0092 | B98: Red Sea and Arabian region | C98: In the Gulf of Suez | D98: Source entry; single scheme on first-pass evidence | E98: TSS identity confirmed (first pass); operational status: In force. Official baseline reconciliation pending. | F98: Unresolved (lead: VTS-037) | G98: Unresolved | J98: New scheme adopted by resolution A.374(X) (14 November 1977); amended scheme adopted at MSC 67, COLREG.2/Circ.42 (2 January 1997), implemented 1 July 1997. Compilation notes associated 'Rules for ships navigating in the Gulf of Suez' (MSC 46/19). Earlier amendments also appear in the compilation. | K98: SRC-001 | L98: https://www.scribd.com/document/1014775753/1-1-IMO-Adopted-Traffic-Separation-Schemes-on-the-ADMIRALTY-Chart-Series | M98: Notice 17; scheme label: In the Gulf of Suez | N98: UKHO-labelled document on third-party host; edition and currency unverified. | O98: SRC-054; SRC-074; SRC-080 | P98: https://www.transportstyrelsen.se/globalassets/global/sjofart/dokument/sjotrafik_dok/imo_colreg.2_cirkular.pdf?id=58526 https://wwwcdn.imo.org/localresources/en/KnowledgeCentre/IndexofIMOResolutions/AssemblyDocuments/A.374(10).pdf https://www.marinelink.com/news/307563 | Q98: B19 | R98: Association proposed | S98: 2026-09-29
A99: TSS-0093 | B99: Red Sea and Arabian region | C99: In the Entrance to the Gulf of Aqaba | D99: Source entry; single scheme on first-pass evidence | E99: TSS identity confirmed (first pass); operational status: In force. Official baseline reconciliation pending. | F99: Unresolved | G99: Unresolved | J99: Official name found: In the entrance to the Gulf of Aqaba. New scheme adopted at MSC 61 (December 1992), COLREG.2/Circ.39; implemented 0000 UTC 1 October 1993 after Egypt confirmed survey of Grafton Passage and aids (Circ.39/Add.1). Nearby areas to be avoided north of the Strait of Tiran and at Ras Mohammed adopted by A.827(19). | K99: SRC-001 | L99: https://www.scribd.com/document/1014775753/1-1-IMO-Adopted-Traffic-Separation-Schemes-on-the-ADMIRALTY-Chart-Series | M99: Notice 17; scheme label: In the Entrance to the Gulf of Aqaba | N99: UKHO-labelled document on third-party host; edition and currency unverified. | O99: SRC-054; SRC-072 | P99: https://www.transportstyrelsen.se/globalassets/global/sjofart/dokument/sjotrafik_dok/imo_colreg.2_cirkular.pdf?id=58526 https://wwwcdn.imo.org/localresources/en/KnowledgeCentre/IndexofIMOResolutions/AssemblyDocuments/A.827(19).pdf | Q99: B19 | R99: Researched; unresolved | S99: 2026-09-29
A100: TSS-0094 | B100: Red Sea and Arabian region | C100: In the Southern Red Sea - West and South of Hanish al Kubra | D100: Source entry; single scheme on first-pass evidence | E100: TSS identity confirmed (first pass); operational status: In force. Official baseline reconciliation pending. | F100: Unresolved | G100: Unresolved | J100: Official name found: In the Southern Red Sea: west and south of Hanish al Kubra Island. New scheme adopted at MSC 76, COLREG.2/Circ.52 (6 January 2003) Annex 1, implemented 0000 UTC 1 July 2003. Annex 1 contains two schemes (this and east of Jabal Zuqar, TSS-0095). | K100: SRC-001 | L100: https://www.scribd.com/document/1014775753/1-1-IMO-Adopted-Traffic-Separation-Schemes-on-the-ADMIRALTY-Chart-Series | M100: Notice 17; scheme label: In the Southern Red Sea - West and South of Hanish al Kubra | N100: UKHO-labelled document on third-party host; edition and currency unverified. | O100: SRC-054 | P100: https://www.transportstyrelsen.se/globalassets/global/sjofart/dokument/sjotrafik_dok/imo_colreg.2_cirkular.pdf?id=58526 | Q100: B19 | R100: Researched; unresolved | S100: 2026-09-29
A101: TSS-0095 | B101: Red Sea and Arabian region | C101: In the Southern Red Sea - East of Jabal Zuqar Island | D101: Source entry; single scheme on first-pass evidence | E101: TSS identity confirmed (first pass); operational status: In force. Official baseline reconciliation pending. | F101: Unresolved | G101: Unresolved | J101: Official name found: In the Southern Red Sea: east of Jabal Zuqar Island. New scheme adopted at MSC 76, COLREG.2/Circ.52 Annex 1, implemented 0000 UTC 1 July 2003. Southbound lane 140° then 166°, northbound 346° then 320°. | K101: SRC-001 | L101: https://www.scribd.com/document/1014775753/1-1-IMO-Adopted-Traffic-Separation-Schemes-on-the-ADMIRALTY-Chart-Series | M101: Notice 17; scheme label: In the Southern Red Sea - East of Jabal Zuqar Island | N101: UKHO-labelled document on third-party host; edition and currency unverified. | O101: SRC-054 | P101: https://www.transportstyrelsen.se/globalassets/global/sjofart/dokument/sjotrafik_dok/imo_colreg.2_cirkular.pdf?id=58526 | Q101: B19 | R101: Researched; unresolved | S101: 2026-09-29
... A112: TSS-0106 | B112: Indian Ocean and South Asia | C112: Off Dondra Head | D112: Source entry; single scheme on first-pass evidence | E112: TSS identity provisional (first pass); operational status: In force. Official baseline reconciliation pending. | F112: Unresolved | G112: Unresolved | J112: Official name found: Off Dondra Head (TSS south of Dondra Head). MEPC 80/16/3 (28 Apr 2023) states the existing TSS south of Dondra Head is in Ships' Routeing Section IV and was established in 1980; adoption instrument (IMO circular/resolution) not retrieved. 2023 industry/IWC proposal to move the TSS about 15 nm south was opposed by Sri Lanka (press leads); no change evidenced. | K112: SRC-001 | L112: https://www.scribd.com/document/1014775753/1-1-IMO-Adopted-Traffic-Separation-Schemes-on-the-ADMIRALTY-Chart-Series | M112: Notice 17; scheme label: Off Dondra Head | N112: UKHO-labelled document on third-party host; edition and currency unverified. | O112: SRC-090 | P112: https://www.worldshipping.org/s/MEPC-80-16-3-Call-for-establishment-of-a-new-traffic-separation-scheme-south-of-Sri-Lanka-IWC-ICS-BI.pdf | Q112: B22 | R112: Researched; unresolved | S112: 2026-09-29
A113: TSS-0107 | B113: Malacca, Singapore and Indonesia | C113: At One Fathom Bank | D113: Source entry; single scheme on first-pass evidence | E113: TSS identity confirmed (first pass); operational status: In force. Official baseline reconciliation pending. | F113: Confirmed present: VTS-004 | G113: Confirmed present: SRS-004 | H113: VTS-004 | I113: SRS-004 | J113: Source segment within the Malacca–Singapore routeing system. Do not equate segments with VTS areas. Official name found: At One Fathom Bank (with precautionary area 'Off Port Klang'). Amended scheme adopted by MSC 69 (May 1998); COLREG.2/Circ.44 annex 1, implemented 0000 UTC 1 Dec 1998, with precautionary area 'Off Port Klang'. Segment of the Malacca-Singapore routeing system. | K113: SRC-001 | L113: https://www.scribd.com/document/1014775753/1-1-IMO-Adopted-Traffic-Separation-Schemes-on-the-ADMIRALTY-Chart-Series | M113: Notice 17; scheme label: At One Fathom Bank | N113: UKHO-labelled document on third-party host; edition and currency unverified. | O113: SRC-054; SRC-083; SRC-007; SRC-084 | P113: https://www.transportstyrelsen.se/globalassets/global/sjofart/dokument/sjotrafik_dok/imo_colreg.2_cirkular.pdf?id=58526 https://www.mpa.gov.sg/api/media/78c165e3-67e4-4da3-9496-c196739374d2/-pc98-65.pdf https://www.mpa.gov.sg/port-marine-ops/operations/vessel-traffic-information-system/operational-areas https://file.go.gov.sg/spi2026apr17.pdf | Q113: B22 | R113: Initial association evidenced | S113: 2026-09-29
...

Sheet Stage 4 Findings
A1: STAGE 4 FINDINGS | B10 TO B34
A3: v0.3 | First-pass record research. Findings are research determinations, not operational guidance. Unresolved never means absent.
A6: Record ID | B6: Batch | C6: Group | D6: Source label | E6: Official name | F6: States | G6: TSS identity | H6: Identity note | I6: Operational status | J6: Components | K6: VTS finding | L6: VTS service IDs | M6: VTS basis | N6: Reporting finding | O6: Reporting scheme IDs | P6: Reporting basis | Q6: Voluntary reporting | R6: Applicability notes | S6: Provisional complexity | T6: Complexity reason | U6: Source IDs | V6: Open questions | W6: Audit adjustments at merge
A7: TSS-0046 | B7: B10 | C7: A | D7: German Bight Western Approach | E7: German Bight western approach | F7: Germany | G7: Confirmed | H7: Named in IMO COLREG.2/Circ.59 (MSC 83, 2007) as amended scheme with special provisions for the North Hinder to German Bight tanker route, implemented 1 May 2008 (S1); listed in IMO Ships' Routeing 2008 (S27) and Transportstyrelsen 2017 list (S4). German statute designates it a deep-water route (Tiefwasserweg) mandatory for large tankers (S6 Nr. 6). MSC 109 adopted a revised containership recommendation covering it from 1 July 2025 (lead S5). No evidence of renaming or restructuring by recent IMO amendments was found. | I7: In force | K7: Confirmed present | L7: VTS-016 | M7: AnlBV Anlage Nr. 3.1 requires ships approaching the Inner German Bight from the west to report to 'German Bight Traffic' at 007° 10' E 'unabhängig davon, ob das Verkehrstrennungsgebiet German Bight Western Approach benutzt wird' (S6); Nr. 5.1 states traffic is monitored under maritime traffic safety. Coverage evidenced for the eastern part of the scheme and its approach into the Inner German Bight; the western extent of the scheme relative to the VTS area was not verified. | N7: Unresolved | P7: National mandatory report (AnlBV Nr. 3.1) at 007° 10' E for ships and tows over 300 GT, expressly regardless of use of this TSS (S6). Not an IMO-adopted SRS. | R7: Report: over 300 GT. Mandatory use of the TSS (AnlBV Nr. 6): oil tankers over 10,000 GT, NLS Z tankers over 10,000 GT, NLS X/Y tankers over 5,000 GT, gas tankers over 10,000 GT approaching or leaving the Inner German Bight from the west. Mandatory route for tankers from North Hinder to the German Bight applies to oil tankers 10,000 GT and over, chemical/NLS tankers 5,000 GT (X/Y) or 10,000 GT (Z) and over, and gas carriers 10,000 GT and over (S1, annex 4). Reports under AnlBV Anlage Nr. 3.1 and SeeSchStrO section 58 are made to German Bight Traffic, a VTS. Recorded under the service as VTS reporting duties (national statute, not an IMO-adopted scheme). | S7: Complex | T7: National mandatory reporting plus national mandatory-use rule, IMO mandatory tanker route and 2025 containership recommendation overlap; cross-border Dutch/German routeing context. | U7: SRC-024; SRC-027; SRC-028; SRC-029; SRC-031; SRC-033; SRC-034; SRC-050 | V7: Exact westward extent of the scheme and whether any part lies in Netherlands waters not verified. IMO text of the 2024 containership recommendation (MSC 109) not retrieved. No evidence found of any recent IMO renaming of German TSS, but Circ. texts after 2016 were not all retrieved. | W7: reporting_finding: Confirmed present -> Unresolved. Reports under AnlBV Anlage Nr. 3.1 and SeeSchStrO section 58 are made to German Bight Traffic, a VTS. Recorded under the service as VTS reporting duties (national statute, not an IMO-adopted scheme). No separate mandatory scheme evidenced.
A8: TSS-0047 | B8: B10 | C8: A | D8: Elbe Approach | E8: Elbe approach | F8: Germany | G8: Confirmed | H8: Listed as 'Elbe approach' in IMO Ships' Routeing 2008 (S27) and the Transportstyrelsen 2017 list of IMO schemes (S4). Adopting and latest amending circular not retrieved. | I8: In force | K8: Confirmed present | L8: VTS-018; VTS-016 | M8: Cuxhaven VTS is responsible for the Elbe 'im Bereich der Elbeansteuerung' (Elbe approach) (S9); the GDWS Bekanntmachung sets the Cuxhaven Elbe Traffic area from buoy Nordergründe-Nord (008° E), with outbound reports there to German Bight Traffic on VHF 80 (S7). Coverage is of the direct approach; the TSS lanes themselves are in the Inner German Bight covered by German Bight Traffic, but the exact TSS-to-sector boundary was not verified. | N8: Unresolved | P8: SeeSchStrO § 58 position report at NGN (008° E) to Cuxhaven Elbe Traffic inbound and German Bight Traffic outbound (S7); AnlBV Nr. 3.1 entry report for ships entering the Inner German Bight from west or north (S6). National, not IMO. | R8: SeeSchStrO § 58: vessels of 50 m LOA or more and ships under § 30(1). AnlBV: over 300 GT. SeeSchStrO section 58 reports on the Elbe approach are made to the VTS centres. Recorded under the service as VTS reporting duties. Reports under AnlBV Anlage Nr. 3.1 and SeeSchStrO section 58 are made to German Bight Traffic, a VTS. Recorded under the service as VTS reporting duties (national statute, not an IMO-adopted scheme). | S8: Intermediate | T8: Two VTS services and two national reporting regimes meet at the seaward end of the Elbe. | U8: SRC-027; SRC-029; SRC-030; SRC-032; SRC-033; SRC-050 | V8: Adopting IMO instrument and current chart geometry not retrieved; confirm whether the TSS lies seaward of NGN (German Bight Traffic sector) or partly within Cuxhaven Elbe Traffic sector. | W8: reporting_finding: Confirmed present -> Unresolved. SeeSchStrO section 58 reports on the Elbe approach are made to the VTS centres. Recorded under the service as VTS reporting duties. Reports under AnlBV Anlage Nr. 3.1 and SeeSchStrO section 58 are made to German Bight Traffic, a VTS. Recorded under the service as VTS reporting duties (national statute, not an IMO-adopted scheme). No separate mandatory scheme evidenced.
A9: TSS-0048 | B9: B10 | C9: A | D9: Jade Approach | E9: Jade approach | F9: Germany | G9: Confirmed | H9: Listed as 'Jade approach' in IMO Ships' Routeing 2008 (S27) and Transportstyrelsen 2017 list (S4). WSV describes it as the link between Terschelling-German Bight and the Western Approach giving access to Weser and Jade from the north (S11). German statute places a pilot transfer position 'im Verkehrstrennungsgebiet Jade Approach' within the Inner German Bight (S6 Nr. 8). | I9: In force | K9: Confirmed present | L9: VTS-016 | M9: AnlBV Nr. 8 locates the scheme in the Inner German Bight outside the territorial sea; Nr. 5.1 states traffic there is monitored under maritime traffic safety and Nr. 3.1 routes reports to German Bight Traffic (S6). German Bight Traffic monitors the inner German Bight from Borkum to Helgoland (S8). | N9: Unresolved | P9: AnlBV Nr. 3.1 report at 54° 20' N or 007° 10' E; SeeSchStrO § 58 entry report at 54° 15' N west of Helgoland to German Bight Traffic (S6, S7). | R9: AnlBV: over 300 GT. SeeSchStrO § 58: 50 m or more. Compulsory pilotage from the Jade Approach transfer position for large tankers, bulk carriers and other ships per AnlBV Nr. 8 (S6). Reports under AnlBV Anlage Nr. 3.1 and SeeSchStrO section 58 are made to German Bight Traffic, a VTS. Recorded under the service as VTS reporting duties (national statute, not an IMO-adopted scheme). | S9: Intermediate | T9: National reporting, VTS and offshore pilotage obligations combine; single VTS. | U9: SRC-027; SRC-029; SRC-030; SRC-031; SRC-034; SRC-050 | V9: Adopting IMO instrument and any recent amendments not retrieved. | W9: reporting_finding: Confirmed present -> Unresolved. Reports under AnlBV Anlage Nr. 3.1 and SeeSchStrO section 58 are made to German Bight Traffic, a VTS. Recorded under the service as VTS reporting duties (national statute, not an IMO-adopted scheme). No separate mandatory scheme evidenced.
A10: TSS-0049 | B10: B10 | C10: A | D10: Terschelling - German Bight | E10: Terschelling-German Bight | F10: Netherlands; Germany | G10: Confirmed | H10: Amended by COLREG.2/Circ.59 (MSC 83, implemented 1 May 2008) (S1); listed in Ships' Routeing 2008 (S27) and Transportstyrelsen 2017 list (S4). MSC 109 containership recommendation from 1 July 2025 (lead S5). | I10: In force | K10: Confirmed present | L10: VTS-016 | M10: Bekanntmachung 19.1.4 and 19.1.5 require vessels using the TSS 'Terschelling - German Bight' and its inshore traffic zone to report to German Bight Traffic at Borkumriff buoy (VHF 79) and at TG 17/C eastbound (VHF 80) (S7). This establishes coverage of the German (eastern) part only. For the Dutch part: No Dutch VTS was found whose defined area covers this offshore scheme. The Netherlands Coastguard performs Vessel Traffic Monitoring (VTMon) and distinguishes VTS as provided by traffic centres (S14, S15); VTMon is recorded as a lead only, not as a VTS. | N10: Unresolved | P10: SeeSchStrO § 58 entry and position reports (vessels 50 m or more) and AnlBV Nr. 3.1 (over 300 GT) apply on the German part (S6, S7). National, not IMO. No mandatory reporting identified for the Dutch part. | Q10: Netherlands Coastguard broadcasts wave-height advice for container ships in TSS Terschelling-German Bight and may advise the northern route; advice is not binding (S13). | R10: Mandatory route for tankers from North Hinder to the German Bight applies to oil tankers 10,000 GT and over, chemical/NLS tankers 5,000 GT (X/Y) or 10,000 GT (Z) and over, and gas carriers 10,000 GT and over (S1, annex 4). Coastguard advice targets container ships 100 to 200 m at 3 m waves and over 200 m at 4 m waves (S13). Reports under AnlBV Anlage Nr. 3.1 and SeeSchStrO section 58 are made to German Bight Traffic, a VTS. Recorded under the service as VTS reporting duties (national statute, not an IMO-adopted scheme). | S10: Complex | T10: Cross-border scheme: German VTS and national reporting on eastern part, no VTS evidenced on Dutch part, plus mandatory tanker route and containership advice. | U10: SRC-024; SRC-027; SRC-028; SRC-029; SRC-030; SRC-031; SRC-034; SRC-036; SRC-037; SRC-038; SRC-050 | V10: Exact boundary between German Bight Traffic coverage and the Dutch part not verified. Rijkswaterstaat Brandaris (Terschelling) VTS designation could not be read (officielebekendmakingen.nl returned HTTP 403); search snippets indicate its area is the Terschelling zeegat approach, not the TSS. | W10: reporting_finding: Confirmed present -> Unresolved. Reports under AnlBV Anlage Nr. 3.1 and SeeSchStrO section 58 are made to German Bight Traffic, a VTS. Recorded under the service as VTS reporting duties (national statute, not an IMO-adopted scheme). No separate mandatory scheme evidenced.
A11: TSS-0050 | B11: B10 | C11: A | D11: Vlieland North | E11: Vlieland North (part of 'Off Vlieland, Vlieland North and Vlieland Junction') | F11: Netherlands | G11: Confirmed | H11: COLREG.2/Circ.59 (MSC 83, implemented 1 May 2008) amended the special provisions of 'Off Vlieland, Vlieland North and Vlieland Junction' (S1). IMO Ships' Routeing 2008 treats these as one routeing system entry (S27). Component of the same system as TSS-0051. | I11: In force | J11: Off Vlieland; Vlieland North; Vlieland Junction | K11: Unresolved | M11: No Dutch VTS was found whose defined area covers this offshore scheme. The Netherlands Coastguard performs Vessel Traffic Monitoring (VTMon) and distinguishes VTS as provided by traffic centres (S14, S15); VTMon is recorded as a lead only, not as a VTS. | N11: Unresolved | P11: No IMO-adopted mandatory ship reporting system or national mandatory reporting specific to this scheme was found. Netherlands Coastguard states it 'has no powers to impose traffic directions' (S13). A failed search is not proof of absence. | R11: Mandatory route for tankers from North Hinder to the German Bight applies to oil tankers 10,000 GT and over, chemical/NLS tankers 5,000 GT (X/Y) or 10,000 GT (Z) and over, and gas carriers 10,000 GT and over (S1, annex 4). | S11: Intermediate | T11: Part of a multi-component routeing system linked to the IMO mandatory tanker route; no VTS or reporting identified. | U11: SRC-024; SRC-027; SRC-036; SRC-037; SRC-038; SRC-050 | V11: Duplicate/grouping: likely to merge with TSS-0051 under 'Off Vlieland, Vlieland North and Vlieland Junction'. Current Dutch legal text (puc.overheid.nl) returned HTTP 403.
A12: TSS-0051 | B12: B11 | C12: A | D12: Off Vlieland | E12: Off Vlieland (part of 'Off Vlieland, Vlieland North and Vlieland Junction') | F12: Netherlands | G12: Confirmed | H12: As TSS-0050: amended by COLREG.2/Circ.59, implemented 1 May 2008 (S1); single entry in Ships' Routeing 2008 (S27). MSC 109 containership recommendation covers 'Off Vlieland' from 1 July 2025 (lead S5). | I12: In force | J12: Off Vlieland; Vlieland North; Vlieland Junction | K12: Unresolved | M12: No Dutch VTS was found whose defined area covers this offshore scheme. The Netherlands Coastguard performs Vessel Traffic Monitoring (VTMon) and distinguishes VTS as provided by traffic centres (S14, S15); VTMon is recorded as a lead only, not as a VTS. | N12: Unresolved | P12: No IMO-adopted mandatory ship reporting system or national mandatory reporting specific to this scheme was found. Netherlands Coastguard states it 'has no powers to impose traffic directions' (S13). A failed search is not proof of absence. | Q12: Coastguard container-ship wave advice applies to the southern route north of the West Frisian Islands (S13); relationship to this specific scheme not stated. | R12: Mandatory route for tankers from North Hinder to the German Bight applies to oil tankers 10,000 GT and over, chemical/NLS tankers 5,000 GT (X/Y) or 10,000 GT (Z) and over, and gas carriers 10,000 GT and over (S1, annex 4). | S12: Intermediate | T12: Multi-component system, mandatory tanker route and containership recommendation; no VTS identified. | U12: SRC-024; SRC-027; SRC-028; SRC-036; SRC-037; SRC-038; SRC-050 | V12: Merge with TSS-0050. Text of the 2024 containership recommendation not retrieved.
A13: TSS-0052 | B13: B11 | C13: A | D13: Off Texel | E13: Off Texel | F13: Netherlands | G13: Confirmed | H13: Amended by COLREG.2/Circ.59 (implemented 1 May 2008) (S1); further amended by COLREG.2/Circ.64 (MSC 91, 2012), implemented 1 August 2013, per the Transportstyrelsen list (S4); Circ.64 text itself not retrieved. | I13: In force | K13: Unresolved | M13: No Dutch VTS was found whose defined area covers this offshore scheme. The Netherlands Coastguard performs Vessel Traffic Monitoring (VTMon) and distinguishes VTS as provided by traffic centres (S14, S15); VTMon is recorded as a lead only, not as a VTS. Den Helder port VTS not researched for coverage of this scheme. | N13: Unresolved | P13: No IMO-adopted mandatory ship reporting system or national mandatory reporting specific to this scheme was found. Netherlands Coastguard states it 'has no powers to impose traffic directions' (S13). A failed search is not proof of absence. | R13: Mandatory route for tankers from North Hinder to the German Bight applies to oil tankers 10,000 GT and over, chemical/NLS tankers 5,000 GT (X/Y) or 10,000 GT (Z) and over, and gas carriers 10,000 GT and over (S1, annex 4). | S13: Intermediate | T13: Linked to IMO mandatory tanker route; 2013 restructuring of Dutch routeing. | U13: SRC-024; SRC-027; SRC-037; SRC-038 | V13: Retrieve COLREG.2/Circ.64 (NOAA copy redirects; IMO copy not found). Check Den Helder VTS area against the scheme.
A14: TSS-0053 | B14: B11 | C14: A | D14: In the Approaches to IJmuiden | E14: In the approaches to IJmuiden | F14: Netherlands | G14: Confirmed | H14: New scheme adopted by MSC 91 and circulated as COLREG.2/Circ.64 (2012), implemented 1 August 2013, per Transportstyrelsen list (S4); associated precautionary areas in SN.1/Circ.317 (S4). Separate IMO deep-water route leading to IJmuiden listed in Ships' Routeing 2008 (S27). Circ.64 text not retrieved. | I14: In force | K14: Unresolved | L14: VTS-019 | M14: VTS North Sea Canal Area covers 'the approaches to IJmuiden ... within a 12-nautical-mile radius ... including the extended IJ-geul deep water channel' (S12). The source does not state that the TSS lanes lie within this area; the extended IJ-geul is a separate IMO deep-water route. VTS named as a strong lead; overlap with the TSS needs chart verification. | N14: Unresolved | P14: No IMO or national mandatory reporting system specific to the TSS found. Within the VTS area there are ordinary VTS reporting duties: report on arrival at 12 nm to Sector IJmuiden VHF 61 and to IJmuiden Approaches VHF 07 'as soon as VHF contact is possible' (S12). These are VTS reporting duties, recorded separately. | R14: VTS reporting and listening watch apply to vessels in the VTS area per S12. | S14: Intermediate | T14: TSS, deep-water route, precautionary areas and a port VTS with sector structure; overlap to be confirmed. | U14: SRC-027; SRC-035; SRC-050 | V14: Retrieve Circ.64 annex or chart INT 1418 to test whether any TSS lane lies within 12 nm of the breakwaters or on the extended IJ-geul. Dutch 2020 to 2023 Notices to Mariners (defensie.nl) returned 404.
A15: TSS-0054 | B15: B11 | C15: A | D15: Off Brown Ridge | F15: Netherlands (presumed) | G15: Provisional | H15: Existence of a TSS 'Off Brown Ridge' is indicated only by leads: Wikipedia list 'Brown Ridge' (S30) and search snippets describing a deep-water route linking TSS Off Brown Ridge to TSS West Friesland and the 1 August 2013 Dutch re-routeing. Not found in Ships' Routeing 2008 contents (S27) or Transportstyrelsen 2017 list (S4) as a separate entry; may be a component of 'Off Friesland' or of the 2013 Dutch routeing package. Adopting instrument not retrieved. | I15: Not established | K15: Unresolved | M15: No Dutch VTS was found whose defined area covers this offshore scheme. The Netherlands Coastguard performs Vessel Traffic Monitoring (VTMon) and distinguishes VTS as provided by traffic centres (S14, S15); VTMon is recorded as a lead only, not as a VTS. | N15: Unresolved | P15: No IMO-adopted mandatory ship reporting system or national mandatory reporting specific to this scheme was found. Netherlands Coastguard states it 'has no powers to impose traffic directions' (S13). A failed search is not proof of absence. | R15: Search snippet (lead) states it forms part of a mandatory route for some classes of vessels; not verified. | S15: Not assessed | T15: Identity not confirmed. | U15: SRC-027; SRC-050; SRC-053 | V15: Identify adopting instrument (possibly COLREG.2/Circ.64 or a 2012/2013 Dutch package); Dutch official texts on puc.overheid.nl blocked (HTTP 403); Dutch NtM 2017 no.183 returned 404.
A16: TSS-0055 | B16: B11 | C16: A | D16: West Friesland | E16: West Friesland scheme (part of routeing system 'Off Friesland') | F16: Netherlands | G16: Confirmed | H16: Component of the 'Off Friesland' routeing system; amended by COLREG.2/Circ.66 (MSC 94, 21 November 2014), implemented 1 June 2015 (S2), corrected by COLREG.2/Circ.66/Corr.1 (MSC 96, 2016, immediate effect) (S3). MSC 109 containership recommendation covers 'Off Friesland' from 1 July 2025 (lead S5). | I16: In force | J16: West Friesland; North Friesland; East Friesland; Off Botney Ground (per S1); deep-water routes of 'Off Friesland' | K16: Unresolved | M16: No Dutch VTS was found whose defined area covers this offshore scheme. The Netherlands Coastguard performs Vessel Traffic Monitoring (VTMon) and distinguishes VTS as provided by traffic centres (S14, S15); VTMon is recorded as a lead only, not as a VTS. | N16: Unresolved | P16: No IMO-adopted mandatory ship reporting system or national mandatory reporting specific to this scheme was found. Netherlands Coastguard states it 'has no powers to impose traffic directions' (S13). A failed search is not proof of absence. | R16: Western route of Off Friesland is strongly recommended for deep-draught tankers exempted from the southern part of the mandatory tanker route (S1). | S16: Intermediate | T16: Component of a multi-scheme routeing system with deep-water routes and tanker routeing provisions. | U16: SRC-024; SRC-025; SRC-026; SRC-028; SRC-037; SRC-038 | V16: Grouping: TSS-0055, TSS-0056, TSS-0057 and TSS-0058 appear to be components of the single IMO routeing system 'Off Friesland'; consider merging.
A17: TSS-0056 | B17: B12 | C17: A | D17: North Friesland | E17: North Friesland scheme (part of routeing system 'Off Friesland') | F17: Netherlands | G17: Confirmed | H17: Established within 'Off Friesland' by COLREG.2/Circ.66 (implemented 1 June 2015), with separation zones around 54° 00' to 54° 05' N, 004° 40' to 005° 06' E (S2, S3). Dutch offshore scheme, not the German North Frisian coast. Lead (search summary) says it replaced the Friesland Junction precautionary area; not verified in retrieved text. | I17: In force | J17: West Friesland; North Friesland; East Friesland | K17: Unresolved | M17: No Dutch VTS was found whose defined area covers this offshore scheme. The Netherlands Coastguard performs Vessel Traffic Monitoring (VTMon) and distinguishes VTS as provided by traffic centres (S14, S15); VTMon is recorded as a lead only, not as a VTS. | N17: Unresolved | P17: No IMO-adopted mandatory ship reporting system or national mandatory reporting specific to this scheme was found. Netherlands Coastguard states it 'has no powers to impose traffic directions' (S13). A failed search is not proof of absence. | S17: Intermediate | T17: Component of multi-scheme routeing system. | U17: SRC-025; SRC-026; SRC-037; SRC-038 | V17: Merge with TSS-0055/0057. Confirm fate of Friesland Junction precautionary area.
A18: TSS-0057 | B18: B12 | C18: A | D18: East Friesland | E18: East Friesland scheme (part of routeing system 'Off Friesland') | F18: Netherlands | G18: Confirmed | H18: Amended within 'Off Friesland' by COLREG.2/Circ.66 (implemented 1 June 2015) and Corr.1 (2016) (S2, S3). Dutch offshore scheme around 54° 02' to 54° 06' N, 005° 08' to 005° 10' E at its western boundary; not the German East Frisian coast. | I18: In force | J18: West Friesland; North Friesland; East Friesland | K18: Unresolved | M18: No Dutch VTS was found whose defined area covers this offshore scheme. The Netherlands Coastguard performs Vessel Traffic Monitoring (VTMon) and distinguishes VTS as provided by traffic centres (S14, S15); VTMon is recorded as a lead only, not as a VTS. | N18: Unresolved | P18: No IMO-adopted mandatory ship reporting system or national mandatory reporting specific to this scheme was found. Netherlands Coastguard states it 'has no powers to impose traffic directions' (S13). A failed search is not proof of absence. | S18: Intermediate | T18: Component of multi-scheme routeing system. | U18: SRC-025; SRC-026; SRC-037; SRC-038 | V18: Merge with TSS-0055/0056. Eastern extent (toward German EEZ) not verified.
A19: TSS-0058 | B19: B12 | C19: A | D19: Off Botney Ground | E19: Off Botney Ground (part of western route of routeing system 'Off Friesland') | F19: Netherlands (presumed; UK/NL boundary area not verified) | G19: Confirmed | H19: COLREG.2/Circ.59 names 'TSS Off Botney Ground' as part of the alternative western route of the routeing system 'Off Friesland' for deep-draught tankers (S1). Not a separate entry in Ships' Routeing 2008 contents (S27). Currency after 2015 not separately verified. | I19: In force | K19: Unresolved | M19: No Dutch VTS was found whose defined area covers this offshore scheme. The Netherlands Coastguard performs Vessel Traffic Monitoring (VTMon) and distinguishes VTS as provided by traffic centres (S14, S15); VTMon is recorded as a lead only, not as a VTS. | N19: Unresolved | P19: No IMO-adopted mandatory ship reporting system or national mandatory reporting specific to this scheme was found. Netherlands Coastguard states it 'has no powers to impose traffic directions' (S13). A failed search is not proof of absence. | R19: Deep-draught tankers exempted from the southern part of the mandatory tanker route are 'strongly recommended' to use this western route and log the deviation (S1). | S19: Intermediate | T19: Offshore component linked to tanker routeing provisions; State responsibility to confirm. | U19: SRC-024; SRC-050; SRC-053 | V19: Confirm coordinates and responsible State; confirm whether still in force after the 2015 Off Friesland amendments. Consider grouping with Off Friesland records.
A20: TSS-0059 | B20: B12 | C20: A | D20: Off Ushant (Île d'Ouessant) | E20: Off Ushant | F20: France | G20: Confirmed | H20: Amended by COLREG.2/Circ.51 (MSC 75), implemented 1 May 2003 (S18); further amended by COLREG.2/Circ.64 (MSC 91), implemented 1 June 2013 per search result (Circ.64 text not retrieved). French ministry 2024 confirms DST Ouessant under CROSS Corsen (S19). | I20: In force | K20: Confirmed present | L20: VTS-021 | M20: IMO MSC.52(66): OUESSREP area 'covers a circular area 35 miles in radius centred on the Ile d'Ouessant' and 'The TSS covers the entire area'; shore authority is the Corsen/Ouessant VTS 'Ushant Traffic' at CROSS Corsen, VHF 13 (S16). French ministry 2024: 'DST Ouessant : zone de compétences CROSS Corsen' (S19). | N20: Confirmed present | O20: SRS-009 | P20: OUESSREP, IMO-adopted SOLAS mandatory ship reporting system (MSC.52(66), amended MSC.251(83) in force 1 May 2008) covering the TSS (S16, S17); French 2024 publication confirms Channel CROSS monitor ships over 300 UMS 'soumis à un compte rendu obligatoire' (S19). | R20: Ships of more than 300 GRT (S16). Report content amended 2008 to include bunker quantity for ships carrying over 5,000 t bunkers (S17). | S20: Intermediate | T20: Single VTS with IMO mandatory reporting; well documented. | U20: SRC-039; SRC-040; SRC-041; SRC-042 | V20: A current CROSS Corsen or Premar Atlantique page with VHF channels was not retrieved; channels are from the 1996 IMO text.
A21: TSS-0060 | B21: B12 | C21: A | D21: Off Finisterre | E21: Off Finisterre | F21: Spain | G21: Confirmed | H21: Originally adopted by A.767(18) (cited in S20); amended by A.957(23), implemented 1 June 2004, adding lanes for ships carrying dangerous or pollutant cargoes in bulk (S21). Listed in Ships' Routeing 2008 (S27). | I21: In force | K21: Confirmed present | L21: VTS-022 | M21: MSC.63(67): FINREP area 'includes the traffic separation scheme "off Finisterre"' and ships 'shall report to the Finisterre Traffic VTS' (S20). The amended 2004 outer southbound lane reaches 010° 13.7' W (S21), slightly west of the 1996 FINREP limit (010° 10' W), so coverage of the outermost lane is not evidenced. | N21: Confirmed present | O21: SRS-010 | P21: FINREP, IMO-adopted mandatory SRS in force 3 June 1997 (S20). | R21: FINREP: ships of 50 m LOA or more; ships carrying hazardous or potentially polluting cargo; tows over 50 m; smaller vessels fishing in or using lanes in emergency (S20). Dangerous cargo ships use designated outer lanes (S21). | S21: Intermediate | T21: VTS with IMO mandatory reporting; cargo-based lane allocation; possible mismatch of FINREP limit with amended TSS. | U21: SRC-043; SRC-044; SRC-045; SRC-050 | V21: Salvamento Marítimo website returned HTTP 503/TLS failure, so current VTS name and VHF channel not confirmed from operator; only a 2025 news lead (S22). Check whether FINREP geographical limits were amended after 2004.
A22: TSS-0061 | B22: B13 | C22: A | D22: Off Cape Roca (Cabo da Roca) | E22: Off Cape Roca | F22: Portugal | G22: Confirmed | H22: Amended by MSC 79 (December 2004) with entry into force 1 July 2005 (S23 preamble) and again by COLREG.2/Circ.61 (MSC 87), implemented 1 December 2010 (S26). Established in Portuguese law as 'EST do cabo da Roca' (S23 art. 4). | I22: In force | K22: Confirmed present | L22: VTS-023 | M22: DL 263/2009 art. 6 defines the coastal VTS area (west limit 10° 14' W north of 38° 41' N) and art. 10(4) gives the CCTMC supervision of 'regras aplicáveis aos esquemas de separação de tráfego' (S24); DL 198/2006 art. 9 assigns TSS enforcement to the national VTS authority (S23). All Circ.61 positions of the scheme (westmost 010° 13.78' W) fall inside the statutory VTS area on coordinate comparison (S26). | N22: Confirmed present | O22: SRS-011 | P22: COPREP (MSC.278(85), in force 1 June 2009) area bounded west by 010° 14' W and to the south-west by the line 38° 41' N 010° 14' W to 36° 30' N 009° 35' W (S25); the scheme lies inside on coordinate comparison. Reports to Roca Control. | Q22: COPREP invites any other vessel type to participate voluntarily (S25). | R22: COPREP and VTS: ships of 300 GT or above, dangerous/polluting cargo, passenger ships, tows over 100 m, fishing vessels 24 m or more (S24, S25). Separate lanes for ships carrying dangerous or pollutant cargoes in bulk (S26). | S22: Intermediate | T22: Single national coastal VTS with IMO mandatory reporting and cargo-based lanes. | U22: SRC-046; SRC-047; SRC-048; SRC-049 | V22: DL 263/2009 cites IPTM; current operating authority (DGRM) not confirmed from a DGRM page. Coverage relies on coordinate comparison.
A23: TSS-0062 | B23: B13 | C23: A | D23: Off Cape St. Vicente (Cabo de São Vicente) | E23: Off Cape S. Vicente | F23: Portugal | G23: Confirmed | H23: Amended by MSC 79 (in force 1 July 2005) (S23 preamble) and COLREG.2/Circ.61, implemented 1 December 2010 (S26). 'EST do cabo de São Vicente' in Portuguese law (S23 art. 4). | I23: In force | K23: Confirmed present | L23: VTS-023 | M23: As TSS-0061: statutory VTS area and CCTMC duty to supervise TSS rules (S24 art. 6, 10(4)); DL 198/2006 art. 9 (S23). Circ.61 positions (around 36° 36' to 37° 02' N, 008° 58' to 009° 34' W for retrieved points) lie inside the VTS area line 38° 41' N 10° 14' W to 36° 30' N 9° 35' W on coordinate comparison (S26). | N23: Confirmed present | O23: SRS-011 | P23: COPREP area (S25) encloses the scheme on coordinate comparison; reports to Roca Control. | Q23: COPREP voluntary participation for other vessel types (S25). | R23: As TSS-0061. | S23: Intermediate | T23: As TSS-0061. | U23: SRC-046; SRC-047; SRC-048; SRC-049 | V23: Outermost southbound dangerous-cargo lane coordinates not all extracted; verify it lies east of the COPREP/VTS boundary.
A24: TSS-0063 | B24: B13 | C24: A | D24: At Banco del Hoyo | E24: At Banco del Hoyo | F24: Spain (presumed) | G24: Provisional | H24: Listed in IMO Ships' Routeing 2008 contents, Section II Western European waters, page II/32, after Off Cape S. Vicente (S27), and in Transportstyrelsen 2017 list as adopted by A.284(VIII) 1973 with no later amendment (S4). Location, coordinates and responsible State not retrieved. | I24: In force | K24: Unresolved | M24: Location not established, so no VTS coverage could be tested. Possible leads (not evidenced): Tarifa VTS / GIBREP if the scheme lies in the western approach to the Strait of Gibraltar, but GIBREP area is 005° 58' W to 005° 15' W only (MSC.63(67) annex 2, S20). | N24: Unresolved | P24: No reporting system linked; location not established. | S24: Not assessed | T24: Identity and location unresolved. | U24: SRC-027; SRC-043; SRC-050; SRC-053 | V24: Retrieve Ships' Routeing Part B II/32 or resolution A.284(VIII) to fix location; confirm whether still in force in 2026.
A25: TSS-0064 | B25: B13 | C25: A | D25: Between Grand Canary and Tenerife | E25: Western Traffic Separation Scheme (between Grand Canary and Tenerife), part of the Canary Islands schemes | F25: Spain | G25: Confirmed | H25: New scheme adopted by MSC 81 in COLREG.2/Circ.57 (26 May 2006), implemented 1 December 2006 (S28). Listed as 'Between Grand Canary and Tenerife' in Ships' Routeing 2008 (S27). | I25: In force | K25: Unresolved | M25: No designated VTS found. Primary sources name MRCC Tenerife as recipient of voluntary TSS notifications and CANREP reports (S28, S29), but describe it as an MRCC, not a VTS. MRCC recorded as lead (SVC-es-canarias-mrcc). | N25: Confirmed present | O25: SRS-012 | P25: CANREP area is a polygon along the outer limit of the territorial sea enclosing the archipelago, so inter-island waters including this scheme lie inside (S29, section 2.1). Applies only to specified heavy-oil tankers. | Q25: Ships may notify entry to and departure from the TSS via MRCC Tenerife on VHF 16 (S28). | R25: CANREP: tankers of 600 dwt and above carrying heavy crude, heavy fuel oil, bitumen or tar, transiting or trading inter-island (S29). | S25: Intermediate | T25: Narrow-scope IMO mandatory reporting plus voluntary TSS notification; no VTS. | U25: SRC-050; SRC-051; SRC-052 | V25: Check whether Salvamento Marítimo operates a VTS function for the Canary TSS (website unavailable). CANREP coverage of the TSS rests on the polygon description; the chartlet was not inspected.
A26: TSS-0065 | B26: B13 | C26: A | D26: Between Grand Canary and Fuerteventura | E26: Eastern Traffic Separation Scheme (between Grand Canary and Fuerteventura), part of the Canary Islands schemes | F26: Spain | G26: Confirmed | H26: New scheme in COLREG.2/Circ.57, implemented 1 December 2006 (S28); includes a precautionary area and inshore traffic zone. Listed in Ships' Routeing 2008 (S27). | I26: In force | K26: Unresolved | M26: As TSS-0064; MRCC Las Palmas receives voluntary notifications (S28); no VTS designation found. | N26: Confirmed present | O26: SRS-012 | P26: Inside the CANREP polygon (S29); ships entering east of 015° 30' W report to MRCC Las Palmas. | Q26: Ships may notify entry to and departure from the TSS via MRCC Las Palmas on VHF 16 (S28). | R26: CANREP: as TSS-0064. | S26: Intermediate | T26: As TSS-0064. | U26: SRC-050; SRC-051; SRC-052 | V26: As TSS-0064.
A27: TSS-0066 | B27: B14 | C27: B | D27: In the Strait of Gibraltar | E27: In the Strait of Gibraltar | F27: Spain, Morocco | G27: Confirmed | H27: Listed as amended scheme in COLREG.2/Circ.40 (implemented 24 Nov 1994) and COLREG.2/Circ.58 (MSC 82, implemented 1 July 2007); MSC.300(87) (2010) refers to the amended TSS within the GIBREP area. Earlier original adoption not traced. | I27: In force | K27: Confirmed present | L27: VTS-025; VTS-026 | M27: MSC.300(87) annex 3.5.1: both Tarifa and Tangier centres monitor navigation in the TSS using radar and AIS; S11 confirms CCS Tarifa ('Tarifa Tráfico') provides the maritime traffic service in the Strait. | N27: Confirmed present | O27: SRS-015 | P27: GIBREP area (005°58'W to 005°15'W) includes the amended TSS (MSC.300(87) annex 2.1). | R27: GIBREP: all ships of 300 GT and over; all ships carrying hazardous or potentially polluting cargo; towing/pushing; vessels under 300 GT using lanes to fish or the separation zone in emergency. Cross-Strait scheduled ferries may have special arrangements. | S27: Complex | T27: Two-State shared VTS and mandatory SOLAS V/11 reporting with direction-dependent reporting centres. | U27: SRC-054; SRC-055; SRC-056; SRC-059 | V27: Lead (news/petition, not primary) that Tarifa Tráfico functions were moved provisionally to CCS Algeciras; not verified because salvamentomaritimo.es returned HTTP 503. Current VHF channels should be rechecked against the latest ALRS/Spanish NtM.
A28: TSS-0067 | B28: B14 | C28: B | D28: Off Cabo de Gata | E28: Off Cabo de Gata | F28: Spain | G28: Confirmed | H28: New scheme in COLREG.2/Circ.44 (MSC 69, implemented 1 Dec 1998); amended by COLREG.2/Circ.57 (MSC 81, implemented 1 Dec 2006). Amended scheme includes an inshore traffic zone. | I28: In force | K28: Confirmed present | L28: VTS-027 | M28: S11 (Ministry of Transport, Feb 2025): Salvamento Marítimo is responsible for controlling traffic safety in the DST of Cabo de Gata; S12 (2015) counts vessels identified passing the Cabo de Gata DST. Controlling centre (CCS Almería) is lead only. | N28: Unresolved | P28: S11 states Spain's mandatory reporting systems are at Fisterra and the Strait of Gibraltar (plus Canarias PSSA) 'mientras que en el cabo de Gata existe un sistema de notificación voluntaria'. Absence of mandatory reporting positively stated by an official source. | Q28: Voluntary reporting system at Cabo de Gata (RPT-cabo-de-gata-voluntary); details not retrieved. | S28: Intermediate | T28: Single-State VTS monitoring with voluntary reporting only. | U28: SRC-054; SRC-056; SRC-057 | V28: Confirm centre name (CCS Almería), call sign and VHF channel from Salvamento Marítimo (site returned HTTP 503) or ALRS Vol 6. | W28: reporting_finding: Confirmed absent -> Unresolved. Absence rests on a Ministry of Transport magazine article, not a formal complete list. Record the voluntary Cabo de Gata system; confirm absence of mandatory reporting against ALRS Vol 6 or IMO SN.1/Circ.
A29: TSS-0068 | B29: B14 | C29: B | D29: Off Cape Palos (Cabo de Palos) | E29: Off Cape Palos | F29: Spain | G29: Confirmed | H29: New scheme in COLREG.2/Circ.52 (MSC 76, implemented 1 July 2003). S11 (2025) lists cabo de Palos among Spain's existing DSTs. | I29: In force | K29: Unresolved | L29: VTS-028 | M29: S11 lists the DSTs Salvamento Marítimo controls as Fisterra, Tarifa, Cabo de Gata and Canarias, omitting Cabo de Palos, but the same article also states generally that DSTs are controlled by VTS assigned to Salvamento Marítimo. No source establishes CCS Cartagena coverage of the TSS. | N29: Unresolved | P29: S11: 'En España existen sistemas de notificación obligatoria en Fisterra y en el estrecho de Gibraltar' (plus Canarias PSSA); Cabo de Palos not included. Moderate confidence: enumerative statement in an official publication rather than a formal complete list. | S29: Simple | T29: Single-State TSS, no mandatory reporting, VTS coverage unclear. | U29: SRC-054; SRC-056 | V29: Does CCS Cartagena monitor the Palos TSS? salvamentomaritimo.es (HTTP 503) and ALRS not accessible. | W29: reporting_finding: Confirmed absent -> Unresolved. Absence rests on an enumerative magazine statement (researcher rated moderate confidence). Not sufficient for Confirmed absent.
A30: TSS-0069 | B30: B14 | C30: B | D30: Off Cape la Nao (Cabo de la Nao) | E30: Off Cape La Nao | F30: Spain | G30: Confirmed | H30: New scheme in COLREG.2/Circ.52 (MSC 76, implemented 1 July 2003); reference chart Spanish IHM chart 47. S11 (2025) lists cabo de la Nao among Spain's DSTs. | I30: In force | K30: Unresolved | L30: VTS-029 | M30: As for Cabo de Palos: S11 omits La Nao from the DSTs Salvamento Marítimo controls; no source establishes CCS Valencia coverage. | N30: Unresolved | P30: S11 enumerates Spain's mandatory reporting systems (Fisterra, Gibraltar, Canarias PSSA); La Nao not included. Moderate confidence. | S30: Simple | T30: Single-State TSS, no mandatory reporting, VTS coverage unclear. | U30: SRC-054; SRC-056 | V30: Does CCS Valencia monitor the La Nao TSS? Primary Salvamento Marítimo pages not accessible (HTTP 503). | W30: reporting_finding: Confirmed absent -> Unresolved. Absence rests on an enumerative magazine statement (researcher rated moderate confidence). Not sufficient for Confirmed absent.
A31: TSS-0070 | B31: B14 | C31: B | D31: Off Cani Island (Îles Cani) | E31: North of Cani Island (Off Cani Island) | F31: Tunisia | G31: Confirmed | H31: Tunisian scheme (Îles Cani, off Bizerte coast), not the Bonifacio Strait. Amended by COLREG.2/Circ.58 (MSC 82, implemented 1 July 2007) together with Off Cape Bon; reference chart 150-DST of the Tunisian Hydrographic and Oceanographic Service. Original scheme reported operating since 1 Aug 1970 (search snippet from NOAA document, lead only). | I31: In force | K31: Unresolved | M31: No Tunisian VTS or traffic monitoring centre covering the scheme found; searches returned only general coastal surveillance (RMAC) news. | N31: Unresolved | P31: No IMO-adopted SRS for the area in S14 list; national reporting not researched to a primary source. | S31: Simple | T31: Single-State TSS with no identified VTS or reporting. | U31: SRC-054; SRC-059 | V31: Tunisian Marine Marchande / SHOM Tunisie sources not found online. Region hint linking Cani Island to BONIFREP is wrong: BONIFREP (MSC.73(69)) is Corsica/Sardinia and not relevant here.
A32: TSS-0071 | B32: B15 | C32: B | D32: Off Cape Bon (Cap Bon) | E32: North of Cape Bon (Off Cape Bon) | F32: Tunisia | G32: Confirmed | H32: Amended by COLREG.2/Circ.58 (MSC 82, implemented 1 July 2007) with Off Cani Island; reference chart 150-DST (Tunisia). Original scheme reported operating since 1 Aug 1970 (lead only). | I32: In force | K32: Unresolved | M32: No Tunisian VTS covering the scheme found. | N32: Unresolved | P32: No IMO-adopted SRS listed for the area (S14); national reporting not established. | S32: Simple | T32: Single-State TSS with no identified VTS or reporting. | U32: SRC-054; SRC-059 | V32: As for TSS-0070; Italian VTS/Pantelleria-Sicily Channel arrangements not researched (outside scheme).
A33: TSS-0072 | B33: B15 | C33: B | D33: In the Corsica Channel | E33: In the Corsica Channel | F33: France, Italy | G33: Confirmed | H33: New scheme in COLREG.2/Circ.67 (MSC 96, implemented 1 Dec 2016), between Cap Corse and Isola Capraia, with ITZ along the Corsican coast; reference charts SHOM 7013 and IIM 40. | I33: In force | K33: Unresolved | M33: Italian Guardia Costiera lists 11 VTS centres (S18, S19); none (Livorno not among them) is shown to cover the Corsica Channel. French coverage (CROSS MED) not researched to primary; CROSS is not a VTS. | N33: Unresolved | P33: No IMO SRS for the Corsica Channel in S14 (2017 list); any later measure or national reporting not found. | S33: Intermediate | T33: Bi-national scheme; no identified VTS, possible national arrangements. | U33: SRC-054; SRC-063; SRC-064; SRC-059 | V33: Italian MIT page on the 2015 Italy-France agreement (mit.gov.it/node/298) returned HTTP 503. Check whether a Livorno VTS has since been activated and whether France/Italy require reporting.
A34: TSS-0073 | B34: B15 | C34: B | D34: In the Adriatic Sea: In the North Adriatic Sea | E34: In the North Adriatic Sea (eastern part and western part), part of 'In the Adriatic Sea' | F34: Italy, Croatia (with Slovenia in the wider system) | G34: Confirmed | H34: Adopted in COLREG.2/Circ.54 annex 3 (MSC 78, implemented 1 Dec 2004); western part amended by COLREG.2/Circ.58 (implemented 1 July 2007). Includes precautionary area at southern limits. | I34: In force | J34: In the North Adriatic Sea - Eastern part; In the North Adriatic Sea - Western part; Precautionary area at the southern limits | K34: Unresolved | L34: VTS-033 | M34: S20: VTS Croatia supervises application of the Adriatic TSS of COLREG.2/Circ.54 and 58 'u VTS području' (area incl. territorial sea and ZERP). Whether each component lies within the Croatian VTS area was not verified; no Italian VTS area covers this offshore scheme. | N34: Confirmed present | O34: SRS-016 | P34: ADRIREP covers the whole Adriatic north of 40°25'N (S13), which includes this scheme. | R34: ADRIREP (revised, from 1 Dec 2026): oil tankers 150 GT and above, ships 10,000 GT and above, any ship carrying hazardous cargo. | S34: Complex | T34: Multi-State offshore scheme under a multi-authority mandatory reporting system. | U34: SRC-054; SRC-058; SRC-065 | V34: Plot components against Croatian ZERP/VTS chart 950 VTS to confirm coverage; confirm whether 2015 Croatian VTS description remains current. Later Adriatic TSS amendments after 2016 not checked (compilation ends c. Circ.68).
A35: TSS-0074 | B35: B15 | C35: B | D35: In the Adriatic Sea: Approaches to the Gulf of Trieste | E35: Approaches to Gulf of Trieste | F35: Italy, Slovenia, Croatia | G35: Confirmed | H35: Component of 'In the Adriatic Sea', COLREG.2/Circ.54 annex 3 (implemented 1 Dec 2004); separation line 45°07'.50N 013°00'.37E to 45°19'.00N 012°56'.87E. | I35: In force | K35: Unresolved | L35: VTS-033 | M35: Scheme lies offshore south-west of Istria, outside the VTS Trieste and Koper areas (S15, S16). VTS Croatia supervises Circ.54 schemes within its area (S20) but location of this component relative to that area not verified. | N35: Confirmed present | O35: SRS-016 | P35: Within ADRIREP area (whole Adriatic north of 40°25'N). | R35: ADRIREP categories as in RPT-adrirep. | S35: Complex | T35: Multi-State approach scheme; VTS responsibility unclear; mandatory ADRIREP. | U35: SRC-054; SRC-058; SRC-065 | V35: Confirm which State's waters and VTS area contain this component.
A36: TSS-0075 | B36: B15 | C36: B | D36: In the Adriatic Sea: Approaches to the Gulf of Venice | E36: Approaches to Gulf of Venice | F36: Italy | G36: Confirmed | H36: Component of 'In the Adriatic Sea', COLREG.2/Circ.54 annex 3 (implemented 1 Dec 2004); separation zone amended by COLREG.2/Circ.58 (implemented 1 July 2007). | I36: In force | K36: Confirmed present | L36: VTS-032 | M36: Direct approach: TSS northern terminus (c. 45°10'-45°14'N, 012°29'-012°39'E, S4) adjoins the Venice VTS area outer limit B-C (45°08.4'N 012°25.7'E to 45°16.0'N 012°35.0'E, S17), and participating vessels must call Venice VTS 5 NM outside that limit, i.e. while in the TSS. Coverage inferred by comparing coordinates from two primary sources; the manual does not say in words that the VTS covers the TSS. | N36: Confirmed present | O36: SRS-016 | P36: Within ADRIREP area; Venice MRSC and VTS Venezia are ADRIREP authorities (S13, S17). | R36: Venice VTS participation mandatory for vessels of 300 GT and upwards (S17); ADRIREP categories as in RPT-adrirep. | S36: Intermediate | T36: Single-State approach scheme leading to a mandatory VTS, plus ADRIREP. | U36: SRC-054; SRC-058; SRC-062; SRC-063 | V36: Venice manual dated 2017; check current edition. Reviewer to confirm the direct-approach judgement.
A37: TSS-0076 | B37: B16 | C37: B | D37: In the Adriatic Sea: In the Gulf of Trieste and approaches to/from Koper | E37: In the Gulf of Trieste; Approaches to/from Koper (with precautionary area in the Gulf of Trieste) | F37: Slovenia, Italy (Croatia party to trilateral scheme) | G37: Confirmed | H37: Components of 'In the Adriatic Sea', COLREG.2/Circ.54 annex 3 (implemented 1 Dec 2004). Label groups two schemes plus a precautionary area. | I37: In force | J37: In the Gulf of Trieste; Approaches to/from Koper; Precautionary area in the Gulf of Trieste | K37: Confirmed present | L37: VTS-030; VTS-031 | M37: Koper VTS manual section 7.1 describes both TSS and requires vessels in its area to use the lanes (S15). VTS Trieste manual: 'Nell'Area VTS di Trieste è ricompreso lo schema obbligatorio di separazione del traffico ... Golfo di Trieste' (S16). Each covers the part within its national waters. | N37: Confirmed present | O37: SRS-016 | P37: Within ADRIREP area; MRCC Koper and VTS Trieste are ADRIREP authorities (S13). Separate mandatory VTS reports to Koper VTS (entry/exit, 1 h before entry) and VTS Trieste are VTS duties, not separate schemes. | R37: Koper VTS: ships of 300 GT and upwards; fishing, traditional and recreational craft of 45 m and upwards; warships and government vessels exempt. VTS Trieste: 300 GT and over; pleasure/traditional craft 45 m and over. | S37: Complex | T37: Three-State area with two national VTS and ADRIREP. | U37: SRC-054; SRC-058; SRC-060; SRC-061 | V37: Croatian role (VTS Croatia/Umag) in the Gulf of Trieste not checked.
A38: TSS-0077 | B38: B16 | C38: B | D38: In the Adriatic Sea: Approaches to/from Monfalcone | E38: Approaches to/from Monfalcone | F38: Italy | G38: Confirmed | H38: Component of 'In the Adriatic Sea', COLREG.2/Circ.54 annex 3 (implemented 1 Dec 2004); amended scheme per COLREG.2/Circ.58 referenced in VTS Trieste manual. | I38: In force | K38: Confirmed present | L38: VTS-031 | M38: VTS Trieste area limits were set taking account of the TSS 'nella parte finale di ingresso/uscita dal porto di Monfalcone', and the manual states the Monfalcone TSS is included within the VTS area (S16). | N38: Confirmed present | O38: SRS-016 | P38: Within ADRIREP area; VTS Trieste is an ADRIREP authority (S13). | R38: VTS Trieste participation mandatory for ships of 300 GT and over etc. | S38: Intermediate | T38: Single VTS plus ADRIREP. | U38: SRC-054; SRC-058; SRC-061 | V38: Confirm whether all of the Monfalcone TSS or only its final part lies in the VTS area.
A39: TSS-0078 | B39: B16 | C39: B | D39: Saronicos Gulf (Saronikós Kólpos, in the Approaches to Piraiévs) | E39: Saronicos Gulf | F39: Greece | G39: Provisional | H39: Existence as an IMO-adopted TSS evidenced by the 1991 COLREG.2 circular cancelling its inshore traffic zone (implemented 19 April 1991); original adoption instrument and current status not verified. | I39: In force | K39: Unresolved | L39: VTS-035 | M39: Lead only (S24): VTS in Piraeus linked to national VTMIS covering the wider Piraeus sea area. No primary source on VTS area or TSS coverage (hcg.gr HTTP 403). | N39: Unresolved | P39: No IMO SRS for Greece in S14; Greek national VTS participation rules seen only in search snippets (lead). | S39: Intermediate | T39: Busy port approach likely with VTS; evidence incomplete. | U39: SRC-054; SRC-068; SRC-069 | V39: Obtain Hellenic Coast Guard VTS Piraeus regulation/ALRS entry; confirm TSS still current in Ships' Routeing (operational status provisional).
A40: TSS-0079 | B40: B16 | C40: B | D40: In the approaches to the port of Thessaloníki | E40: In the approaches to the Port of Thessaloniki | F40: Greece | G40: Confirmed | H40: New scheme in COLREG.2/Circ.60 (MSC 85, implemented 1 June 2009). | I40: In force | K40: Unresolved | M40: No source found for a Thessaloniki VTS; lead S24 lists Greek VTS at Piraeus, Patras, Igoumenitsa and Kerkyra only (undated, not primary). | N40: Unresolved | P40: No IMO SRS; national reporting not established. | S40: Simple | T40: Single-State port approach TSS; VTS status unknown. | U40: SRC-054; SRC-068; SRC-069 | V40: Check Hellenic Coast Guard for any Thessaloniki VTS (planned or operational) and port reporting duties.
A41: TSS-0080 | B41: B16 | C41: B | D41: Strait of Istanbul - North Approach | E41: Strait of Istanbul - North Approach | F41: Turkey | G41: Confirmed | H41: Adopted by MSC 63, COLREG.2/Circ.40 (implemented 24 Nov 1994), together with 'Strait of Istanbul', 'Strait of Istanbul - South Approach and Sea of Marmara', 'Strait of Canakkale' and its South-West Approach. National regulation (2019) Art. 4 sets the TSS limits in the north at 41°20'.944 N. This record covers the North Approach only; linked components to be resolved in their own records. | I41: In force | K41: Confirmed present | L41: VTS-034 | M41: Turkish Straits Maritime Traffic Regulation 2019, Art. 4-5: TSS in the Turkish Straits and their approaches (northern limit 41°20'.944 N) with TBGTH established for application and supervision of the TSS and reporting system; S21 confirms TSVTS operational since 2003 with İstanbul centre. | N41: Confirmed present | O41: SRS-017 | P41: Regulation Art. 7: SP-2 2 h or 20 NM before entering the Istanbul Strait and position report 5 NM before the entrance, i.e. in the North Approach. National mandatory system, not IMO-adopted. | R41: SP-1: ships carrying dangerous cargo and ships of 500 GT and over (24 h before entry); position and calling-in point reports: ships of 20 m and over. | S41: Complex | T41: Linked multi-segment strait regime with national VTS, mandatory national reporting and Montreux Convention context. | U41: SRC-054; SRC-066; SRC-067; SRC-059 | V41: Sector names/channels (Türkeli etc.) not confirmed from a primary source; Regulation read from scanned Resmî Gazete images (pages 2, 3, 5 only); 2020 amendments not checked.
A42: TSS-0081 | B42: B17 | C42: C | D42: Strait of Istanbul | E42: Strait of Istanbul | F42: Türkiye | G42: Confirmed | H42: Adopted by MSC 63 (May 1994), COLREG.2/Circ.40 item .3, implemented 0000 UTC 24 November 1994; companion schemes 'Strait of Istanbul - North Approach' (item .2) and 'South Approach and Sea of Marmara' (item .4) are separate IMO entries. Associated Rules and Recommendations confirmed by A.827(19). Nationally reproduced in 2019 Turkish Straits Maritime Traffic Regulation Annex 1 (English text lead only). | I42: In force | J42: Strait of Istanbul (COLREG.2/Circ.40 item .3); Possible overlap with Strait of Istanbul - North Approach (item .2), not listed separately in this group | K42: Confirmed present | L42: VTS-034 | M42: KEGM states the TSVTS serves the Istanbul Strait, Marmara Sea and Çanakkale Strait, and was extended in 2008 to cover the Marmara TSS. | N42: Confirmed present | O42: SRS-017 | P42: Implementing Directive Art. 12: ships wishing to transit the Straits must submit SP-1 via the Administration's system; non-compliance leads to administrative action and loss of transit turn. IMO A.827(19) strongly recommends TUBRAP participation. | Q42: At IMO level TUBRAP participation is 'strongly recommended' (A.827(19)); nationally mandatory. | R42: Per unofficial English translation (lead only): SP-1 for ships with dangerous cargo or 500 GRT and over at least 24 h before arrival; SP-2 2 h or 20 NM before entrance; position report 5 NM before entrance and calling point reports for LOA 20 m and over; MARRAP for Marmara traffic. Daylight transit advised for draught 15 m+ or LOA over 200 m (A.827(19)). | S42: Complex | T42: Montreux Convention regime, national mandatory reporting layered on IMO recommendatory rules, one-way traffic and pilotage rules, multiple linked schemes. | U42: SRC-066; SRC-070; SRC-071; SRC-072; SRC-073; SRC-054 | V42: Official Gazette PDF (resmigazete.gov.tr) and mevzuat.gov.tr timed out, so the official Turkish regulation text was not read; English text is an unofficial copy. Confirm whether the source label also covers the North Approach scheme. VTS sector VHF channels not confirmed from a primary page.
A43: TSS-0082 | B43: B17 | C43: C | D43: Strait of Istanbul - South Approach and Sea of Marmara | E43: Strait of Istanbul - South Approach and Sea of Marmara | F43: Türkiye | G43: Confirmed | H43: COLREG.2/Circ.40 item .4, implemented 0000 UTC 24 November 1994. 2019 national regulation Annex 1.3 'Istanbul Strait Southern Approach and Marmara Sea' (English text lead only). | I43: In force | J43: Istanbul Strait southern approach; Marmara Sea TSS | K43: Confirmed present | L43: VTS-034 | M43: KEGM (Turkish page) states TBGTH was extended in 2008 to include the Marmara Sea 'Trafik Ayırım Düzeni'; Implementing Directive Art. 18 addresses ships in the Marmara TSS under TBGTH coordination. | N43: Confirmed present | O43: SRS-017 | P43: Implementing Directive Art. 12: ships wishing to transit the Straits must submit SP-1 via the Administration's system; non-compliance leads to administrative action and loss of transit turn. IMO A.827(19) strongly recommends TUBRAP participation. Marmara-specific MARRAP and 6 h pre-departure SP-1 for Marmara ports appear only in the unofficial translation. | Q43: IMO level: strongly recommended (A.827(19)). | R43: Per unofficial English translation (lead only): SP-1 for ships with dangerous cargo or 500 GRT and over at least 24 h before arrival; SP-2 2 h or 20 NM before entrance; position report 5 NM before entrance and calling point reports for LOA 20 m and over; MARRAP for Marmara traffic. Daylight transit advised for draught 15 m+ or LOA over 200 m (A.827(19)). | S43: Complex | T43: Long TSS through Marmara linking both straits, national rules on breakdowns in TSS, MARRAP sub-reporting. | U43: SRC-066; SRC-070; SRC-071; SRC-072; SRC-073; SRC-054 | V43: Official Turkish regulation text not retrieved (site timeout).
A44: TSS-0083 | B44: B17 | C44: C | D44: Strait of Canakkale | E44: Strait of Canakkale | F44: Türkiye | G44: Confirmed | H44: COLREG.2/Circ.40 item .5, implemented 0000 UTC 24 November 1994; national Annex 1.4 (English text lead only). | I44: In force | K44: Confirmed present | L44: VTS-034 | M44: KEGM states the TSVTS serves the Istanbul Strait, Marmara Sea and Çanakkale Strait, and was extended in 2008 to cover the Marmara TSS. Akbaş (Çanakkale) VTS centre. | N44: Confirmed present | O44: SRS-017 | P44: Implementing Directive Art. 12: ships wishing to transit the Straits must submit SP-1 via the Administration's system; non-compliance leads to administrative action and loss of transit turn. IMO A.827(19) strongly recommends TUBRAP participation. | Q44: IMO level: strongly recommended (A.827(19)). | R44: Per unofficial English translation (lead only): SP-1 for ships with dangerous cargo or 500 GRT and over at least 24 h before arrival; SP-2 2 h or 20 NM before entrance; position report 5 NM before entrance and calling point reports for LOA 20 m and over; MARRAP for Marmara traffic. Daylight transit advised for draught 15 m+ or LOA over 200 m (A.827(19)). | S44: Complex | T44: As for Istanbul Strait: national mandatory reporting, pilotage and transit rules. | U44: SRC-066; SRC-071; SRC-072; SRC-073; SRC-054 | V44: VHF sector channels (Gelibolu, Nara, Kumkale) only from search snippets.
A45: TSS-0084 | B45: B17 | C45: C | D45: Strait of Canakkale - South-west Approach | E45: Strait of Canakkale - South-West Approach | F45: Türkiye | G45: Confirmed | H45: COLREG.2/Circ.40 item .6, implemented 0000 UTC 24 November 1994; national Annex 1.5 'Canakkale Strait Southwestern Approaches' (English text lead only). | I45: In force | K45: Unresolved | L45: VTS-034 | M45: TSVTS confirmed for the Çanakkale Strait, but no primary source retrieved defines the VTS area as extending over the south-west approach. Unofficial translation places the regulation's southern boundary at about 39°44'N, beyond the approach scheme (lead only). | N45: Unresolved | O45: SRS-017 | P45: TUBRAP applies to ships transiting the Straits (primary). That SP-2 is given 20 NM before the entrance, i.e. in the approach, comes only from the unofficial translation. | R45: Per unofficial English translation (lead only): SP-1 for ships with dangerous cargo or 500 GRT and over at least 24 h before arrival; SP-2 2 h or 20 NM before entrance; position report 5 NM before entrance and calling point reports for LOA 20 m and over; MARRAP for Marmara traffic. Daylight transit advised for draught 15 m+ or LOA over 200 m (A.827(19)). | S45: Intermediate | T45: Approach scheme; VTS and TUBRAP coverage very likely but not evidenced by a primary spatial definition. | U45: SRC-066; SRC-071; SRC-073; SRC-054 | V45: Obtain official regulation text or Turkish NtM chartlet showing TBGTH area limits and reporting points in the SW approach.
A46: TSS-0085 | B46: B17 | C46: C | D46: In the Approaches to the Ports of Odessa and Ilichevsk | E46: In the approaches to the ports of Odessa and Ilichevsk (historical); now part of 'Approaches to the Chornomorsk, Odesa and Pivdennyi ports' | F46: Ukraine | G46: Confirmed | H46: Adopted by IMCO/IMO, COLREG.2/Circ.14 of 22 April 1981 (Marad and scanned circular). Ilichevsk renamed Chornomorsk. Per secondary summary of COLREG.2/Circ.78 (MSC 106, issued 13 December 2022), replaced by the amended scheme 'Approaches to the Chornomorsk, Odesa and Pivdennyi ports', implemented 0000 UTC 1 June 2023. Marad primary confirms Ukraine's proposal to merge the two schemes; IMO circular text not itself retrieved. | I46: Withdrawn/superseded | K46: Unresolved | L46: VTS-036 | M46: USPA confirms a 'VTCP Odesa' operated by Delta-Lotsman; Marad refers to 'The VTS of ... Delta Pilot' in proposing TSS changes, but no source defines the VTS area as covering the scheme. Wartime corridor arrangements apply (2022 notice). | N46: Unresolved | P46: No reporting system identified for the scheme in retrieved sources. | S46: Complex | T46: Superseded scheme, renamed ports, successor scheme, conflict-affected area with wartime corridor procedures. | U46: SRC-075; SRC-076; SRC-077; SRC-054 | V46: Retrieve COLREG.2/Circ.78 from IMO directly; recommend the guide records the successor scheme instead. Confirm VTCP Odesa area, VHF channel and any mandatory reporting under current Ukrainian port rules.
A47: TSS-0086 | B47: B18 | C47: C | D47: Between the Ports of Odessa and Ilichevsk | E47: Between the ports of Odessa and Ilichevsk (historical); now part of 'Approaches to the Chornomorsk, Odesa and Pivdennyi ports' | F47: Ukraine | G47: Confirmed | H47: Adopted per COLREG.2/Circ.14 (22 April 1981). Replaced with effect from 1 June 2023 by the combined amended scheme under COLREG.2/Circ.78 (secondary summary; Marad primary confirms merger proposal). | I47: Withdrawn/superseded | K47: Unresolved | L47: VTS-036 | M47: As TSS-0085: VTCP Odesa exists, coverage of this scheme not evidenced. | N47: Unresolved | P47: No reporting system identified. | S47: Complex | T47: Superseded and merged scheme in a conflict-affected area. | U47: SRC-075; SRC-076; SRC-077; SRC-054 | V47: Merge with TSS-0085 as one successor record.
A48: TSS-0087 | B48: B18 | C48: C | D48: In the area Off the South-western Coast of the Crimea | E48: In the area off the south-western coast of the Crimea | F48: Ukraine (proposing State; reference chart by State Hydrographic Service of Ukraine). Area temporarily occupied by the Russian Federation according to Ukraine and UNGA resolution 73/263 (as cited by Ukraine); control disputed | G48: Confirmed | H48: New scheme adopted at MSC 87, COLREG.2/Circ.61 (1 June 2010), implemented 0000 UTC 1 December 2010. Two parts: Routeing System No.9 'Sevastopol Harbour Approach' and No.3 'From Cape Khersones to Cape Aitodor'. No IMO revocation found in retrieved sources. | I48: Not established | J48: Sevastopol Harbour Approach (Routeing System No.9); From Cape Khersones to Cape Aitodor (Routeing System No.3) | K48: Unresolved | M48: No VTS source retrieved. Any service in this area would be operated by authorities whose jurisdiction is disputed; not assessed. | N48: Unresolved | P48: No reporting system identified. | R48: Ukraine told IMO (CL 4508, Feb 2022) and IHO (2021) that the Russian Federation interfered with or disabled use of these IMO schemes through closures of areas. The scheme remains an IMO-adopted measure on the evidence found; this record does not assert that it can currently be used safely. | S48: Complex | T48: Disputed, conflict-affected area; IMO measure whose practical functioning is reported as disrupted; competing claims of authority. | U48: SRC-049; SRC-078; SRC-079 | V48: Check latest IMO Ships' Routeing edition and any MSC decisions for current status; check navigational warnings (NAVAREA III) for closures. Editorial neutrality review required.
A49: TSS-0088 | B49: B18 | C49: C | D49: In the Southern Approaches to the Kerch Strait | E49: In the southern approaches to the Kerch Strait | F49: Originally adopted on USSR chart basis; coastal States Ukraine and the Russian Federation; Crimean coast control disputed (Ukraine regards it as temporarily occupied) | G49: Confirmed | H49: New scheme adopted by resolution A.374(X), 14 November 1977 (reference chart USSR No.514). Implementation date 15 May 1978 is a search-snippet lead only. Ukraine's IMO Circular Letter 4508 calls it 'Approaches to the Kerch Strait from the South', approved by IMO. No revocation found. | I49: Not established | K49: Unresolved | M49: No VTS source retrieved for the southern approaches; any service would be subject to the jurisdictional dispute. Not assessed. | N49: Unresolved | P49: No reporting system identified. | R49: Ukraine reports (CL 4508) that the Russian Federation interfered with the functioning of this IMO scheme and closed parts of the Kerch Strait area. This record does not assert current safe operation. | S49: Complex | T49: Disputed and conflict-affected; access restrictions reported; competing authorities. | U49: SRC-074; SRC-078; SRC-079 | V49: Confirm implementation date and any later amendment; review IMO and NAVAREA III status. Editorial neutrality review required.
A50: TSS-0089 | B50: B18 | C50: C | D50: Off the Mediterranean Coast of Egypt | E50: Off the Mediterranean coast of Egypt | F50: Egypt | G50: Confirmed | H50: New scheme adopted at MSC 75, COLREG.2/Circ.51 (31 May 2002), implemented 0000 UTC 1 December 2002. Comprises approach schemes to Damietta (Mina Dumyat) and Port Said (Bur Said) with two precautionary areas. | I50: In force | J50: Western Approach to Mina Dumyat; Precautionary area north Dumyat; Eastern Approaches to Mina Dumyat; Western Approaches to Bur Said; Eastern Approach to Bur Said; Precautionary area north west Bur Said | K50: Unresolved | M50: No primary source retrieved. Leads (search snippets only): Port Said port control on VHF 12; Damietta Port VTMS. Suez Canal Authority navigation pages fetched had no VTMS content. | N50: Unresolved | P50: No reporting system identified. | S50: Intermediate | T50: Grouped scheme serving two major ports and Suez Canal northern approach; several possible port and canal services. | U50: SRC-041 | V50: Obtain Suez Canal Authority Rules of Navigation (Port Said approach reporting) and Damietta Port Authority VTS details.
A51: TSS-0090 | B51: B18 | C51: C | D51: Off Alphard Banks, 34 miles south of Cape Infanta | E51: Off Alphard Banks 34 miles south of Cape Infanta | F51: South Africa | G51: Confirmed | H51: New scheme adopted at MSC 69, COLREG.2/Circ.44 (May 1998) Annex 9 'Off the south coast of South Africa', implemented 0000 UTC 1 December 1998. Charts on Cape Datum. | I51: In force | K51: Unresolved | M51: No VTS evidenced for this offshore area; port VTS services not shown to extend here. | N51: Unresolved | P51: SASAR Regulations 2016 reg. 30 require a ship reporting system to be established (general SAR reporting, not TSS-specific); SAMSA MN 13/2017 imposes reporting for compromised vessels in SA waters. Neither is a TSS reporting system. | Q51: Lead: South African ship reporting for SAR purposes (name and participation not confirmed). | S51: Simple | T51: Single offshore scheme around an offshore hazard; no evidenced VTS or reporting. | U51: SRC-054; SRC-081; SRC-082 | V51: Confirm whether any SAMSA/Transnet VTS or coastal surveillance covers the area; confirm current name and status of the SA ship reporting system (SAFREP lead).
A52: TSS-0091 | B52: B19 | C52: C | D52: Off the FA Platform, 47 miles south of Mossel Bay | E52: Off the FA Platform 47 miles south of Mossel Bay | F52: South Africa | G52: Confirmed | H52: New scheme adopted at MSC 69, COLREG.2/Circ.44 Annex 9, implemented 0000 UTC 1 December 1998. | I52: In force | K52: Unresolved | M52: No VTS evidenced; Mossel Bay port services not shown to cover a scheme 47 NM offshore. | N52: Unresolved | P52: As TSS-0090. | S52: Simple | T52: Single offshore platform scheme. | U52: SRC-054; SRC-081; SRC-082 | V52: Check whether the FA platform remains in place (scheme purpose) and whether South Africa has proposed amendment or revocation.
A53: TSS-0092 | B53: B19 | C53: C | D53: In the Gulf of Suez | E53: In the Gulf of Suez | F53: Egypt | G53: Confirmed | H53: New scheme adopted by resolution A.374(X) (14 November 1977); amended scheme adopted at MSC 67, COLREG.2/Circ.42 (2 January 1997), implemented 1 July 1997. Compilation notes associated 'Rules for ships navigating in the Gulf of Suez' (MSC 46/19). Earlier amendments also appear in the compilation. | I53: In force | K53: Unresolved | L53: VTS-037 | M53: Only trade press (2002) describes a Gulf of Suez VTIMS with two centres on the Gulf; no current Egyptian primary source retrieved. | N53: Unresolved | P53: No reporting system identified; Suez Canal Authority rules not retrieved. | S53: Intermediate | T53: Long TSS with associated rules, oil field traffic, adjoining Suez Canal southern approach. | U53: SRC-054; SRC-074; SRC-080 | V53: Identify the current Egyptian authority and VTS (Egyptian Authority for Maritime Safety or Ports and Lighthouses successor) and any Gulf of Suez reporting requirement.
A54: TSS-0093 | B54: B19 | C54: C | D54: In the Entrance to the Gulf of Aqaba | E54: In the entrance to the Gulf of Aqaba | F54: Egypt (implementing Government per IMO); adjoining Saudi Arabia | G54: Confirmed | H54: New scheme adopted at MSC 61 (December 1992), COLREG.2/Circ.39; implemented 0000 UTC 1 October 1993 after Egypt confirmed survey of Grafton Passage and aids (Circ.39/Add.1). Nearby areas to be avoided north of the Strait of Tiran and at Ras Mohammed adopted by A.827(19). | I54: In force | K54: Unresolved | M54: No VTS source retrieved for the Strait of Tiran entrance. | N54: Unresolved | P54: No reporting system identified. | R54: Associated ATBAs (A.827(19)): ships carrying dangerous or toxic cargoes or exceeding 500 GT should avoid specified areas north of Tiran and at Sharm El Sheikh / Ras Mohammed. | S54: Intermediate | T54: Multi-State approaches (Egypt, Saudi Arabia, Jordan and Israel ports in the Gulf) and associated ATBAs. | U54: SRC-054; SRC-072 | V54: Check for any Egyptian or Saudi VTS coverage at Tiran and any reporting requirement for Gulf of Aqaba traffic.
A55: TSS-0094 | B55: B19 | C55: C | D55: In the Southern Red Sea - West and South of Hanish al Kubra | E55: In the Southern Red Sea: west and south of Hanish al Kubra Island | F55: Yemen (Hanish islands; proposing Government not stated in the retrieved circular) | G55: Confirmed | H55: New scheme adopted at MSC 76, COLREG.2/Circ.52 (6 January 2003) Annex 1, implemented 0000 UTC 1 July 2003. Annex 1 contains two schemes (this and east of Jabal Zuqar, TSS-0095). | I55: In force | K55: Unresolved | M55: No VTS source retrieved. | N55: Unresolved | P55: No reporting system identified. | R55: Area affected by Red Sea security incidents; security advisories are outside the scope of this record. | S55: Intermediate | T55: Paired schemes in a security-affected area with no identified coastal VTS. | U55: SRC-054 | V55: Confirm proposing State(s) from MSC 76 report; check for any Yemeni or regional VTS; confirm no amendment since 2003.
A56: TSS-0095 | B56: B19 | C56: C | D56: In the Southern Red Sea - East of Jabal Zuqar Island | E56: In the Southern Red Sea: east of Jabal Zuqar Island | F56: Yemen (Jabal Zuqar; proposing Government not stated in the retrieved circular) | G56: Confirmed | H56: New scheme adopted at MSC 76, COLREG.2/Circ.52 Annex 1, implemented 0000 UTC 1 July 2003. Southbound lane 140° then 166°, northbound 346° then 320°. | I56: In force | K56: Unresolved | M56: No VTS source retrieved. | N56: Unresolved | P56: No reporting system identified. | R56: As TSS-0094. | S56: Intermediate | T56: As TSS-0094. | U56: SRC-054 | V56: As TSS-0094.
A57: TSS-0096 | B57: B20 | C57: D | D57: In the Strait of Bab-el-Mandeb | E57: In the Strait of Bab el Mandeb | F57: Yemen; Djibouti (coastal States by geography; not named in the instruments retrieved) | G57: Confirmed | H57: IMO-adopted by Assembly resolution A.284(VIII) (20 Nov 1973). Amended scheme adopted by MSC 76 and promulgated by COLREG.2/Circ.52, implemented 0000 UTC 1 July 2003 (southbound 155° then 120°, northbound 300° then 335°, turning line off Mayyun Island). Separate from the 'In the Southern Red Sea' TSS adopted in the same circular. | I57: In force | K57: Unresolved | M57: No VTS covering the strait was found in any primary source (Yemen, Djibouti). Searches returned only commentary. | N57: Unresolved | P57: No IMO-adopted mandatory ship reporting system found for Bab el Mandeb. No national mandatory reporting evidenced. | Q57: UKMTO Voluntary Reporting Scheme and MSCIO registration for the Voluntary Reporting Area (VRA); the VRA extent including the Red Sea is a search-snippet lead only (UKMTO site returned HTTP 403). Security reporting, not a navigational VTS. | S57: Intermediate | T57: Multi-State strait, security-affected area with military/security voluntary reporting overlays; no VTS identified. | U57: SRC-086; SRC-054; SRC-091 | V57: Confirm any VTS at Perim/Djibouti; confirm VRA extent from UKMTO/MSCIO primary page (403). Current edition of IMO Ships' Routeing and UKHO ANM Section 17 not retrieved (UKHO download returned HTTP 500), so later amendments or revocations after the cited circular cannot be excluded.
A58: TSS-0097 | B58: B20 | C58: D | D58: Off Ras al Hadd | E58: Off Ras al Hadd | F58: Oman | G58: Confirmed | H58: New scheme adopted by MSC 41; COLREG.2/Circ.12 (19 Nov 1979), effective 15 Feb 1980. Inshore traffic zone redescribed by COLREG.2/Circ.40 (MSC 63), implemented 24 Nov 1994. | I58: In force | K58: Unresolved | M58: No Omani VTS covering the Ras al Hadd TSS found in a primary source. Oman port VTS (e.g. nearby Sur/Qalhat) not evidenced to cover the scheme. | N58: Unresolved | P58: No IMO-adopted mandatory ship reporting system found; no Omani national mandatory reporting evidenced. | Q58: UKMTO daily position reporting, MSCIO VRA registration and IFC-IOR voluntary reporting recommended for vessels in the Gulf of Oman and North Arabian Sea (Liberia MSB 14/2026). | S58: Simple | T58: Single-State coastal TSS with ITZ; no VTS or mandatory reporting identified. | U58: SRC-054; SRC-091 | V58: Oman Ministry of Transport VTS list not found online. Current edition of IMO Ships' Routeing and UKHO ANM Section 17 not retrieved (UKHO download returned HTTP 500), so later amendments or revocations after the cited circular cannot be excluded.
A59: TSS-0098 | B59: B20 | C59: D | D59: Off Ra's al Kuh | E59: Off Ra's al Kuh | F59: Iran (Islamic Republic of) (inferred from positions c. 25°35'-25°47'N 057°03'-057°15'E; State not named in the circular) | G59: Confirmed | H59: New scheme adopted by MSC 78; COLREG.2/Circ.54 (28 May 2004), implemented 0000 UTC 1 December 2004. Two 2-mile lanes, 2-mile separation zone and an associated inshore traffic zone; lanes lead towards the Strait of Hormuz / Gulf of Oman. | I59: In force | K59: Unresolved | M59: No Iranian VTS evidenced as covering this scheme. Bandar Abbas VTS (Iran PMO) is a lead for the Hormuz area only and is not linked to Ra's al Kuh. | N59: Unresolved | P59: No IMO-adopted mandatory reporting system found; no national requirement evidenced. | Q59: UKMTO / MSCIO VRA / IFC-IOR voluntary reporting recommended for the Gulf of Oman (Liberia MSB 14/2026). | S59: Intermediate | T59: Approach to the Strait of Hormuz in a conflict-affected area; State attribution inferred from position. | U59: SRC-054; SRC-091 | V59: Confirm proposing Government from MSC 78 report or Ships' Routeing. Current edition of IMO Ships' Routeing and UKHO ANM Section 17 not retrieved (UKHO download returned HTTP 500), so later amendments or revocations after the cited circular cannot be excluded.
A60: TSS-0099 | B60: B20 | C60: D | D60: In the Strait of Hormuz | E60: In the Strait of Hormuz | F60: Oman; Iran (Islamic Republic of) (proposing States per IMO) | G60: Confirmed | H60: Proposed by Iran and Oman and adopted by IMO in 1968 (IMO page, 2026); included in A.284(VIII) (1973); amended scheme adopted by MSC 40 (IMCO circular dated 7 June 1979); reference chart changed to BA 3172 (WGS 84) by COLREG.2/Circ.33 (25 Feb 1994); inshore traffic zone off Musandam redescribed by COLREG.2/Circ.40 (implemented 24 Nov 1994). 2026 hostilities: IMO page confirms the TSS as 'existing'; press reports of temporary Omani routes north and south of the lanes are leads only and were not verified from an Omani Notice to Mariners. | I60: In force | K60: Unresolved | L60: VTS-039 | M60: No primary source establishing a VTS covering the IMO Hormuz TSS. Lead: search snippet (puertos.es document, HTTP 403) says Bandar Abbas VTC requires contact on VHF 13 before entering local 'TSS (area A/B)' between Larak, Hormuz and Qeshm, which appear to be port-approach lanes rather than the IMO scheme. Omani radar monitoring from Musandam is a press lead only. | N60: Unresolved | P60: No IMO-adopted mandatory ship reporting system for the Strait of Hormuz found. Flag-State guidance recommends voluntary security reporting only. | Q60: UKMTO daily reporting, MSCIO VRA registration and IFC-IOR voluntary reporting for vessels transiting the Strait of Hormuz (Liberia MSB 14/2026); IMO page also points to UKMTO, JMIC and MSCIO advisories and Oman NAVAREA IX notices. | R60: Conflict-affected (2026); security level 3 advised by at least one flag State for Liberian ships. Recorded neutrally. | S60: Complex | T60: Two-State strait, conflict-affected, temporary routeing reports, layered security reporting, possible Iranian port VTS overlap. | U60: SRC-088; SRC-086; SRC-054; SRC-091 | V60: Obtain Oman NAVAREA IX notices on temporary routes and any Omani/Iranian VTS covering the TSS; puertos.es document on Bandar Abbas VTS blocked (403). Current edition of IMO Ships' Routeing and UKHO ANM Section 17 not retrieved (UKHO download returned HTTP 500), so later amendments or revocations after the cited circular cannot be excluded.
A61: TSS-0100 | B61: B20 | C61: D | D61: Tunb-Farur | E61: Tunb-Farur | F61: Iran (Islamic Republic of) and adjacent waters; lanes pass either side of Jaz-Tunb and Jaz-Farur (sovereignty over the Tunb islands is disputed between Iran and the United Arab Emirates; recorded neutrally) | G61: Provisional | H61: Adopted by Assembly resolution A.284(VIII) (20 Nov 1973): separate westbound (258°/278°) and eastbound (098°/078°) lanes, linking to the Strait of Hormuz scheme. No later amendment or revocation found in the COLREG.2 circular compilation, but current status not verified in the current Ships' Routeing. | I61: In force | J61: Westbound traffic lane (north of Jaz-Tunb/Jaz-Farur); Eastbound traffic lane (south of the islands) | K61: Unresolved | M61: No VTS evidenced as covering the scheme. | N61: Unresolved | P61: No IMO-adopted mandatory reporting found; none evidenced nationally. | Q61: UKMTO / MSCIO / IFC-IOR voluntary reporting for vessels in the Arabian Gulf (Liberia MSB 14/2026). | S61: Intermediate | T61: Lanes split around disputed islands in a conflict-affected area; identity rests on a 1973 instrument. | U61: SRC-086; SRC-091 | V61: Confirm current status (Ships' Routeing Part B). Current edition of IMO Ships' Routeing and UKHO ANM Section 17 not retrieved (UKHO download returned HTTP 500), so later amendments or revocations after the cited circular cannot be excluded.
A62: TSS-0101 | B62: B21 | C62: D | D62: Between Zaqqum and Umm Shaif | E62: Between Zaqqum and Umm Shaif oilfields | F62: United Arab Emirates (Abu Dhabi) | G62: Confirmed | H62: New scheme adopted by MSC 46; COLREG.2/Circ.15 (6 April 1982); effective not before 31 Dec 1982 and on notification by the Government concerned. ADNOC Port Marine Notice DZM/MN/019/2023 (14 Mar 2023) refers to the 'Zaqqum Traffic Separation Scheme', indicating it remains in use. | I62: In force | K62: Unresolved | L62: VTS-038 | M62: ADNOC Harbour Master (Port of Das, Zirku & Mubarraz) notice on traffic within the Zaqqum TSS instructs vessels to maintain a listening watch on VHF 23 (Das VTIS) and to inform Das VTIS. Notice is temporary (2023 pipe-laying) so full VTS area limits are not stated. | N62: Unresolved | P62: No IMO-adopted or national mandatory reporting system evidenced for the scheme; Das VTIS reporting duties are within the VTS, not a separate system. | Q62: UKMTO / MSCIO / IFC-IOR voluntary security reporting for the Arabian Gulf (Liberia MSB 14/2026). | S62: Intermediate | T62: Offshore oilfield TSS with terminal-operator VTIS; coverage evidenced only via a temporary notice. | U62: SRC-054; SRC-089; SRC-091 | V62: Obtain a standing ADNOC PPA document describing the Das VTIS area; confirm UAE notification date of implementation. Current edition of IMO Ships' Routeing and UKHO ANM Section 17 not retrieved (UKHO download returned HTTP 500), so later amendments or revocations after the cited circular cannot be excluded. | W62: vts_finding: Confirmed present -> Unresolved. Only evidence is a temporary 2023 ADNOC notice that does not state the Das VTIS area; not sufficient for current coverage. Das VTIS retained as a lead.
A63: TSS-0102 | B63: B21 | C63: D | D63: In the Approaches to Ras Tanura and Ju'aymah | E63: In the approaches to Ras Tanura and Ju'aymah | F63: Saudi Arabia | G63: Confirmed | H63: 'In the approach to Ras Tanura' in A.284(VIII) (1973); amended and renamed 'In the approaches to Ras Tanura and Ju'aymah (as amended)' by A.338(IX) (12 Nov 1975), in three parts. Later amendments not checked. | I63: In force | J63: Part I: Ras Tanura Approach; Part II: Ju'aymah Approach; Part III: Ju'aymah Departure | K63: Unresolved | L63: VTS-040 | M63: Lead only: Saudi Aramco Ports and Terminals documents (search snippets) mention Ras Tanura Port Control on VHF 10/16 and a Vessel Traffic Management System at Ju'aymah, but every Aramco PDF returned 404/403 so coverage of the TSS could not be verified. | N63: Unresolved | P63: No IMO-adopted mandatory reporting system found; port reporting requirements not verified. | Q63: UKMTO / MSCIO / IFC-IOR voluntary security reporting for the Arabian Gulf (Liberia MSB 14/2026). | S63: Intermediate | T63: Grouped three-part scheme serving oil terminals with an operator-run port control/VTMS lead. | U63: SRC-086; SRC-087; SRC-091 | V63: Aramco 'Port of Ras Tanura' and Ju'aymah terminal PDFs would not load (404/403, HTTP/2 errors). Current edition of IMO Ships' Routeing and UKHO ANM Section 17 not retrieved (UKHO download returned HTTP 500), so later amendments or revocations after the cited circular cannot be excluded.
A64: TSS-0103 | B64: B21 | C64: D | D64: Marjan/Zuluf | E64: Marjan/Zuluf (originally 'Between the Zuluf and Marjan oil fields') | F64: Saudi Arabia (by location; not named in circulars) | G64: Confirmed | H64: New scheme adopted by MSC 59; COLREG.2/Circ.37 (19 June 1991), implemented 16 Nov 1991. Amended by MSC 70; COLREG.2/Circ.45 (8 Jan 1999), implemented 1 July 1999, superseding COLREG.2/Circ.43 (10 Feb 1997). Renamed 'Marjan/Zuluf (amended scheme)'. | I64: In force | K64: Unresolved | M64: No VTS evidenced as covering the scheme; Saudi Aramco documents could not be retrieved. | N64: Unresolved | P64: No IMO-adopted or national mandatory reporting evidenced. | Q64: UKMTO / MSCIO / IFC-IOR voluntary security reporting for the Arabian Gulf (Liberia MSB 14/2026). | S64: Simple | T64: Single-State offshore oilfield TSS; no VTS or reporting identified. | U64: SRC-054; SRC-091 | V64: Current edition of IMO Ships' Routeing and UKHO ANM Section 17 not retrieved (UKHO download returned HTTP 500), so later amendments or revocations after the cited circular cannot be excluded.
A65: TSS-0104 | B65: B21 | C65: D | D65: Approaches to the Port of Ra's al Khafji | E65: Approaches to the Port of Ra's al Khafji | F65: Saudi Arabia (Government of Saudi Arabia notified IMO) | G65: Confirmed | H65: New scheme adopted by MSC 78; COLREG.2/Circ.54 (28 May 2004), planned 1 Dec 2004; implementation postponed to 1 June 2005 by COLREG.2/Circ.54/Add.1 (13 Sep 2004, note by Saudi Arabia). | I65: In force | K65: Unresolved | M65: No VTS evidenced (Al-Khafji Joint Operations port control not found in a primary source). | N65: Unresolved | P65: No IMO-adopted or national mandatory reporting evidenced. | Q65: UKMTO / MSCIO / IFC-IOR voluntary security reporting for the Arabian Gulf (Liberia MSB 14/2026). | S65: Simple | T65: Single port approach TSS; no VTS or reporting identified. | U65: SRC-054; SRC-085; SRC-091 | V65: Khafji lies near the former Saudi-Kuwaiti Divided/Neutral Zone; operator arrangements not checked. Current edition of IMO Ships' Routeing and UKHO ANM Section 17 not retrieved (UKHO download returned HTTP 500), so later amendments or revocations after the cited circular cannot be excluded.
A66: TSS-0105 | B66: B21 | C66: D | D66: Off Mina'Al Ahmadi | E66: Off Mina Al-Ahmadi | F66: Kuwait (by location; not named in circular) | G66: Confirmed | H66: New scheme adopted by MSC 79; COLREG.2/Circ.55 (15 Dec 2004), implemented 0000 UTC 1 July 2005. The adopted measure comprises three schemes (North Scheme I, North Scheme II, The South Scheme); annex notes the Mina Al-Ahmadi deep departure channel remains in use. | I66: In force | J66: North Scheme I; North Scheme II; The South Scheme | K66: Unresolved | M66: No VTS evidenced; port information sites (lead only) say marine operations are run by the Kuwait Oil Company harbour master, without VTS coverage details. | N66: Unresolved | P66: No IMO-adopted or national mandatory reporting evidenced. | Q66: UKMTO / MSCIO / IFC-IOR voluntary security reporting for the Arabian Gulf (Liberia MSB 14/2026). | S66: Intermediate | T66: Grouped label covering three schemes serving an oil port; VTS status unknown. | U66: SRC-054; SRC-091 | V66: Kuwait Ports Authority / KOC port regulations not found online. Current edition of IMO Ships' Routeing and UKHO ANM Section 17 not retrieved (UKHO download returned HTTP 500), so later amendments or revocations after the cited circular cannot be excluded.
A67: TSS-0106 | B67: B22 | C67: D | D67: Off Dondra Head | E67: Off Dondra Head (TSS south of Dondra Head) | F67: Sri Lanka | G67: Provisional | H67: MEPC 80/16/3 (28 Apr 2023) states the existing TSS south of Dondra Head is in Ships' Routeing Section IV and was established in 1980; adoption instrument (IMO circular/resolution) not retrieved. 2023 industry/IWC proposal to move the TSS about 15 nm south was opposed by Sri Lanka (press leads); no change evidenced. | I67: In force | K67: Unresolved | M67: No VTS covering the TSS found. Sri Lanka Ports Authority VTMS at Colombo (supplier press releases, lead only) is a port system and not evidenced to cover Dondra Head. | N67: Unresolved | P67: No IMO-adopted or national mandatory reporting system evidenced. | S67: Simple | T67: Single-State coastal TSS; no VTS or reporting identified; environmental review pressure noted. | U67: SRC-090 | V67: Retrieve the 1980 adoption instrument and any Sri Lanka Merchant Shipping Secretariat notice. Current edition of IMO Ships' Routeing and UKHO ANM Section 17 not retrieved (UKHO download returned HTTP 500), so later amendments or revocations after the cited circular cannot be excluded.
A68: TSS-0107 | B68: B22 | C68: D | D68: At One Fathom Bank | E68: At One Fathom Bank (with precautionary area 'Off Port Klang') | F68: Malaysia (Straits of Malacca; system proposed by Indonesia, Malaysia and Singapore) | G68: Confirmed | H68: Amended scheme adopted by MSC 69 (May 1998); COLREG.2/Circ.44 annex 1, implemented 0000 UTC 1 Dec 1998, with precautionary area 'Off Port Klang'. Segment of the Malacca-Singapore routeing system. | I68: In force | K68: Confirmed present | L68: VTS-004 | M68: Scheme spans c. 03°02'.7N to 02°41'N (Circ.44). On the STRAITREP chartlet the Sector 1 (Angsa)/Sector 2 (Jugra) boundary runs at about 02°52'N towards Port Klang, so the scheme lies in Sectors 1 and 2, both 'Klang VTS' (MSC.73(69) para 3.4); VHF 66 (Sector 1) and 88 (Sector 2). | N68: Confirmed present | O68: SRS-004 | P68: STRAITREP (MSC.73(69), in force 1 Dec 1998) applies throughout the operational area, which 'includes the routeing system in the Straits of Malacca and Singapore'; reports to the VTS authority for the sector. Sectors 1-2: Klang VTS. | R68: STRAITREP participants: ships of 300 GT and above; 50 m or more in length; towing/pushing combinations of 300 GT or 50 m; any tonnage carrying hazardous cargo; all VHF-fitted passenger vessels; smaller VHF-fitted vessels using the lanes in an emergency (MSC.73(69) Annex 1 para 1.1). | S68: Intermediate | T68: One VTS but two STRAITREP sectors/channels; part of a multi-State routeing and reporting system. | U68: SRC-054; SRC-083; SRC-007; SRC-084 | V68: Sector boundaries are published only as chartlets (MSC.73(69) appendices 1-2); allocation is by visual interpretation of the MPA 2026 chartlet against Circ.44 coordinates, not by stated boundary coordinates. Later amendments to the Malacca schemes after 1998 not checked. Operating authority of Klang and Johor VTS (Marine Department Malaysia) not stated in fetched sources; Malaysian sources not retrieved.
